Workbook

Sheet Readme
A1: Language Coherence Model — Subjects, Concepts and Connectors tables (v0.3)
A2: First pass generated by build_tables.py. The weights are design decisions (blue) and can be edited.
A4: 1. The four axes
A5: Pole | B5: Label | C5: Pronoun | D5: Character | E5: Weight | F5: What goes there
A6: Up | B6: Context | C6: We | D6: Possibility | E6: V | F6: viable, open, possible, alive, future, good
A7: Down | B7: World | C7: That | D7: logical | E7: I | F7: dangerous, sad, closed, inert, past, negation
A8: Right | B8: Imposition | C8: I | D8: Sensory | E8: Lv | F8: raw perception, concrete, body, physical action
A9: Left | B9: Adaptation | C9: You | D9: structural | E9: Gv | F9: relation, judgment, standard, language, the social
A11: 2. Scale and position
A12: Each node has 4 independent weights, integers from 0 to 10 (0 = no weight). Happiness, for example, weighs in V, Lv and Gv and nothing in I.
A13: x = (Lv − Gv) / 2 → x > 0 toward Imposition, x < 0 toward Adaptation. y = (V − I) / 2 → y > 0 toward Context, y < 0 toward World.
A14: Cell (10 × 10): column = ROUNDUP(x + 5), row = ROUNDUP(5 − y), clipped to 1..10. Row 1 = Context, row 10 = World; column 1 = Adaptation, column 10 = Imposition.
A15: ⚠ With even N there is no central cell: x = 0 falls in column 5 and y = 0 in row 5 (Adaptation / Context side). It is a provisional rule.
A16: τ (tension) = MIN(V, I): separates the ambivalent from the neutral, which the centroid collapses to the same point.
A18: 3. How weights are assigned (inheritance down the tree)
A19: type (biological / non_biological / action / quality) → category → subtype: each level ADDS an adjustment. See the Weight_rules sheet.
A20: Valence: SentiWordNet. V += round(6 × positivity), I += round(6 × negativity). They are independent of each other.
A21: Per-axis lists from Unique Host: sensory adjectives → Imposition, judgment or relation → Adaptation (the hand-written list takes precedence over the generated one).
A22: Hand-made concepts: intrinsic danger, intrinsic emotion and state type adjust V/I/Lv/Gv; they take precedence over the first WordNet sense (ghost = illogical).
A23: People and animals: separated by their WordNet lineage (threat, imposes itself, close bond, cares or teaches; domestic, predator).
... A26: 4. What each table contains
A27: Table | B27: Nodes | C27: Contents
A28: Subjects | B28: =COUNTA(Subjects_nodes!A2:A1392) -> 1391 | C28: biological lexicon (people, animals, plants, body, groups) + subject concepts + pronouns
A29: Concepts | B29: =COUNTA(Concepts_nodes!A2:A7677) -> 7676 | C29: non_biological, action and quality lexicon + hand-made concepts (state, illusory, environment, tone, music)
A30: Connectors | B30: =COUNTA(Connectors_nodes!A2:A197) -> 196 | C30: conjunctions, connective adverbs, transition phrases and punctuation
A32: 5. Connectors: time runs vertically
A33: North = future, possibility, condition, purpose and 'we/us' (join, include). South = past, negation, closure, result, exception.
A34: East–West = present: the horizontal band (V = I, y ≈ 0). West = structure (joins, compares, explains); East = the speaker imposes (emphasis, stance).
A35: Each relation in the document has a base weight (Weight_rules sheet). If a word has two roles, they are two nodes: 'so (result)' and 'so that'; 'though (concessive)' and 'though (sentence-initial)'.
A36: The 'Compare' column of Connectors_nodes contrasts the proposed axis with the one of the Unique Host construction.
A38: 6. What is NOT there (limits of this pass)
A39: • The 7 concepts of type 'language' (who, which, where…) were left out of Subjects and Concepts: relatives and interrogatives now live in Connectors.
A40: • 261 concepts that are inflections of another word are not separate nodes.
A41: • 'he, she, they, him, her, this, these' are not in any Unique Host pronoun list and were not placed.
A42: • Links (v0.4): 'Related (nodes)' comes from the 597 hand-made concepts; 'Related (WordNet)' is derived from WordNet (is-a, kind-of, part, derived, similar, definition); 'Related (manual)' is a hand-written narrative seed (tools/related_manual.py); 'Opposites' are WordNet antonyms. State labels (hostile, defenseless…) are listed separately because they are not nodes.
A43: • People are still concentrated: the tree has almost no words in its person leaves (237 in total, no sub-leaves).
A44: • SentiWordNet valence is noisy for nouns; the extremes (rows 1 and 10) should be reviewed by hand.
A45: • Only base forms of verbs exist: tense (past = World, future = Context) does not yet move the weight of an action.

Sheet Subjects
A1: Table of Subjects (10 × 10)
A2: Each cell shows how many words it has and the first ones (hand-made concepts first). Full list in the sheet Subjects_nodes. Position: x = (Lv − Gv)/2, y = (V − I)/2.
C4: ◄ Adaptation (You, structural) | H4: Imposition (I, Sensory) ►
C5: 1 | D5: 2 | E5: 3 | F5: 4 | G5: 5 | H5: 6 | I5: 7 | J5: 8 | K5: 9 | L5: 10
A6: Context (We, Possibility) ▲ | B6: 1 | C6: 91 children, members, child, kids, son, baby … +85 | D6: 2 father, mother | E6: 10 santa, researchers, masters, fool, researcher, fools … +4 | G6: 5 we, us, our, ours, ourselves | H6: 2 duke, archbishop
B7: 2 | C7: 116 author, doctor, professor, teacher, artist, teachers … +110 | E7: 498 man, god, women, men, friends, guys … +492 | F7: 4 person, angelo, saint, saints | G7: 3 flowers, flower, bud | H7: 153 president, players, player, king, director, minister … +147 | I7: 1 hero
B8: 3 | C8: 4 you, your, yours, yourself | D8: 3 dog, dogs, puppy | E8: 183 he, she, they, him, her, his … +177 | F8: 20 fish, bird, pet, character, michael, characters … +14 | G8: 51 tree, trees, fruit, bush, root, alexander … +45 | H8: 7 cops, cop, administrator, loser, administrators, losers … +1 | K8: 4 hand, eye, ear, ears | L8: 5 i, me, my, mine, myself
B9: 4 | D9: 9 victim, victims, prisoners, prisoner, survivors, survivor … +3 | E9: 21 bull, mouse, pig, mice, insects, pigs … +15 | F9: 4 animals, animal, hydra, phantom | G9: 2 cole, sneak | I9: 2 brain, brains | J9: 13 body, bodies, gene, flesh, genes, sweat … +7 | K9: 59 head, hair, ass, feet, skin, foot … +53 | L9: 1 face
B10: 5 | D10: 3 patients, patient, casualties | E10: 5 hunt, mercenary, zombie, stalker, cultist | F10: 11 cat, fox, cats, lion, eagles, lions … +5 | G10: 11 blades, punk, runner, highwayman, swindler, cutthroat … +5 | H10: 2 bandit, warlord | I10: 19 bone, muscle, stomach, tissue, vessel, vessels … +13
B11: 6 | D11: 2 vagrant, invalid | E11: 10 killer, spider, burns, widow, killers, enemies … +4 | F11: 8 monster, monsters, goblin, troll, vampire, werewolf … +2 | G11: 11 stranger, ted, hood, criminals, strangers, rogue … +5 | H11: 2 villain, tyrant
B12: 7 | E12: 7 dragon, snake, sharks, snakes, shark, beast … +1 | F12: 1 dragons | G12: 1 liar | J12: 1 blood | K12: 2 fang, claw
B13: 8 | F13: 2 wolf, wolves | G13: 12 thief, assassin, raider, pirate, pirates, raiders … +6
B14: 9 | G14: 2 outlaw, ogre | J14: 2 this, these
A15: World (That, logical) ▼ | B15: 10 | G15: 4 that, it, those, itself
A18: Count per cell (COUNTIFS formulas over Subjects_nodes)
C19: 1 | D19: 2 | E19: 3 | F19: 4 | G19: 5 | H19: 6 | I19: 7 | J19: 8 | K19: 9 | L19: 10
B20: 1 | C20: =COUNTIFS(Subjects_nodes!$K$2:$K$1392,C$19,Subjects_nodes!$L$2:$L$1392,$B20) -> 91 | D20: =COUNTIFS(Subjects_nodes!$K$2:$K$1392,D$19,Subjects_nodes!$L$2:$L$1392,$B20) -> 2 | E20: =COUNTIFS(Subjects_nodes!$K$2:$K$1392,E$19,Subjects_nodes!$L$2:$L$1392,$B20) -> 10 | F20: =COUNTIFS(Subjects_nodes!$K$2:$K$1392,F$19,Subjects_nodes!$L$2:$L$1392,$B20) -> 0 | G20: =COUNTIFS(Subjects_nodes!$K$2:$K$1392,G$19,Subjects_nodes!$L$2:$L$1392,$B20) -> 5 | H20: =COUNTIFS(Subjects_nodes!$K$2:$K$1392,H$19,Subjects_nodes!$L$2:$L$1392,$B20) -> 2 | I20: =COUNTIFS(Subjects_nodes!$K$2:$K$1392,I$19,Subjects_nodes!$L$2:$L$1392,$B20) -> 0 | J20: =COUNTIFS(Subjects_nodes!$K$2:$K$1392,J$19,Subjects_nodes!$L$2:$L$1392,$B20) -> 0 | ... L20: =COUNTIFS(Subjects_nodes!$K$2:$K$1392,L$19,Subjects_nodes!$L$2:$L$1392,$B20) -> 0
B21: 2 | C21: =COUNTIFS(Subjects_nodes!$K$2:$K$1392,C$19,Subjects_nodes!$L$2:$L$1392,$B21) -> 116 | D21: =COUNTIFS(Subjects_nodes!$K$2:$K$1392,D$19,Subjects_nodes!$L$2:$L$1392,$B21) -> 0 | E21: =COUNTIFS(Subjects_nodes!$K$2:$K$1392,E$19,Subjects_nodes!$L$2:$L$1392,$B21) -> 498 | F21: =COUNTIFS(Subjects_nodes!$K$2:$K$1392,F$19,Subjects_nodes!$L$2:$L$1392,$B21) -> 4 | G21: =COUNTIFS(Subjects_nodes!$K$2:$K$1392,G$19,Subjects_nodes!$L$2:$L$1392,$B21) -> 3 | H21: =COUNTIFS(Subjects_nodes!$K$2:$K$1392,H$19,Subjects_nodes!$L$2:$L$1392,$B21) -> 153 | I21: =COUNTIFS(Subjects_nodes!$K$2:$K$1392,I$19,Subjects_nodes!$L$2:$L$1392,$B21) -> 1 | J21: =COUNTIFS(Subjects_nodes!$K$2:$K$1392,J$19,Subjects_nodes!$L$2:$L$1392,$B21) -> 0 | ... L21: =COUNTIFS(Subjects_nodes!$K$2:$K$1392,L$19,Subjects_nodes!$L$2:$L$1392,$B21) -> 0
B22: 3 | C22: =COUNTIFS(Subjects_nodes!$K$2:$K$1392,C$19,Subjects_nodes!$L$2:$L$1392,$B22) -> 4 | D22: =COUNTIFS(Subjects_nodes!$K$2:$K$1392,D$19,Subjects_nodes!$L$2:$L$1392,$B22) -> 3 | E22: =COUNTIFS(Subjects_nodes!$K$2:$K$1392,E$19,Subjects_nodes!$L$2:$L$1392,$B22) -> 183 | F22: =COUNTIFS(Subjects_nodes!$K$2:$K$1392,F$19,Subjects_nodes!$L$2:$L$1392,$B22) -> 20 | G22: =COUNTIFS(Subjects_nodes!$K$2:$K$1392,G$19,Subjects_nodes!$L$2:$L$1392,$B22) -> 51 | H22: =COUNTIFS(Subjects_nodes!$K$2:$K$1392,H$19,Subjects_nodes!$L$2:$L$1392,$B22) -> 7 | I22: =COUNTIFS(Subjects_nodes!$K$2:$K$1392,I$19,Subjects_nodes!$L$2:$L$1392,$B22) -> 0 | J22: =COUNTIFS(Subjects_nodes!$K$2:$K$1392,J$19,Subjects_nodes!$L$2:$L$1392,$B22) -> 0 | ... L22: =COUNTIFS(Subjects_nodes!$K$2:$K$1392,L$19,Subjects_nodes!$L$2:$L$1392,$B22) -> 5
B23: 4 | C23: =COUNTIFS(Subjects_nodes!$K$2:$K$1392,C$19,Subjects_nodes!$L$2:$L$1392,$B23) -> 0 | D23: =COUNTIFS(Subjects_nodes!$K$2:$K$1392,D$19,Subjects_nodes!$L$2:$L$1392,$B23) -> 9 | E23: =COUNTIFS(Subjects_nodes!$K$2:$K$1392,E$19,Subjects_nodes!$L$2:$L$1392,$B23) -> 21 | F23: =COUNTIFS(Subjects_nodes!$K$2:$K$1392,F$19,Subjects_nodes!$L$2:$L$1392,$B23) -> 4 | G23: =COUNTIFS(Subjects_nodes!$K$2:$K$1392,G$19,Subjects_nodes!$L$2:$L$1392,$B23) -> 2 | H23: =COUNTIFS(Subjects_nodes!$K$2:$K$1392,H$19,Subjects_nodes!$L$2:$L$1392,$B23) -> 0 | I23: =COUNTIFS(Subjects_nodes!$K$2:$K$1392,I$19,Subjects_nodes!$L$2:$L$1392,$B23) -> 2 | J23: =COUNTIFS(Subjects_nodes!$K$2:$K$1392,J$19,Subjects_nodes!$L$2:$L$1392,$B23) -> 13 | ... L23: =COUNTIFS(Subjects_nodes!$K$2:$K$1392,L$19,Subjects_nodes!$L$2:$L$1392,$B23) -> 1
B24: 5 | C24: =COUNTIFS(Subjects_nodes!$K$2:$K$1392,C$19,Subjects_nodes!$L$2:$L$1392,$B24) -> 0 | D24: =COUNTIFS(Subjects_nodes!$K$2:$K$1392,D$19,Subjects_nodes!$L$2:$L$1392,$B24) -> 3 | E24: =COUNTIFS(Subjects_nodes!$K$2:$K$1392,E$19,Subjects_nodes!$L$2:$L$1392,$B24) -> 5 | F24: =COUNTIFS(Subjects_nodes!$K$2:$K$1392,F$19,Subjects_nodes!$L$2:$L$1392,$B24) -> 11 | G24: =COUNTIFS(Subjects_nodes!$K$2:$K$1392,G$19,Subjects_nodes!$L$2:$L$1392,$B24) -> 11 | H24: =COUNTIFS(Subjects_nodes!$K$2:$K$1392,H$19,Subjects_nodes!$L$2:$L$1392,$B24) -> 2 | I24: =COUNTIFS(Subjects_nodes!$K$2:$K$1392,I$19,Subjects_nodes!$L$2:$L$1392,$B24) -> 19 | J24: =COUNTIFS(Subjects_nodes!$K$2:$K$1392,J$19,Subjects_nodes!$L$2:$L$1392,$B24) -> 0 | ... L24: =COUNTIFS(Subjects_nodes!$K$2:$K$1392,L$19,Subjects_nodes!$L$2:$L$1392,$B24) -> 0
B25: 6 | C25: =COUNTIFS(Subjects_nodes!$K$2:$K$1392,C$19,Subjects_nodes!$L$2:$L$1392,$B25) -> 0 | D25: =COUNTIFS(Subjects_nodes!$K$2:$K$1392,D$19,Subjects_nodes!$L$2:$L$1392,$B25) -> 2 | E25: =COUNTIFS(Subjects_nodes!$K$2:$K$1392,E$19,Subjects_nodes!$L$2:$L$1392,$B25) -> 10 | F25: =COUNTIFS(Subjects_nodes!$K$2:$K$1392,F$19,Subjects_nodes!$L$2:$L$1392,$B25) -> 8 | G25: =COUNTIFS(Subjects_nodes!$K$2:$K$1392,G$19,Subjects_nodes!$L$2:$L$1392,$B25) -> 11 | H25: =COUNTIFS(Subjects_nodes!$K$2:$K$1392,H$19,Subjects_nodes!$L$2:$L$1392,$B25) -> 2 | I25: =COUNTIFS(Subjects_nodes!$K$2:$K$1392,I$19,Subjects_nodes!$L$2:$L$1392,$B25) -> 0 | J25: =COUNTIFS(Subjects_nodes!$K$2:$K$1392,J$19,Subjects_nodes!$L$2:$L$1392,$B25) -> 0 | ... L25: =COUNTIFS(Subjects_nodes!$K$2:$K$1392,L$19,Subjects_nodes!$L$2:$L$1392,$B25) -> 0
B26: 7 | C26: =COUNTIFS(Subjects_nodes!$K$2:$K$1392,C$19,Subjects_nodes!$L$2:$L$1392,$B26) -> 0 | D26: =COUNTIFS(Subjects_nodes!$K$2:$K$1392,D$19,Subjects_nodes!$L$2:$L$1392,$B26) -> 0 | E26: =COUNTIFS(Subjects_nodes!$K$2:$K$1392,E$19,Subjects_nodes!$L$2:$L$1392,$B26) -> 7 | F26: =COUNTIFS(Subjects_nodes!$K$2:$K$1392,F$19,Subjects_nodes!$L$2:$L$1392,$B26) -> 1 | G26: =COUNTIFS(Subjects_nodes!$K$2:$K$1392,G$19,Subjects_nodes!$L$2:$L$1392,$B26) -> 1 | H26: =COUNTIFS(Subjects_nodes!$K$2:$K$1392,H$19,Subjects_nodes!$L$2:$L$1392,$B26) -> 0 | I26: =COUNTIFS(Subjects_nodes!$K$2:$K$1392,I$19,Subjects_nodes!$L$2:$L$1392,$B26) -> 0 | J26: =COUNTIFS(Subjects_nodes!$K$2:$K$1392,J$19,Subjects_nodes!$L$2:$L$1392,$B26) -> 1 | ... L26: =COUNTIFS(Subjects_nodes!$K$2:$K$1392,L$19,Subjects_nodes!$L$2:$L$1392,$B26) -> 0
B27: 8 | C27: =COUNTIFS(Subjects_nodes!$K$2:$K$1392,C$19,Subjects_nodes!$L$2:$L$1392,$B27) -> 0 | D27: =COUNTIFS(Subjects_nodes!$K$2:$K$1392,D$19,Subjects_nodes!$L$2:$L$1392,$B27) -> 0 | E27: =COUNTIFS(Subjects_nodes!$K$2:$K$1392,E$19,Subjects_nodes!$L$2:$L$1392,$B27) -> 0 | F27: =COUNTIFS(Subjects_nodes!$K$2:$K$1392,F$19,Subjects_nodes!$L$2:$L$1392,$B27) -> 2 | G27: =COUNTIFS(Subjects_nodes!$K$2:$K$1392,G$19,Subjects_nodes!$L$2:$L$1392,$B27) -> 12 | H27: =COUNTIFS(Subjects_nodes!$K$2:$K$1392,H$19,Subjects_nodes!$L$2:$L$1392,$B27) -> 0 | I27: =COUNTIFS(Subjects_nodes!$K$2:$K$1392,I$19,Subjects_nodes!$L$2:$L$1392,$B27) -> 0 | J27: =COUNTIFS(Subjects_nodes!$K$2:$K$1392,J$19,Subjects_nodes!$L$2:$L$1392,$B27) -> 0 | ... L27: =COUNTIFS(Subjects_nodes!$K$2:$K$1392,L$19,Subjects_nodes!$L$2:$L$1392,$B27) -> 0
B28: 9 | C28: =COUNTIFS(Subjects_nodes!$K$2:$K$1392,C$19,Subjects_nodes!$L$2:$L$1392,$B28) -> 0 | D28: =COUNTIFS(Subjects_nodes!$K$2:$K$1392,D$19,Subjects_nodes!$L$2:$L$1392,$B28) -> 0 | E28: =COUNTIFS(Subjects_nodes!$K$2:$K$1392,E$19,Subjects_nodes!$L$2:$L$1392,$B28) -> 0 | F28: =COUNTIFS(Subjects_nodes!$K$2:$K$1392,F$19,Subjects_nodes!$L$2:$L$1392,$B28) -> 0 | G28: =COUNTIFS(Subjects_nodes!$K$2:$K$1392,G$19,Subjects_nodes!$L$2:$L$1392,$B28) -> 2 | H28: =COUNTIFS(Subjects_nodes!$K$2:$K$1392,H$19,Subjects_nodes!$L$2:$L$1392,$B28) -> 0 | I28: =COUNTIFS(Subjects_nodes!$K$2:$K$1392,I$19,Subjects_nodes!$L$2:$L$1392,$B28) -> 0 | J28: =COUNTIFS(Subjects_nodes!$K$2:$K$1392,J$19,Subjects_nodes!$L$2:$L$1392,$B28) -> 2 | ... L28: =COUNTIFS(Subjects_nodes!$K$2:$K$1392,L$19,Subjects_nodes!$L$2:$L$1392,$B28) -> 0
B29: 10 | C29: =COUNTIFS(Subjects_nodes!$K$2:$K$1392,C$19,Subjects_nodes!$L$2:$L$1392,$B29) -> 0 | D29: =COUNTIFS(Subjects_nodes!$K$2:$K$1392,D$19,Subjects_nodes!$L$2:$L$1392,$B29) -> 0 | E29: =COUNTIFS(Subjects_nodes!$K$2:$K$1392,E$19,Subjects_nodes!$L$2:$L$1392,$B29) -> 0 | F29: =COUNTIFS(Subjects_nodes!$K$2:$K$1392,F$19,Subjects_nodes!$L$2:$L$1392,$B29) -> 0 | G29: =COUNTIFS(Subjects_nodes!$K$2:$K$1392,G$19,Subjects_nodes!$L$2:$L$1392,$B29) -> 4 | H29: =COUNTIFS(Subjects_nodes!$K$2:$K$1392,H$19,Subjects_nodes!$L$2:$L$1392,$B29) -> 0 | I29: =COUNTIFS(Subjects_nodes!$K$2:$K$1392,I$19,Subjects_nodes!$L$2:$L$1392,$B29) -> 0 | J29: =COUNTIFS(Subjects_nodes!$K$2:$K$1392,J$19,Subjects_nodes!$L$2:$L$1392,$B29) -> 0 | ... L29: =COUNTIFS(Subjects_nodes!$K$2:$K$1392,L$19,Subjects_nodes!$L$2:$L$1392,$B29) -> 0
B30: Total | C30: =SUM(C20:L29) -> 1391 | D30: nodes in the sheet: | E30: =COUNTA(Subjects_nodes!A2:A1392) -> 1391 | F30: =IF(C30=E30,"✔ matches","✖ does not match") -> ✔ matches

Sheet Concepts
A1: Table of Concepts (10 × 10)
A2: Each cell shows how many words it has and the first ones (hand-made concepts first). Full list in the sheet Concepts_nodes. Position: x = (Lv − Gv)/2, y = (V − I)/2.
C4: ◄ Adaptation (You, structural) | H4: Imposition (I, Sensory) ►
C5: 1 | D5: 2 | E5: 3 | F5: 4 | G5: 5 | H5: 6 | I5: 7 | J5: 8 | K5: 9 | L5: 10
A6: Context (We, Possibility) ▲ | B6: 1 | C6: 1 excellent | E6: 1 dream | J6: 3 passion, favour, desired | K6: 2 hope, ambition
B7: 2 | C7: 25 best, better, nice, beautiful, perfect, successful … +19 | D7: 16 important, happy, smart, healthy, correct, intellectual … +10 | E7: 10 plan, goal, joke, vision, intention, jokes … +4 | G7: 2 sexy, enthusiastic | H7: 6 captured, capture, renewed, decorated, fulfill, copied | I7: 8 enjoy, loved, loves, enjoyed, loving, enjoying … +2 | J7: 14 desire, pleasure, joy, emotions, emotion, preference … +8 | K7: 1 pride
B8: 3 | C8: 63 different, fine, amazing, interesting, welcome, grand … +57 | D8: 80 clear, worth, financial, fair, significant, rich … +74 | E8: 166 music, eyes, truth, respect, method, taste … +160 | F8: 70 goods, popularity, asset, goodness, reliability, try … +64 | G8: 8 aware, proud, alive, emotional, alert, eager … +2 | H8: 81 opportunity, written, built, published, writing, created … +75 | I8: 16 project, courtesy, interested, liked, likes, prefer … +10 | J8: 119 love, relief, excitement, satisfaction, gratitude, attachment … +113 | K8: 8 hopes, ego, wonders, awe, hoping, hoped … +2
B9: 4 | C9: 103 same, public, available, similar, private, super … +97 | D9: 343 new, high, sure, national, american, social … +337 | E9: 1290 point, order, news, book, information, thanks … +1284 | F9: 276 kind, self, urgent, quality, ability, beauty … +270 | G9: 23 name, trust, profit, assets, treasure, trusts … +17 | H9: 40 westminster, incentive, incentives, bliss, added, add … +34 | I9: 127 melody, safe, training, favor, reform, approval … +121 | J9: 292 feelings, mood, jam, soup, roast, vodka … +286 | K9: 79 turtle, used, using, fuck, eat, released … +73 | L9: 88 run, walk, fly, hide, breathe, duck … +82
B10: 5 | C10: 34 poor, funny, worst, magic, severe, relative … +28 | D10: 71 real, less, late, likely, sorry, average … +65 | E10: 200 part, future, heart, rest, relationship, percent … +194 | F10: 431 good, way, power, level, control, age … +425 | G10: 111 be, things, cost, land, share, gold … +105 | H10: 315 money, identity, office, john, reason, building … +309 | I10: 469 house, room, door, window, angry, work … +463 | J10: 52 pity, compassion, screams, screaming, scream, auditory_silence … +46 | K10: 218 dress, clothes, suit, shirt, cap, tie … +212 | L10: 8 missing, missed, suffering, suffered, suffer, smells … +2
B11: 6 | C11: 20 striking, worse, offensive, horrible, annoying, silly … +14 | D11: 25 sad, cheap, false, dirty, secondary, steady … +19 | E11: 23 scale, bias, curse, apology, scales, autism … +17 | F11: 119 number, lot, nothing, bit, size, increase … +113 | G11: 17 amount, effects, option, options, amounts, premium … +11 | H11: 361 home, state, city, top, states, side … +355 | I11: 127 terrified, care, bank, sea, success, river … +121 | J11: 333 place, night, light, street, forest, alarm … +327 | K11: 116 rage, envy, outrage, car, cup, bed … +110
B12: 7 | C12: 5 terrible, awful, notorious, negative, unfortunate | D12: 7 fake, painful, nasty, abusive, filthy, miserable … +1 | E12: 144 wraith, arrows, year, years, day, days … +138 | F12: 9 executed, trapped, execute, mysterious, limit, scores … +3 | G12: 26 tone, alone, group, space, event, feeling … +20 | H12: 354 burn, burning, burned, burnt, life, thing … +348 | I12: 170 food, tortured, slash, choke, strangle, lunge … +164 | J12: 163 surprise, disappointment, surprises, surprised, scared, feared … +157 | K12: 151 hatred, frustration, fury, temper, tired, smoking … +145 | L12: 2 water, keys
B13: 8 | D13: 1 lonely | E13: 3 hours, fall, era | F13: 6 abandoned, threatened, murdered, threatening, threaten, poisoning | G13: 3 afraid, quantity, quantities | H13: 37 prison, cage, dungeon, prisons, died, die … +31 | I13: 26 shot, punch, slaughter, shooting, shoot, fired … +20 | J13: 20 fear, shame, shock, horror, panic, terror … +14 | K13: 34 anger, killed, kill, struck, kills, flooding … +28 | L13: 3 hurt, hurts, hurting
B14: 9 | D14: 1 dead | E14: 1 history | F14: 2 lost, bad | H14: 9 poverty, ruin, unemployment, disability, guilt, disabilities … +3 | I14: 14 attack, murder, attacks, strike, assault, strikes … +8 | J14: 10 chain, knife, torture, knives, axe, surprising … +4 | K14: 2 spite, wounded
A15: World (That, logical) ▼ | B15: 10 | F15: 4 mourn, betrayal, hopeless, orphan | G15: 1 dehumanization | H15: 14 pain, injury, injuries, wound, collapse, flame … +8 | I15: 27 death, fire, killing, smoke, storm, threat … +21 | J15: 1 poison | K15: 15 blade, gun, guns, bomb, sword, rifle … +9
A18: Count per cell (COUNTIFS formulas over Concepts_nodes)
C19: 1 | D19: 2 | E19: 3 | F19: 4 | G19: 5 | H19: 6 | I19: 7 | J19: 8 | K19: 9 | L19: 10
B20: 1 | C20: =COUNTIFS(Concepts_nodes!$K$2:$K$7677,C$19,Concepts_nodes!$L$2:$L$7677,$B20) -> 1 | D20: =COUNTIFS(Concepts_nodes!$K$2:$K$7677,D$19,Concepts_nodes!$L$2:$L$7677,$B20) -> 0 | E20: =COUNTIFS(Concepts_nodes!$K$2:$K$7677,E$19,Concepts_nodes!$L$2:$L$7677,$B20) -> 1 | F20: =COUNTIFS(Concepts_nodes!$K$2:$K$7677,F$19,Concepts_nodes!$L$2:$L$7677,$B20) -> 0 | G20: =COUNTIFS(Concepts_nodes!$K$2:$K$7677,G$19,Concepts_nodes!$L$2:$L$7677,$B20) -> 0 | H20: =COUNTIFS(Concepts_nodes!$K$2:$K$7677,H$19,Concepts_nodes!$L$2:$L$7677,$B20) -> 0 | I20: =COUNTIFS(Concepts_nodes!$K$2:$K$7677,I$19,Concepts_nodes!$L$2:$L$7677,$B20) -> 0 | J20: =COUNTIFS(Concepts_nodes!$K$2:$K$7677,J$19,Concepts_nodes!$L$2:$L$7677,$B20) -> 3 | ... L20: =COUNTIFS(Concepts_nodes!$K$2:$K$7677,L$19,Concepts_nodes!$L$2:$L$7677,$B20) -> 0
B21: 2 | C21: =COUNTIFS(Concepts_nodes!$K$2:$K$7677,C$19,Concepts_nodes!$L$2:$L$7677,$B21) -> 25 | D21: =COUNTIFS(Concepts_nodes!$K$2:$K$7677,D$19,Concepts_nodes!$L$2:$L$7677,$B21) -> 16 | E21: =COUNTIFS(Concepts_nodes!$K$2:$K$7677,E$19,Concepts_nodes!$L$2:$L$7677,$B21) -> 10 | F21: =COUNTIFS(Concepts_nodes!$K$2:$K$7677,F$19,Concepts_nodes!$L$2:$L$7677,$B21) -> 0 | G21: =COUNTIFS(Concepts_nodes!$K$2:$K$7677,G$19,Concepts_nodes!$L$2:$L$7677,$B21) -> 2 | H21: =COUNTIFS(Concepts_nodes!$K$2:$K$7677,H$19,Concepts_nodes!$L$2:$L$7677,$B21) -> 6 | I21: =COUNTIFS(Concepts_nodes!$K$2:$K$7677,I$19,Concepts_nodes!$L$2:$L$7677,$B21) -> 8 | J21: =COUNTIFS(Concepts_nodes!$K$2:$K$7677,J$19,Concepts_nodes!$L$2:$L$7677,$B21) -> 14 | ... L21: =COUNTIFS(Concepts_nodes!$K$2:$K$7677,L$19,Concepts_nodes!$L$2:$L$7677,$B21) -> 0
B22: 3 | C22: =COUNTIFS(Concepts_nodes!$K$2:$K$7677,C$19,Concepts_nodes!$L$2:$L$7677,$B22) -> 63 | D22: =COUNTIFS(Concepts_nodes!$K$2:$K$7677,D$19,Concepts_nodes!$L$2:$L$7677,$B22) -> 80 | E22: =COUNTIFS(Concepts_nodes!$K$2:$K$7677,E$19,Concepts_nodes!$L$2:$L$7677,$B22) -> 166 | F22: =COUNTIFS(Concepts_nodes!$K$2:$K$7677,F$19,Concepts_nodes!$L$2:$L$7677,$B22) -> 70 | G22: =COUNTIFS(Concepts_nodes!$K$2:$K$7677,G$19,Concepts_nodes!$L$2:$L$7677,$B22) -> 8 | H22: =COUNTIFS(Concepts_nodes!$K$2:$K$7677,H$19,Concepts_nodes!$L$2:$L$7677,$B22) -> 81 | I22: =COUNTIFS(Concepts_nodes!$K$2:$K$7677,I$19,Concepts_nodes!$L$2:$L$7677,$B22) -> 16 | J22: =COUNTIFS(Concepts_nodes!$K$2:$K$7677,J$19,Concepts_nodes!$L$2:$L$7677,$B22) -> 119 | ... L22: =COUNTIFS(Concepts_nodes!$K$2:$K$7677,L$19,Concepts_nodes!$L$2:$L$7677,$B22) -> 0
B23: 4 | C23: =COUNTIFS(Concepts_nodes!$K$2:$K$7677,C$19,Concepts_nodes!$L$2:$L$7677,$B23) -> 103 | D23: =COUNTIFS(Concepts_nodes!$K$2:$K$7677,D$19,Concepts_nodes!$L$2:$L$7677,$B23) -> 343 | E23: =COUNTIFS(Concepts_nodes!$K$2:$K$7677,E$19,Concepts_nodes!$L$2:$L$7677,$B23) -> 1290 | F23: =COUNTIFS(Concepts_nodes!$K$2:$K$7677,F$19,Concepts_nodes!$L$2:$L$7677,$B23) -> 276 | G23: =COUNTIFS(Concepts_nodes!$K$2:$K$7677,G$19,Concepts_nodes!$L$2:$L$7677,$B23) -> 23 | H23: =COUNTIFS(Concepts_nodes!$K$2:$K$7677,H$19,Concepts_nodes!$L$2:$L$7677,$B23) -> 40 | I23: =COUNTIFS(Concepts_nodes!$K$2:$K$7677,I$19,Concepts_nodes!$L$2:$L$7677,$B23) -> 127 | J23: =COUNTIFS(Concepts_nodes!$K$2:$K$7677,J$19,Concepts_nodes!$L$2:$L$7677,$B23) -> 292 | ... L23: =COUNTIFS(Concepts_nodes!$K$2:$K$7677,L$19,Concepts_nodes!$L$2:$L$7677,$B23) -> 88
B24: 5 | C24: =COUNTIFS(Concepts_nodes!$K$2:$K$7677,C$19,Concepts_nodes!$L$2:$L$7677,$B24) -> 34 | D24: =COUNTIFS(Concepts_nodes!$K$2:$K$7677,D$19,Concepts_nodes!$L$2:$L$7677,$B24) -> 71 | E24: =COUNTIFS(Concepts_nodes!$K$2:$K$7677,E$19,Concepts_nodes!$L$2:$L$7677,$B24) -> 200 | F24: =COUNTIFS(Concepts_nodes!$K$2:$K$7677,F$19,Concepts_nodes!$L$2:$L$7677,$B24) -> 431 | G24: =COUNTIFS(Concepts_nodes!$K$2:$K$7677,G$19,Concepts_nodes!$L$2:$L$7677,$B24) -> 111 | H24: =COUNTIFS(Concepts_nodes!$K$2:$K$7677,H$19,Concepts_nodes!$L$2:$L$7677,$B24) -> 315 | I24: =COUNTIFS(Concepts_nodes!$K$2:$K$7677,I$19,Concepts_nodes!$L$2:$L$7677,$B24) -> 469 | J24: =COUNTIFS(Concepts_nodes!$K$2:$K$7677,J$19,Concepts_nodes!$L$2:$L$7677,$B24) -> 52 | ... L24: =COUNTIFS(Concepts_nodes!$K$2:$K$7677,L$19,Concepts_nodes!$L$2:$L$7677,$B24) -> 8
B25: 6 | C25: =COUNTIFS(Concepts_nodes!$K$2:$K$7677,C$19,Concepts_nodes!$L$2:$L$7677,$B25) -> 20 | D25: =COUNTIFS(Concepts_nodes!$K$2:$K$7677,D$19,Concepts_nodes!$L$2:$L$7677,$B25) -> 25 | E25: =COUNTIFS(Concepts_nodes!$K$2:$K$7677,E$19,Concepts_nodes!$L$2:$L$7677,$B25) -> 23 | F25: =COUNTIFS(Concepts_nodes!$K$2:$K$7677,F$19,Concepts_nodes!$L$2:$L$7677,$B25) -> 119 | G25: =COUNTIFS(Concepts_nodes!$K$2:$K$7677,G$19,Concepts_nodes!$L$2:$L$7677,$B25) -> 17 | H25: =COUNTIFS(Concepts_nodes!$K$2:$K$7677,H$19,Concepts_nodes!$L$2:$L$7677,$B25) -> 361 | I25: =COUNTIFS(Concepts_nodes!$K$2:$K$7677,I$19,Concepts_nodes!$L$2:$L$7677,$B25) -> 127 | J25: =COUNTIFS(Concepts_nodes!$K$2:$K$7677,J$19,Concepts_nodes!$L$2:$L$7677,$B25) -> 333 | ... L25: =COUNTIFS(Concepts_nodes!$K$2:$K$7677,L$19,Concepts_nodes!$L$2:$L$7677,$B25) -> 0
B26: 7 | C26: =COUNTIFS(Concepts_nodes!$K$2:$K$7677,C$19,Concepts_nodes!$L$2:$L$7677,$B26) -> 5 | D26: =COUNTIFS(Concepts_nodes!$K$2:$K$7677,D$19,Concepts_nodes!$L$2:$L$7677,$B26) -> 7 | E26: =COUNTIFS(Concepts_nodes!$K$2:$K$7677,E$19,Concepts_nodes!$L$2:$L$7677,$B26) -> 144 | F26: =COUNTIFS(Concepts_nodes!$K$2:$K$7677,F$19,Concepts_nodes!$L$2:$L$7677,$B26) -> 9 | G26: =COUNTIFS(Concepts_nodes!$K$2:$K$7677,G$19,Concepts_nodes!$L$2:$L$7677,$B26) -> 26 | H26: =COUNTIFS(Concepts_nodes!$K$2:$K$7677,H$19,Concepts_nodes!$L$2:$L$7677,$B26) -> 354 | I26: =COUNTIFS(Concepts_nodes!$K$2:$K$7677,I$19,Concepts_nodes!$L$2:$L$7677,$B26) -> 170 | J26: =COUNTIFS(Concepts_nodes!$K$2:$K$7677,J$19,Concepts_nodes!$L$2:$L$7677,$B26) -> 163 | ... L26: =COUNTIFS(Concepts_nodes!$K$2:$K$7677,L$19,Concepts_nodes!$L$2:$L$7677,$B26) -> 2
B27: 8 | C27: =COUNTIFS(Concepts_nodes!$K$2:$K$7677,C$19,Concepts_nodes!$L$2:$L$7677,$B27) -> 0 | D27: =COUNTIFS(Concepts_nodes!$K$2:$K$7677,D$19,Concepts_nodes!$L$2:$L$7677,$B27) -> 1 | E27: =COUNTIFS(Concepts_nodes!$K$2:$K$7677,E$19,Concepts_nodes!$L$2:$L$7677,$B27) -> 3 | F27: =COUNTIFS(Concepts_nodes!$K$2:$K$7677,F$19,Concepts_nodes!$L$2:$L$7677,$B27) -> 6 | G27: =COUNTIFS(Concepts_nodes!$K$2:$K$7677,G$19,Concepts_nodes!$L$2:$L$7677,$B27) -> 3 | H27: =COUNTIFS(Concepts_nodes!$K$2:$K$7677,H$19,Concepts_nodes!$L$2:$L$7677,$B27) -> 37 | I27: =COUNTIFS(Concepts_nodes!$K$2:$K$7677,I$19,Concepts_nodes!$L$2:$L$7677,$B27) -> 26 | J27: =COUNTIFS(Concepts_nodes!$K$2:$K$7677,J$19,Concepts_nodes!$L$2:$L$7677,$B27) -> 20 | ... L27: =COUNTIFS(Concepts_nodes!$K$2:$K$7677,L$19,Concepts_nodes!$L$2:$L$7677,$B27) -> 3
B28: 9 | C28: =COUNTIFS(Concepts_nodes!$K$2:$K$7677,C$19,Concepts_nodes!$L$2:$L$7677,$B28) -> 0 | D28: =COUNTIFS(Concepts_nodes!$K$2:$K$7677,D$19,Concepts_nodes!$L$2:$L$7677,$B28) -> 1 | E28: =COUNTIFS(Concepts_nodes!$K$2:$K$7677,E$19,Concepts_nodes!$L$2:$L$7677,$B28) -> 1 | F28: =COUNTIFS(Concepts_nodes!$K$2:$K$7677,F$19,Concepts_nodes!$L$2:$L$7677,$B28) -> 2 | G28: =COUNTIFS(Concepts_nodes!$K$2:$K$7677,G$19,Concepts_nodes!$L$2:$L$7677,$B28) -> 0 | H28: =COUNTIFS(Concepts_nodes!$K$2:$K$7677,H$19,Concepts_nodes!$L$2:$L$7677,$B28) -> 9 | I28: =COUNTIFS(Concepts_nodes!$K$2:$K$7677,I$19,Concepts_nodes!$L$2:$L$7677,$B28) -> 14 | J28: =COUNTIFS(Concepts_nodes!$K$2:$K$7677,J$19,Concepts_nodes!$L$2:$L$7677,$B28) -> 10 | ... L28: =COUNTIFS(Concepts_nodes!$K$2:$K$7677,L$19,Concepts_nodes!$L$2:$L$7677,$B28) -> 0
B29: 10 | C29: =COUNTIFS(Concepts_nodes!$K$2:$K$7677,C$19,Concepts_nodes!$L$2:$L$7677,$B29) -> 0 | D29: =COUNTIFS(Concepts_nodes!$K$2:$K$7677,D$19,Concepts_nodes!$L$2:$L$7677,$B29) -> 0 | E29: =COUNTIFS(Concepts_nodes!$K$2:$K$7677,E$19,Concepts_nodes!$L$2:$L$7677,$B29) -> 0 | F29: =COUNTIFS(Concepts_nodes!$K$2:$K$7677,F$19,Concepts_nodes!$L$2:$L$7677,$B29) -> 4 | G29: =COUNTIFS(Concepts_nodes!$K$2:$K$7677,G$19,Concepts_nodes!$L$2:$L$7677,$B29) -> 1 | H29: =COUNTIFS(Concepts_nodes!$K$2:$K$7677,H$19,Concepts_nodes!$L$2:$L$7677,$B29) -> 14 | I29: =COUNTIFS(Concepts_nodes!$K$2:$K$7677,I$19,Concepts_nodes!$L$2:$L$7677,$B29) -> 27 | J29: =COUNTIFS(Concepts_nodes!$K$2:$K$7677,J$19,Concepts_nodes!$L$2:$L$7677,$B29) -> 1 | ... L29: =COUNTIFS(Concepts_nodes!$K$2:$K$7677,L$19,Concepts_nodes!$L$2:$L$7677,$B29) -> 0
B30: Total | C30: =SUM(C20:L29) -> 7676 | D30: nodes in the sheet: | E30: =COUNTA(Concepts_nodes!A2:A7677) -> 7676 | F30: =IF(C30=E30,"✔ matches","✖ does not match") -> ✔ matches

Sheet Connectors
A1: Table of Connectors (10 × 10)
A2: Each cell shows how many words it has and the first ones (hand-made concepts first). Full list in the sheet Connectors_nodes. Position: x = (Lv − Gv)/2, y = (V − I)/2.
C4: ◄ Adaptation (You, structural) | H4: Imposition (I, Sensory) ►
C5: 1 | D5: 2 | E5: 3 | F5: 4 | G5: 5 | H5: 6 | I5: 7 | J5: 8 | K5: 9 | L5: 10
A6: Context (We, Possibility) ▲ | B6: 1 | F6: 4 if, so that, in order to, in order that | G6: 11 moreover, furthermore, besides, additionally, likewise, similarly … +5
B7: 2 | E7: 9 even if, provided (that), providing, as long as, so long as, in case … +3 | F7: 12 in a way, sort of, kind of, somewhat, a bit, more or less … +6 | J7: 1 fortunately
B8: 3 | D8: 4 first, to begin with, that (complementizer), & | E8: 5 then, next, afterwards, later, subsequently | K8: 8 indeed, in fact, actually, especially, certainly, as a matter of fact … +2
B9: 4 | D9: 17 and, also, too, plus, by the way, incidentally … +11 | E9: 3 or, either…or, alternatively | F9: 1 … | I9: 8 for example, for instance, such as, including, e.g., in particular … +2 | J9: 6 frankly, honestly, clearly, obviously, apparently, surprisingly
B10: 5 | C10: 1 " " | D10: 27 in other words, that is, i.e., to put it another way, although, even though … +21 | E10: 7 where, when (relative), why, ;, -, ( ) … +1 | I10: 3 meanwhile, at the same time, —
B11: 6 | D11: 16 but, on the other hand, in contrast, by contrast, whereas, while (contrast) … +10 | E11: 1 unless | K11: 1 !
B12: 7 | D12: 2 finally, lastly | E12: 3 instead, rather, or else | I12: 2 I mean, what I mean is
B13: 8 | D13: 7 in conclusion, to sum up, in short, in summary, overall, all in all … +1 | E13: 8 lest, for fear that, before, until, till, by the time … +2 | F13: 10 therefore, thus, hence, consequently, accordingly, as a result … +4
B14: 9 | F14: 15 except, except that, apart from, other than, but for, save … +9 | J14: 2 unfortunately, sadly
A15: World (That, logical) ▼ | B15: 10 | F15: 2 nor, neither…nor
A18: Count per cell (COUNTIFS formulas over Connectors_nodes)
C19: 1 | D19: 2 | E19: 3 | F19: 4 | G19: 5 | H19: 6 | I19: 7 | J19: 8 | K19: 9 | L19: 10
B20: 1 | C20: =COUNTIFS(Connectors_nodes!$K$2:$K$197,C$19,Connectors_nodes!$L$2:$L$197,$B20) -> 0 | D20: =COUNTIFS(Connectors_nodes!$K$2:$K$197,D$19,Connectors_nodes!$L$2:$L$197,$B20) -> 0 | E20: =COUNTIFS(Connectors_nodes!$K$2:$K$197,E$19,Connectors_nodes!$L$2:$L$197,$B20) -> 0 | F20: =COUNTIFS(Connectors_nodes!$K$2:$K$197,F$19,Connectors_nodes!$L$2:$L$197,$B20) -> 4 | G20: =COUNTIFS(Connectors_nodes!$K$2:$K$197,G$19,Connectors_nodes!$L$2:$L$197,$B20) -> 11 | H20: =COUNTIFS(Connectors_nodes!$K$2:$K$197,H$19,Connectors_nodes!$L$2:$L$197,$B20) -> 0 | I20: =COUNTIFS(Connectors_nodes!$K$2:$K$197,I$19,Connectors_nodes!$L$2:$L$197,$B20) -> 0 | J20: =COUNTIFS(Connectors_nodes!$K$2:$K$197,J$19,Connectors_nodes!$L$2:$L$197,$B20) -> 0 | ... L20: =COUNTIFS(Connectors_nodes!$K$2:$K$197,L$19,Connectors_nodes!$L$2:$L$197,$B20) -> 0
B21: 2 | C21: =COUNTIFS(Connectors_nodes!$K$2:$K$197,C$19,Connectors_nodes!$L$2:$L$197,$B21) -> 0 | D21: =COUNTIFS(Connectors_nodes!$K$2:$K$197,D$19,Connectors_nodes!$L$2:$L$197,$B21) -> 0 | E21: =COUNTIFS(Connectors_nodes!$K$2:$K$197,E$19,Connectors_nodes!$L$2:$L$197,$B21) -> 9 | F21: =COUNTIFS(Connectors_nodes!$K$2:$K$197,F$19,Connectors_nodes!$L$2:$L$197,$B21) -> 12 | G21: =COUNTIFS(Connectors_nodes!$K$2:$K$197,G$19,Connectors_nodes!$L$2:$L$197,$B21) -> 0 | H21: =COUNTIFS(Connectors_nodes!$K$2:$K$197,H$19,Connectors_nodes!$L$2:$L$197,$B21) -> 0 | I21: =COUNTIFS(Connectors_nodes!$K$2:$K$197,I$19,Connectors_nodes!$L$2:$L$197,$B21) -> 0 | J21: =COUNTIFS(Connectors_nodes!$K$2:$K$197,J$19,Connectors_nodes!$L$2:$L$197,$B21) -> 1 | ... L21: =COUNTIFS(Connectors_nodes!$K$2:$K$197,L$19,Connectors_nodes!$L$2:$L$197,$B21) -> 0
B22: 3 | C22: =COUNTIFS(Connectors_nodes!$K$2:$K$197,C$19,Connectors_nodes!$L$2:$L$197,$B22) -> 0 | D22: =COUNTIFS(Connectors_nodes!$K$2:$K$197,D$19,Connectors_nodes!$L$2:$L$197,$B22) -> 4 | E22: =COUNTIFS(Connectors_nodes!$K$2:$K$197,E$19,Connectors_nodes!$L$2:$L$197,$B22) -> 5 | F22: =COUNTIFS(Connectors_nodes!$K$2:$K$197,F$19,Connectors_nodes!$L$2:$L$197,$B22) -> 0 | G22: =COUNTIFS(Connectors_nodes!$K$2:$K$197,G$19,Connectors_nodes!$L$2:$L$197,$B22) -> 0 | H22: =COUNTIFS(Connectors_nodes!$K$2:$K$197,H$19,Connectors_nodes!$L$2:$L$197,$B22) -> 0 | I22: =COUNTIFS(Connectors_nodes!$K$2:$K$197,I$19,Connectors_nodes!$L$2:$L$197,$B22) -> 0 | J22: =COUNTIFS(Connectors_nodes!$K$2:$K$197,J$19,Connectors_nodes!$L$2:$L$197,$B22) -> 0 | ... L22: =COUNTIFS(Connectors_nodes!$K$2:$K$197,L$19,Connectors_nodes!$L$2:$L$197,$B22) -> 0
B23: 4 | C23: =COUNTIFS(Connectors_nodes!$K$2:$K$197,C$19,Connectors_nodes!$L$2:$L$197,$B23) -> 0 | D23: =COUNTIFS(Connectors_nodes!$K$2:$K$197,D$19,Connectors_nodes!$L$2:$L$197,$B23) -> 17 | E23: =COUNTIFS(Connectors_nodes!$K$2:$K$197,E$19,Connectors_nodes!$L$2:$L$197,$B23) -> 3 | F23: =COUNTIFS(Connectors_nodes!$K$2:$K$197,F$19,Connectors_nodes!$L$2:$L$197,$B23) -> 1 | G23: =COUNTIFS(Connectors_nodes!$K$2:$K$197,G$19,Connectors_nodes!$L$2:$L$197,$B23) -> 0 | H23: =COUNTIFS(Connectors_nodes!$K$2:$K$197,H$19,Connectors_nodes!$L$2:$L$197,$B23) -> 0 | I23: =COUNTIFS(Connectors_nodes!$K$2:$K$197,I$19,Connectors_nodes!$L$2:$L$197,$B23) -> 8 | J23: =COUNTIFS(Connectors_nodes!$K$2:$K$197,J$19,Connectors_nodes!$L$2:$L$197,$B23) -> 6 | ... L23: =COUNTIFS(Connectors_nodes!$K$2:$K$197,L$19,Connectors_nodes!$L$2:$L$197,$B23) -> 0
B24: 5 | C24: =COUNTIFS(Connectors_nodes!$K$2:$K$197,C$19,Connectors_nodes!$L$2:$L$197,$B24) -> 1 | D24: =COUNTIFS(Connectors_nodes!$K$2:$K$197,D$19,Connectors_nodes!$L$2:$L$197,$B24) -> 27 | E24: =COUNTIFS(Connectors_nodes!$K$2:$K$197,E$19,Connectors_nodes!$L$2:$L$197,$B24) -> 7 | F24: =COUNTIFS(Connectors_nodes!$K$2:$K$197,F$19,Connectors_nodes!$L$2:$L$197,$B24) -> 0 | G24: =COUNTIFS(Connectors_nodes!$K$2:$K$197,G$19,Connectors_nodes!$L$2:$L$197,$B24) -> 0 | H24: =COUNTIFS(Connectors_nodes!$K$2:$K$197,H$19,Connectors_nodes!$L$2:$L$197,$B24) -> 0 | I24: =COUNTIFS(Connectors_nodes!$K$2:$K$197,I$19,Connectors_nodes!$L$2:$L$197,$B24) -> 3 | J24: =COUNTIFS(Connectors_nodes!$K$2:$K$197,J$19,Connectors_nodes!$L$2:$L$197,$B24) -> 0 | ... L24: =COUNTIFS(Connectors_nodes!$K$2:$K$197,L$19,Connectors_nodes!$L$2:$L$197,$B24) -> 0
B25: 6 | C25: =COUNTIFS(Connectors_nodes!$K$2:$K$197,C$19,Connectors_nodes!$L$2:$L$197,$B25) -> 0 | D25: =COUNTIFS(Connectors_nodes!$K$2:$K$197,D$19,Connectors_nodes!$L$2:$L$197,$B25) -> 16 | E25: =COUNTIFS(Connectors_nodes!$K$2:$K$197,E$19,Connectors_nodes!$L$2:$L$197,$B25) -> 1 | F25: =COUNTIFS(Connectors_nodes!$K$2:$K$197,F$19,Connectors_nodes!$L$2:$L$197,$B25) -> 0 | G25: =COUNTIFS(Connectors_nodes!$K$2:$K$197,G$19,Connectors_nodes!$L$2:$L$197,$B25) -> 0 | H25: =COUNTIFS(Connectors_nodes!$K$2:$K$197,H$19,Connectors_nodes!$L$2:$L$197,$B25) -> 0 | I25: =COUNTIFS(Connectors_nodes!$K$2:$K$197,I$19,Connectors_nodes!$L$2:$L$197,$B25) -> 0 | J25: =COUNTIFS(Connectors_nodes!$K$2:$K$197,J$19,Connectors_nodes!$L$2:$L$197,$B25) -> 0 | ... L25: =COUNTIFS(Connectors_nodes!$K$2:$K$197,L$19,Connectors_nodes!$L$2:$L$197,$B25) -> 0
B26: 7 | C26: =COUNTIFS(Connectors_nodes!$K$2:$K$197,C$19,Connectors_nodes!$L$2:$L$197,$B26) -> 0 | D26: =COUNTIFS(Connectors_nodes!$K$2:$K$197,D$19,Connectors_nodes!$L$2:$L$197,$B26) -> 2 | E26: =COUNTIFS(Connectors_nodes!$K$2:$K$197,E$19,Connectors_nodes!$L$2:$L$197,$B26) -> 3 | F26: =COUNTIFS(Connectors_nodes!$K$2:$K$197,F$19,Connectors_nodes!$L$2:$L$197,$B26) -> 0 | G26: =COUNTIFS(Connectors_nodes!$K$2:$K$197,G$19,Connectors_nodes!$L$2:$L$197,$B26) -> 0 | H26: =COUNTIFS(Connectors_nodes!$K$2:$K$197,H$19,Connectors_nodes!$L$2:$L$197,$B26) -> 0 | I26: =COUNTIFS(Connectors_nodes!$K$2:$K$197,I$19,Connectors_nodes!$L$2:$L$197,$B26) -> 2 | J26: =COUNTIFS(Connectors_nodes!$K$2:$K$197,J$19,Connectors_nodes!$L$2:$L$197,$B26) -> 0 | ... L26: =COUNTIFS(Connectors_nodes!$K$2:$K$197,L$19,Connectors_nodes!$L$2:$L$197,$B26) -> 0
B27: 8 | C27: =COUNTIFS(Connectors_nodes!$K$2:$K$197,C$19,Connectors_nodes!$L$2:$L$197,$B27) -> 0 | D27: =COUNTIFS(Connectors_nodes!$K$2:$K$197,D$19,Connectors_nodes!$L$2:$L$197,$B27) -> 7 | E27: =COUNTIFS(Connectors_nodes!$K$2:$K$197,E$19,Connectors_nodes!$L$2:$L$197,$B27) -> 8 | F27: =COUNTIFS(Connectors_nodes!$K$2:$K$197,F$19,Connectors_nodes!$L$2:$L$197,$B27) -> 10 | G27: =COUNTIFS(Connectors_nodes!$K$2:$K$197,G$19,Connectors_nodes!$L$2:$L$197,$B27) -> 0 | H27: =COUNTIFS(Connectors_nodes!$K$2:$K$197,H$19,Connectors_nodes!$L$2:$L$197,$B27) -> 0 | I27: =COUNTIFS(Connectors_nodes!$K$2:$K$197,I$19,Connectors_nodes!$L$2:$L$197,$B27) -> 0 | J27: =COUNTIFS(Connectors_nodes!$K$2:$K$197,J$19,Connectors_nodes!$L$2:$L$197,$B27) -> 0 | ... L27: =COUNTIFS(Connectors_nodes!$K$2:$K$197,L$19,Connectors_nodes!$L$2:$L$197,$B27) -> 0
B28: 9 | C28: =COUNTIFS(Connectors_nodes!$K$2:$K$197,C$19,Connectors_nodes!$L$2:$L$197,$B28) -> 0 | D28: =COUNTIFS(Connectors_nodes!$K$2:$K$197,D$19,Connectors_nodes!$L$2:$L$197,$B28) -> 0 | E28: =COUNTIFS(Connectors_nodes!$K$2:$K$197,E$19,Connectors_nodes!$L$2:$L$197,$B28) -> 0 | F28: =COUNTIFS(Connectors_nodes!$K$2:$K$197,F$19,Connectors_nodes!$L$2:$L$197,$B28) -> 15 | G28: =COUNTIFS(Connectors_nodes!$K$2:$K$197,G$19,Connectors_nodes!$L$2:$L$197,$B28) -> 0 | H28: =COUNTIFS(Connectors_nodes!$K$2:$K$197,H$19,Connectors_nodes!$L$2:$L$197,$B28) -> 0 | I28: =COUNTIFS(Connectors_nodes!$K$2:$K$197,I$19,Connectors_nodes!$L$2:$L$197,$B28) -> 0 | J28: =COUNTIFS(Connectors_nodes!$K$2:$K$197,J$19,Connectors_nodes!$L$2:$L$197,$B28) -> 2 | ... L28: =COUNTIFS(Connectors_nodes!$K$2:$K$197,L$19,Connectors_nodes!$L$2:$L$197,$B28) -> 0
B29: 10 | C29: =COUNTIFS(Connectors_nodes!$K$2:$K$197,C$19,Connectors_nodes!$L$2:$L$197,$B29) -> 0 | D29: =COUNTIFS(Connectors_nodes!$K$2:$K$197,D$19,Connectors_nodes!$L$2:$L$197,$B29) -> 0 | E29: =COUNTIFS(Connectors_nodes!$K$2:$K$197,E$19,Connectors_nodes!$L$2:$L$197,$B29) -> 0 | F29: =COUNTIFS(Connectors_nodes!$K$2:$K$197,F$19,Connectors_nodes!$L$2:$L$197,$B29) -> 2 | G29: =COUNTIFS(Connectors_nodes!$K$2:$K$197,G$19,Connectors_nodes!$L$2:$L$197,$B29) -> 0 | H29: =COUNTIFS(Connectors_nodes!$K$2:$K$197,H$19,Connectors_nodes!$L$2:$L$197,$B29) -> 0 | I29: =COUNTIFS(Connectors_nodes!$K$2:$K$197,I$19,Connectors_nodes!$L$2:$L$197,$B29) -> 0 | J29: =COUNTIFS(Connectors_nodes!$K$2:$K$197,J$19,Connectors_nodes!$L$2:$L$197,$B29) -> 0 | ... L29: =COUNTIFS(Connectors_nodes!$K$2:$K$197,L$19,Connectors_nodes!$L$2:$L$197,$B29) -> 0
B30: Total | C30: =SUM(C20:L29) -> 196 | D30: nodes in the sheet: | E30: =COUNTA(Connectors_nodes!A2:A197) -> 196 | F30: =IF(C30=E30,"✔ matches","✖ does not match") -> ✔ matches

Sheet Subjects_nodes
A1: Word | B1: Type | C1: Category | D1: Subtype | E1: V | F1: I | G1: Lv | H1: Gv | I1: x | J1: y | K1: Col | L1: Row | M1: τ | N1: Source | O1: Sent+ | P1: Sent− | Q1: Synonyms | R1: Related (nodes) | S1: Related (labels without a node) | T1: Related (WordNet) | U1: Related (manual) | V1: Opposites
A2: children | B2: biological | C2: person | E2: 9 | F2: 1 | G2: 1 | H2: 10 | I2: =(G2-H2)/2 -> -4.5 | J2: =(E2-F2)/2 -> 4 | K2: =MAX(1,MIN(10,ROUNDUP(I2+5,0))) -> 1 | L2: =MAX(1,MIN(10,ROUNDUP(5-J2,0))) -> 1 | M2: =MIN(E2,F2) -> 1 | N2: lexicon | O2: 0.04 | P2: 0 | Q2: child, fry, kid, minor, nestling, nipper | T2: juvenile (is-a), orphan (kind-of), imp (kind-of), monkey (kind-of), young (definition), sex (definition), issue (is-a), family (part), human (definition), son (definition)
A3: members | B3: biological | C3: person | E3: 9 | F3: 1 | G3: 1 | H3: 10 | I3: =(G3-H3)/2 -> -4.5 | J3: =(E3-F3)/2 -> 4 | K3: =MAX(1,MIN(10,ROUNDUP(I3+5,0))) -> 1 | L3: =MAX(1,MIN(10,ROUNDUP(5-J3,0))) -> 1 | M3: =MIN(E3,F3) -> 1 | N3: lexicon | O3: 0 | P3: 0 | Q3: fellow member, member | T3: associate (is-a), brother (kind-of), commissioner (kind-of), conservative (kind-of), person (definition), social (definition), group (definition), individual (definition), part (is-a), portion (is-a)
A4: child | B4: biological | C4: person | E4: 9 | F4: 1 | G4: 1 | H4: 10 | I4: =(G4-H4)/2 -> -4.5 | J4: =(E4-F4)/2 -> 4 | K4: =MAX(1,MIN(10,ROUNDUP(I4+5,0))) -> 1 | L4: =MAX(1,MIN(10,ROUNDUP(5-J4,0))) -> 1 | M4: =MIN(E4,F4) -> 1 | N4: lexicon | O4: 0.04 | P4: 0 | Q4: fry, kid, minor, nestling, nipper | T4: juvenile (is-a), orphan (kind-of), imp (kind-of), monkey (kind-of), childhood (derived), young (definition), sex (definition), issue (is-a), family (part), human (definition), son (definition) | U4: play, jump, run, laugh, story, family, mother, father, dog, sing, dance, sleep, climb, swim, cry | V4: parent
A5: kids | B5: biological | C5: person | E5: 9 | F5: 1 | G5: 1 | H5: 10 | I5: =(G5-H5)/2 -> -4.5 | J5: =(E5-F5)/2 -> 4 | K5: =MAX(1,MIN(10,ROUNDUP(I5+5,0))) -> 1 | L5: =MAX(1,MIN(10,ROUNDUP(5-J5,0))) -> 1 | M5: =MIN(E5,F5) -> 1 | N5: lexicon | O5: 0 | P5: 0 | Q5: child, fry, kid, minor, nestling, nipper | T5: juvenile (is-a), orphan (kind-of), imp (kind-of), monkey (kind-of), young (definition), sex (definition), leather (is-a), soft (definition), smooth (definition)
A6: son | B6: biological | C6: person | E6: 9 | F6: 1 | G6: 1 | H6: 10 | I6: =(G6-H6)/2 -> -4.5 | J6: =(E6-F6)/2 -> 4 | K6: =MAX(1,MIN(10,ROUNDUP(I6+5,0))) -> 1 | L6: =MAX(1,MIN(10,ROUNDUP(5-J6,0))) -> 1 | M6: =MIN(E6,F6) -> 1 | N6: lexicon | O6: 0 | P6: 0 | Q6: boy | T6: junior (kind-of), male (definition), human (definition), divine (definition), word (definition) | V6: daughter
A7: baby | B7: biological | C7: person | E7: 9 | F7: 1 | G7: 1 | H7: 10 | I7: =(G7-H7)/2 -> -4.5 | J7: =(E7-F7)/2 -> 4 | K7: =MAX(1,MIN(10,ROUNDUP(I7+5,0))) -> 1 | L7: =MAX(1,MIN(10,ROUNDUP(5-J7,0))) -> 1 | M7: =MIN(E7,F7) -> 1 | N7: lexicon | O7: 0 | P7: 0 | Q7: babe, infant | T7: child (is-a), kid (is-a), newborn (kind-of), young (definition), birth (definition), year (definition), begin (definition), issue (is-a)
A8: wife | B8: biological | C8: person | E8: 9 | F8: 1 | G8: 1 | H8: 10 | I8: =(G8-H8)/2 -> -4.5 | J8: =(E8-F8)/2 -> 4 | K8: =MAX(1,MIN(10,ROUNDUP(I8+5,0))) -> 1 | L8: =MAX(1,MIN(10,ROUNDUP(5-J8,0))) -> 1 | M8: =MIN(E8,F8) -> 1 | N8: lexicon | O8: 0 | P8: 0 | Q8: married woman | T8: woman (is-a), partner (is-a), spouse (is-a), married (definition), man (definition), marriage (definition) | V8: husband
A9: parents | B9: biological | C9: person | E9: 9 | F9: 1 | G9: 1 | H9: 10 | I9: =(G9-H9)/2 -> -4.5 | J9: =(E9-F9)/2 -> 4 | K9: =MAX(1,MIN(10,ROUNDUP(I9+5,0))) -> 1 | L9: =MAX(1,MIN(10,ROUNDUP(5-J9,0))) -> 1 | M9: =MIN(E9,F9) -> 1 | N9: lexicon | O9: 0 | P9: 0 | Q9: parent | T9: mother (kind-of), father (kind-of), family (part), give (definition), birth (definition), raise (definition), child (definition), being (is-a)
A10: member | B10: biological | C10: person | E10: 9 | F10: 1 | G10: 1 | H10: 10 | I10: =(G10-H10)/2 -> -4.5 | J10: =(E10-F10)/2 -> 4 | K10: =MAX(1,MIN(10,ROUNDUP(I10+5,0))) -> 1 | L10: =MAX(1,MIN(10,ROUNDUP(5-J10,0))) -> 1 | M10: =MIN(E10,F10) -> 1 | N10: lexicon | O10: 0 | P10: 0 | Q10: fellow member | T10: associate (is-a), brother (kind-of), commissioner (kind-of), conservative (kind-of), membership (derived), person (definition), social (definition), group (definition), individual (definition), part (is-a), portion (is-a)
A11: mom | B11: biological | C11: person | E11: 10 | F11: 1 | G11: 1 | H11: 10 | I11: =(G11-H11)/2 -> -4.5 | J11: =(E11-F11)/2 -> 4.5 | K11: =MAX(1,MIN(10,ROUNDUP(I11+5,0))) -> 1 | L11: =MAX(1,MIN(10,ROUNDUP(5-J11,0))) -> 1 | M11: =MIN(E11,F11) -> 1 | N11: lexicon | O11: 0.88 | P11: 0 | Q11: ma, mama, mamma, mammy, momma | T11: mother (is-a), informal (definition), terms (definition)
A12: brother | B12: biological | C12: person | E12: 9 | F12: 1 | G12: 1 | H12: 10 | I12: =(G12-H12)/2 -> -4.5 | J12: =(E12-F12)/2 -> 4 | K12: =MAX(1,MIN(10,ROUNDUP(I12+5,0))) -> 1 | L12: =MAX(1,MIN(10,ROUNDUP(5-J12,0))) -> 1 | M12: =MIN(E12,F12) -> 1 | N12: lexicon | O12: 0.04 | P12: 0 | Q12: blood brother | T12: male (definition), parent (definition), member (is-a), mason (kind-of), brotherhood (part), fellow (definition), religion (definition) | V12: sister
A13: daughter | B13: biological | C13: person | E13: 9 | F13: 1 | G13: 1 | H13: 10 | I13: =(G13-H13)/2 -> -4.5 | J13: =(E13-F13)/2 -> 4 | K13: =MAX(1,MIN(10,ROUNDUP(I13+5,0))) -> 1 | L13: =MAX(1,MIN(10,ROUNDUP(5-J13,0))) -> 1 | M13: =MIN(E13,F13) -> 1 | N13: lexicon | O13: 0 | P13: 0 | Q13: girl | T13: female (definition), human (definition) | V13: son
A14: husband | B14: biological | C14: person | E14: 9 | F14: 1 | G14: 1 | H14: 10 | I14: =(G14-H14)/2 -> -4.5 | J14: =(E14-F14)/2 -> 4 | K14: =MAX(1,MIN(10,ROUNDUP(I14+5,0))) -> 1 | L14: =MAX(1,MIN(10,ROUNDUP(5-J14,0))) -> 1 | M14: =MIN(E14,F14) -> 1 | N14: lexicon | O14: 0 | P14: 0 | Q14: hubby, married man | T14: partner (is-a), spouse (is-a), mate (is-a), married (definition), man (definition), woman (definition), marriage (definition) | V14: wife
A15: kid | B15: biological | C15: person | E15: 9 | F15: 1 | G15: 1 | H15: 10 | I15: =(G15-H15)/2 -> -4.5 | J15: =(E15-F15)/2 -> 4 | K15: =MAX(1,MIN(10,ROUNDUP(I15+5,0))) -> 1 | L15: =MAX(1,MIN(10,ROUNDUP(5-J15,0))) -> 1 | M15: =MIN(E15,F15) -> 1 | N15: lexicon | O15: 0 | P15: 0 | Q15: child, fry, minor, nestling, nipper | T15: juvenile (is-a), orphan (kind-of), imp (kind-of), monkey (kind-of), young (definition), sex (definition), leather (is-a), soft (definition), smooth (definition)
A16: dad | B16: biological | C16: person | E16: 9 | F16: 1 | G16: 1 | H16: 10 | I16: =(G16-H16)/2 -> -4.5 | J16: =(E16-F16)/2 -> 4 | K16: =MAX(1,MIN(10,ROUNDUP(I16+5,0))) -> 1 | L16: =MAX(1,MIN(10,ROUNDUP(5-J16,0))) -> 1 | M16: =MIN(E16,F16) -> 1 | N16: lexicon | O16: 0 | P16: 0 | Q16: dada, daddy, pa, papa, pappa | T16: father (is-a), informal (definition), term (definition), probably (definition), baby (definition)
A17: sister | B17: biological | C17: person | E17: 9 | F17: 1 | G17: 1 | H17: 10 | I17: =(G17-H17)/2 -> -4.5 | J17: =(E17-F17)/2 -> 4 | K17: =MAX(1,MIN(10,ROUNDUP(I17+5,0))) -> 1 | L17: =MAX(1,MIN(10,ROUNDUP(5-J17,0))) -> 1 | M17: =MIN(E17,F17) -> 1 | N17: lexicon | O17: 0 | P17: 0 | Q17: sis | T17: female (definition), parent (definition), nun (is-a), roman (definition), catholic (definition) | V17: brother
A18: master | B18: biological | C18: person | E18: 10 | F18: 1 | G18: 2 | H18: 10 | I18: =(G18-H18)/2 -> -4 | J18: =(E18-F18)/2 -> 4.5 | K18: =MAX(1,MIN(10,ROUNDUP(I18+5,0))) -> 1 | L18: =MAX(1,MIN(10,ROUNDUP(5-J18,0))) -> 1 | M18: =MIN(E18,F18) -> 1 | N18: lexicon | O18: 0.29 | P18: 0 | Q18: maestro | T18: artist (is-a), skill (definition), ruler (is-a), general (definition), authority (definition)
A19: pop | B19: biological | C19: person | E19: 9 | F19: 1 | G19: 1 | H19: 10 | I19: =(G19-H19)/2 -> -4.5 | J19: =(E19-F19)/2 -> 4 | K19: =MAX(1,MIN(10,ROUNDUP(I19+5,0))) -> 1 | L19: =MAX(1,MIN(10,ROUNDUP(5-J19,0))) -> 1 | M19: =MIN(E19,F19) -> 1 | N19: lexicon | O19: 0 | P19: 0 | Q19: dad, dada, daddy, pa, papa, pappa | T19: father (is-a), informal (definition), term (definition), probably (definition), baby (definition)
A20: partner | B20: biological | C20: person | E20: 9 | F20: 1 | G20: 1 | H20: 10 | I20: =(G20-H20)/2 -> -4.5 | J20: =(E20-F20)/2 -> 4 | K20: =MAX(1,MIN(10,ROUNDUP(I20+5,0))) -> 1 | L20: =MAX(1,MIN(10,ROUNDUP(5-J20,0))) -> 1 | M20: =MIN(E20,F20) -> 1 | N20: lexicon | O20: 0 | P20: 0 | Q20: better half, married person, mate, spouse | T20: relative (is-a), relation (is-a), wife (kind-of), husband (kind-of), marriage (part), associate (is-a), partnership (derived), activity (definition), sphere (definition), common (definition), interest (definition)
A21: youth | B21: biological | C21: person | E21: 9 | F21: 1 | G21: 1 | H21: 10 | I21: =(G21-H21)/2 -> -4.5 | J21: =(E21-F21)/2 -> 4 | K21: =MAX(1,MIN(10,ROUNDUP(I21+5,0))) -> 1 | L21: =MAX(1,MIN(10,ROUNDUP(5-J21,0))) -> 1 | M21: =MIN(E21,F21) -> 1 | N21: lexicon | O21: 0 | P21: 0 | Q21: spring chicken, young person, younker | T21: juvenile (is-a), blade (kind-of), pupil (kind-of), puppy (kind-of), young (definition), man (definition), boy (definition), collectively (definition)
A22: brothers | B22: biological | C22: person | E22: 9 | F22: 1 | G22: 1 | H22: 10 | I22: =(G22-H22)/2 -> -4.5 | J22: =(E22-F22)/2 -> 4 | K22: =MAX(1,MIN(10,ROUNDUP(I22+5,0))) -> 1 | L22: =MAX(1,MIN(10,ROUNDUP(5-J22,0))) -> 1 | M22: =MIN(E22,F22) -> 1 | N22: lexicon | O22: 0.04 | P22: 0 | Q22: blood brother, brother | T22: male (definition), parent (definition), member (is-a), mason (kind-of), brotherhood (part), fellow (definition), religion (definition)
A23: ma | B23: biological | C23: person | E23: 10 | F23: 1 | G23: 1 | H23: 10 | I23: =(G23-H23)/2 -> -4.5 | J23: =(E23-F23)/2 -> 4.5 | K23: =MAX(1,MIN(10,ROUNDUP(I23+5,0))) -> 1 | L23: =MAX(1,MIN(10,ROUNDUP(5-J23,0))) -> 1 | M23: =MIN(E23,F23) -> 1 | N23: lexicon | O23: 0.29 | P23: 0.04 | Q23: mama, mamma, mammy, mom, momma | T23: mother (is-a), informal (definition), terms (definition), master (definition), degree (definition)
A24: parent | B24: biological | C24: person | E24: 9 | F24: 1 | G24: 1 | H24: 10 | I24: =(G24-H24)/2 -> -4.5 | J24: =(E24-F24)/2 -> 4 | K24: =MAX(1,MIN(10,ROUNDUP(I24+5,0))) -> 1 | L24: =MAX(1,MIN(10,ROUNDUP(5-J24,0))) -> 1 | M24: =MIN(E24,F24) -> 1 | N24: lexicon | O24: 0 | P24: 0 | T24: mother (kind-of), father (kind-of), family (part), parental (derived), give (definition), birth (definition), raise (definition), child (definition), being (is-a) | V24: child
A25: partners | B25: biological | C25: person | E25: 9 | F25: 1 | G25: 1 | H25: 10 | I25: =(G25-H25)/2 -> -4.5 | J25: =(E25-F25)/2 -> 4 | K25: =MAX(1,MIN(10,ROUNDUP(I25+5,0))) -> 1 | L25: =MAX(1,MIN(10,ROUNDUP(5-J25,0))) -> 1 | M25: =MIN(E25,F25) -> 1 | N25: lexicon | O25: 0 | P25: 0 | Q25: better half, married person, mate, partner, spouse | T25: relative (is-a), relation (is-a), wife (kind-of), husband (kind-of), marriage (part), partner (definition), associate (is-a), activity (definition), sphere (definition), common (definition)
A26: sons | B26: biological | C26: person | E26: 9 | F26: 1 | G26: 1 | H26: 10 | I26: =(G26-H26)/2 -> -4.5 | J26: =(E26-F26)/2 -> 4 | K26: =MAX(1,MIN(10,ROUNDUP(I26+5,0))) -> 1 | L26: =MAX(1,MIN(10,ROUNDUP(5-J26,0))) -> 1 | M26: =MIN(E26,F26) -> 1 | N26: lexicon | O26: 0 | P26: 0 | Q26: boy, son | T26: junior (kind-of), male (definition), human (definition), divine (definition), word (definition)
A27: pa | B27: biological | C27: person | E27: 9 | F27: 1 | G27: 1 | H27: 10 | I27: =(G27-H27)/2 -> -4.5 | J27: =(E27-F27)/2 -> 4 | K27: =MAX(1,MIN(10,ROUNDUP(I27+5,0))) -> 1 | L27: =MAX(1,MIN(10,ROUNDUP(5-J27,0))) -> 1 | M27: =MIN(E27,F27) -> 1 | N27: lexicon | O27: 0 | P27: 0 | Q27: dad, dada, daddy, papa, pappa | T27: father (is-a), informal (definition), term (definition), probably (definition), baby (definition), metal (is-a)
A28: babies | B28: biological | C28: person | E28: 9 | F28: 1 | G28: 1 | H28: 10 | I28: =(G28-H28)/2 -> -4.5 | J28: =(E28-F28)/2 -> 4 | K28: =MAX(1,MIN(10,ROUNDUP(I28+5,0))) -> 1 | L28: =MAX(1,MIN(10,ROUNDUP(5-J28,0))) -> 1 | M28: =MIN(E28,F28) -> 1 | N28: lexicon | O28: 0 | P28: 0 | Q28: babe, baby, infant | T28: child (is-a), kid (is-a), newborn (kind-of), young (definition), birth (definition), year (definition), begin (definition), issue (is-a)
A29: uncle | B29: biological | C29: person | E29: 9 | F29: 1 | G29: 1 | H29: 10 | I29: =(G29-H29)/2 -> -4.5 | J29: =(E29-F29)/2 -> 4 | K29: =MAX(1,MIN(10,ROUNDUP(I29+5,0))) -> 1 | L29: =MAX(1,MIN(10,ROUNDUP(5-J29,0))) -> 1 | M29: =MIN(E29,F29) -> 1 | N29: lexicon | O29: 0 | P29: 0 | T29: brother (definition), father (definition), mother (definition), husband (definition) | V29: aunt
A30: sisters | B30: biological | C30: person | E30: 9 | F30: 1 | G30: 1 | H30: 10 | I30: =(G30-H30)/2 -> -4.5 | J30: =(E30-F30)/2 -> 4 | K30: =MAX(1,MIN(10,ROUNDUP(I30+5,0))) -> 1 | L30: =MAX(1,MIN(10,ROUNDUP(5-J30,0))) -> 1 | M30: =MIN(E30,F30) -> 1 | N30: lexicon | O30: 0 | P30: 0 | Q30: sis, sister | T30: female (definition), parent (definition), nun (is-a), roman (definition), catholic (definition)
A31: cousin | B31: biological | C31: person | E31: 9 | F31: 1 | G31: 1 | H31: 10 | I31: =(G31-H31)/2 -> -4.5 | J31: =(E31-F31)/2 -> 4 | K31: =MAX(1,MIN(10,ROUNDUP(I31+5,0))) -> 1 | L31: =MAX(1,MIN(10,ROUNDUP(5-J31,0))) -> 1 | M31: =MIN(E31,F31) -> 1 | N31: lexicon | O31: 0 | P31: 0 | Q31: cousin-german, first cousin, full cousin | T31: relative (is-a), relation (is-a), child (definition), aunt (definition), uncle (definition)
A32: buddy | B32: biological | C32: person | E32: 10 | F32: 1 | G32: 1 | H32: 10 | I32: =(G32-H32)/2 -> -4.5 | J32: =(E32-F32)/2 -> 4.5 | K32: =MAX(1,MIN(10,ROUNDUP(I32+5,0))) -> 1 | L32: =MAX(1,MIN(10,ROUNDUP(5-J32,0))) -> 1 | M32: =MIN(E32,F32) -> 1 | N32: lexicon | O32: 0.12 | P32: 0 | Q32: brother, chum, crony, pal, sidekick | T32: friend (is-a), close (definition), accompany (definition), activity (definition)
A33: participants | B33: biological | C33: person | E33: 9 | F33: 1 | G33: 1 | H33: 10 | I33: =(G33-H33)/2 -> -4.5 | J33: =(E33-F33)/2 -> 4 | K33: =MAX(1,MIN(10,ROUNDUP(I33+5,0))) -> 1 | L33: =MAX(1,MIN(10,ROUNDUP(5-J33,0))) -> 1 | M33: =MIN(E33,F33) -> 1 | N33: lexicon | O33: 0 | P33: 0 | Q33: participant | T33: associate (is-a), bride (kind-of), player (kind-of), take (definition), part (definition), activity (definition), mvp (kind-of), participate (definition)
A34: critics | B34: biological | C34: person | E34: 9 | F34: 1 | G34: 2 | H34: 10 | I34: =(G34-H34)/2 -> -4 | J34: =(E34-F34)/2 -> 4 | K34: =MAX(1,MIN(10,ROUNDUP(I34+5,0))) -> 1 | L34: =MAX(1,MIN(10,ROUNDUP(5-J34,0))) -> 1 | M34: =MIN(E34,F34) -> 1 | N34: lexicon | O34: 0.12 | P34: 0.04 | Q34: critic | T34: professional (is-a), engage (definition), analysis (definition), interpretation (definition), works (definition), judge (is-a), reader (kind-of), referee (kind-of)
A35: daddy | B35: biological | C35: person | E35: 9 | F35: 1 | G35: 1 | H35: 10 | I35: =(G35-H35)/2 -> -4.5 | J35: =(E35-F35)/2 -> 4 | K35: =MAX(1,MIN(10,ROUNDUP(I35+5,0))) -> 1 | L35: =MAX(1,MIN(10,ROUNDUP(5-J35,0))) -> 1 | M35: =MIN(E35,F35) -> 1 | N35: lexicon | O35: 0 | P35: 0 | Q35: dad, dada, pa, papa, pappa | T35: father (is-a), informal (definition), term (definition), probably (definition), baby (definition)
A36: twin | B36: biological | C36: person | E36: 9 | F36: 1 | G36: 1 | H36: 10 | I36: =(G36-H36)/2 -> -4.5 | J36: =(E36-F36)/2 -> 4 | K36: =MAX(1,MIN(10,ROUNDUP(I36+5,0))) -> 1 | L36: =MAX(1,MIN(10,ROUNDUP(5-J36,0))) -> 1 | M36: =MIN(E36,F36) -> 1 | N36: lexicon | O36: 0 | P36: 0 | Q36: Gemini, Twin Falls | T36: born (definition), time (definition), pregnancy (definition), person (is-a), individual (is-a), someone (is-a), sun (definition)
A37: genius | B37: biological | C37: person | E37: 10 | F37: 1 | G37: 2 | H37: 10 | I37: =(G37-H37)/2 -> -4 | J37: =(E37-F37)/2 -> 4.5 | K37: =MAX(1,MIN(10,ROUNDUP(I37+5,0))) -> 1 | L37: =MAX(1,MIN(10,ROUNDUP(5-J37,0))) -> 1 | M37: =MIN(E37,F37) -> 1 | N37: lexicon | O37: 0.46 | P37: 0 | Q37: Einstein, brain, brainiac, mastermind | T37: intellectual (is-a), exceptional (definition), ability (definition), intelligence (is-a), unusual (definition), mental (definition)
A38: teen | B38: biological | C38: person | E38: 9 | F38: 1 | G38: 1 | H38: 10 | I38: =(G38-H38)/2 -> -4.5 | J38: =(E38-F38)/2 -> 4 | K38: =MAX(1,MIN(10,ROUNDUP(I38+5,0))) -> 1 | L38: =MAX(1,MIN(10,ROUNDUP(5-J38,0))) -> 1 | M38: =MIN(E38,F38) -> 1 | N38: lexicon | O38: 0 | P38: 0 | Q38: adolescent, stripling, teenager | T38: juvenile (is-a), punk (kind-of), maturity (definition)
A39: mothers | B39: biological | C39: person | E39: 9 | F39: 1 | G39: 1 | H39: 10 | I39: =(G39-H39)/2 -> -4.5 | J39: =(E39-F39)/2 -> 4 | K39: =MAX(1,MIN(10,ROUNDUP(I39+5,0))) -> 1 | L39: =MAX(1,MIN(10,ROUNDUP(5-J39,0))) -> 1 | M39: =MIN(E39,F39) -> 1 | N39: lexicon | O39: 0 | P39: 0 | Q39: female parent, mother | T39: parent (is-a), ma (kind-of), mama (kind-of), mommy (kind-of), woman (definition), given (definition), birth (definition), child (definition)
A40: colleagues | B40: biological | C40: person | E40: 9 | F40: 1 | G40: 1 | H40: 10 | I40: =(G40-H40)/2 -> -4.5 | J40: =(E40-F40)/2 -> 4 | K40: =MAX(1,MIN(10,ROUNDUP(I40+5,0))) -> 1 | L40: =MAX(1,MIN(10,ROUNDUP(5-J40,0))) -> 1 | M40: =MIN(E40,F40) -> 1 | N40: lexicon | O40: 0 | P40: 0.06 | Q40: co-worker, colleague, fellow worker, workfellow | T40: associate (is-a), works (definition), member (definition), class (definition), profession (definition)
A41: daughters | B41: biological | C41: person | E41: 9 | F41: 1 | G41: 1 | H41: 10 | I41: =(G41-H41)/2 -> -4.5 | J41: =(E41-F41)/2 -> 4 | K41: =MAX(1,MIN(10,ROUNDUP(I41+5,0))) -> 1 | L41: =MAX(1,MIN(10,ROUNDUP(5-J41,0))) -> 1 | M41: =MIN(E41,F41) -> 1 | N41: lexicon | O41: 0 | P41: 0 | Q41: daughter, girl | T41: female (definition), human (definition)
... A43: mama | B43: biological | C43: person | E43: 10 | F43: 1 | G43: 1 | H43: 10 | I43: =(G43-H43)/2 -> -4.5 | J43: =(E43-F43)/2 -> 4.5 | K43: =MAX(1,MIN(10,ROUNDUP(I43+5,0))) -> 1 | L43: =MAX(1,MIN(10,ROUNDUP(5-J43,0))) -> 1 | M43: =MIN(E43,F43) -> 1 | N43: lexicon | O43: 0.44 | P43: 0 | Q43: ma, mamma, mammy, mom, momma | T43: mother (is-a), informal (definition), terms (definition), name (definition), worship (definition)
A44: poet | B44: biological | C44: person | E44: 10 | F44: 1 | G44: 2 | H44: 10 | I44: =(G44-H44)/2 -> -4 | J44: =(E44-F44)/2 -> 4.5 | K44: =MAX(1,MIN(10,ROUNDUP(I44+5,0))) -> 1 | L44: =MAX(1,MIN(10,ROUNDUP(5-J44,0))) -> 1 | M44: =MIN(E44,F44) -> 1 | N44: lexicon | O44: 0.5 | P44: 0 | T44: author (is-a), writer (is-a), poem (definition), term (definition), reserve (definition), good (definition)
A45: aunt | B45: biological | C45: person | E45: 9 | F45: 1 | G45: 1 | H45: 10 | I45: =(G45-H45)/2 -> -4.5 | J45: =(E45-F45)/2 -> 4 | K45: =MAX(1,MIN(10,ROUNDUP(I45+5,0))) -> 1 | L45: =MAX(1,MIN(10,ROUNDUP(5-J45,0))) -> 1 | M45: =MIN(E45,F45) -> 1 | N45: lexicon | O45: 0 | P45: 0 | Q45: auntie, aunty | T45: sister (definition), father (definition), mother (definition), wife (definition) | V45: uncle
A46: associates | B46: biological | C46: person | E46: 9 | F46: 1 | G46: 1 | H46: 10 | I46: =(G46-H46)/2 -> -4.5 | J46: =(E46-F46)/2 -> 4 | K46: =MAX(1,MIN(10,ROUNDUP(I46+5,0))) -> 1 | L46: =MAX(1,MIN(10,ROUNDUP(5-J46,0))) -> 1 | M46: =MIN(E46,F46) -> 1 | N46: lexicon | O46: 0 | P46: 0 | Q46: associate | T46: peer (is-a), equal (is-a), match (is-a), member (kind-of), fellow (kind-of), colleague (kind-of), association (part), join (definition), activity (definition), friend (definition), frequently (definition)
A47: grandmother | B47: biological | C47: person | E47: 9 | F47: 1 | G47: 1 | H47: 10 | I47: =(G47-H47)/2 -> -4.5 | J47: =(E47-F47)/2 -> 4 | K47: =MAX(1,MIN(10,ROUNDUP(I47+5,0))) -> 1 | L47: =MAX(1,MIN(10,ROUNDUP(5-J47,0))) -> 1 | M47: =MIN(E47,F47) -> 1 | N47: lexicon | O47: 0 | P47: 0 | Q47: gran, grandma, grannie, granny, nan | T47: mother (definition), father (definition)
A48: companion | B48: biological | C48: person | E48: 9 | F48: 1 | G48: 1 | H48: 10 | I48: =(G48-H48)/2 -> -4.5 | J48: =(E48-F48)/2 -> 4 | K48: =MAX(1,MIN(10,ROUNDUP(I48+5,0))) -> 1 | L48: =MAX(1,MIN(10,ROUNDUP(5-J48,0))) -> 1 | M48: =MIN(E48,F48) -> 1 | N48: lexicon | O48: 0 | P48: 0 | Q48: associate, comrade, familiar, fellow | T48: friend (is-a), date (kind-of), escort (kind-of), frequently (definition), company (definition), accompany (definition)
A49: babe | B49: biological | C49: person | E49: 9 | F49: 1 | G49: 1 | H49: 10 | I49: =(G49-H49)/2 -> -4.5 | J49: =(E49-F49)/2 -> 4 | K49: =MAX(1,MIN(10,ROUNDUP(I49+5,0))) -> 1 | L49: =MAX(1,MIN(10,ROUNDUP(5-J49,0))) -> 1 | M49: =MIN(E49,F49) -> 1 | N49: lexicon | O49: 0.06 | P49: 0.06 | Q49: baby, infant | T49: child (is-a), kid (is-a), newborn (kind-of), young (definition), birth (definition), year (definition), begin (definition), girl (is-a)
A50: grandma | B50: biological | C50: person | E50: 9 | F50: 1 | G50: 1 | H50: 10 | I50: =(G50-H50)/2 -> -4.5 | J50: =(E50-F50)/2 -> 4 | K50: =MAX(1,MIN(10,ROUNDUP(I50+5,0))) -> 1 | L50: =MAX(1,MIN(10,ROUNDUP(5-J50,0))) -> 1 | M50: =MIN(E50,F50) -> 1 | N50: lexicon | O50: 0 | P50: 0 | Q50: gran, grandmother, grannie, granny, nan | T50: mother (definition), father (definition)
A51: oracle | B51: biological | C51: person | E51: 9 | F51: 1 | G51: 2 | H51: 10 | I51: =(G51-H51)/2 -> -4 | J51: =(E51-F51)/2 -> 4 | K51: =MAX(1,MIN(10,ROUNDUP(I51+5,0))) -> 1 | L51: =MAX(1,MIN(10,ROUNDUP(5-J51,0))) -> 1 | M51: =MIN(E51,F51) -> 1 | N51: lexicon | O51: 0.12 | P51: 0 | Q51: prophesier, prophet, seer, vaticinator | T51: divine (definition), future (definition), prophecy (is-a), obscure (definition), reveal (definition)
A52: alchemist | B52: biological | C52: person | E52: 9 | F52: 1 | G52: 2 | H52: 10 | I52: =(G52-H52)/2 -> -4 | J52: =(E52-F52)/2 -> 4 | K52: =MAX(1,MIN(10,ROUNDUP(I52+5,0))) -> 1 | L52: =MAX(1,MIN(10,ROUNDUP(5-J52,0))) -> 1 | M52: =MIN(E52,F52) -> 1 | N52: lexicon | O52: 0.12 | P52: 0 | T52: intellectual (is-a), practice (definition), seek (definition), life (definition), stone (definition)
A53: darling | B53: biological | C53: person | E53: 9 | F53: 1 | G53: 1 | H53: 10 | I53: =(G53-H53)/2 -> -4.5 | J53: =(E53-F53)/2 -> 4 | K53: =MAX(1,MIN(10,ROUNDUP(I53+5,0))) -> 1 | L53: =MAX(1,MIN(10,ROUNDUP(5-J53,0))) -> 1 | M53: =MIN(E53,F53) -> 1 | N53: lexicon | O53: 0 | P53: 0 | Q53: dearie, deary, ducky, favorite, favourite | T53: lover (is-a), chosen (kind-of), special (definition), love (definition), river (is-a), australia (part), australian (definition), murray (definition)
A54: teenager | B54: biological | C54: person | E54: 9 | F54: 1 | G54: 1 | H54: 10 | I54: =(G54-H54)/2 -> -4.5 | J54: =(E54-F54)/2 -> 4 | K54: =MAX(1,MIN(10,ROUNDUP(I54+5,0))) -> 1 | L54: =MAX(1,MIN(10,ROUNDUP(5-J54,0))) -> 1 | M54: =MIN(E54,F54) -> 1 | N54: lexicon | O54: 0 | P54: 0 | Q54: adolescent, stripling, teen | T54: juvenile (is-a), punk (kind-of), maturity (definition)
A55: bride | B55: biological | C55: person | E55: 9 | F55: 1 | G55: 1 | H55: 10 | I55: =(G55-H55)/2 -> -4.5 | J55: =(E55-F55)/2 -> 4 | K55: =MAX(1,MIN(10,ROUNDUP(I55+5,0))) -> 1 | L55: =MAX(1,MIN(10,ROUNDUP(5-J55,0))) -> 1 | M55: =MIN(E55,F55) -> 1 | N55: lexicon | O55: 0 | P55: 0 | Q55: Bridget, Brigid, Saint Bride, Saint Bridget, Saint Brigid | T55: woman (definition), recently (definition), married (definition), saint (is-a), irish (definition)
A56: fathers | B56: biological | C56: person | E56: 9 | F56: 1 | G56: 1 | H56: 10 | I56: =(G56-H56)/2 -> -4.5 | J56: =(E56-F56)/2 -> 4 | K56: =MAX(1,MIN(10,ROUNDUP(I56+5,0))) -> 1 | L56: =MAX(1,MIN(10,ROUNDUP(5-J56,0))) -> 1 | M56: =MIN(E56,F56) -> 1 | N56: lexicon | O56: 0 | P56: 0 | Q56: begetter, father, male parent | T56: parent (is-a), papa (kind-of), pa (kind-of), dad (kind-of), male (definition), term (definition), address (definition), father (definition), root (is-a)
A57: wives | B57: biological | C57: person | E57: 9 | F57: 1 | G57: 1 | H57: 10 | I57: =(G57-H57)/2 -> -4.5 | J57: =(E57-F57)/2 -> 4 | K57: =MAX(1,MIN(10,ROUNDUP(I57+5,0))) -> 1 | L57: =MAX(1,MIN(10,ROUNDUP(5-J57,0))) -> 1 | M57: =MIN(E57,F57) -> 1 | N57: lexicon | O57: 0 | P57: 0 | Q57: married woman, wife | T57: woman (is-a), partner (is-a), spouse (is-a), married (definition), man (definition), marriage (definition)
A58: nephew | B58: biological | C58: person | E58: 9 | F58: 1 | G58: 1 | H58: 10 | I58: =(G58-H58)/2 -> -4.5 | J58: =(E58-F58)/2 -> 4 | K58: =MAX(1,MIN(10,ROUNDUP(I58+5,0))) -> 1 | L58: =MAX(1,MIN(10,ROUNDUP(5-J58,0))) -> 1 | M58: =MIN(E58,F58) -> 1 | N58: lexicon | O58: 0 | P58: 0 | T58: son (definition), brother (definition), sister (definition) | V58: niece
A59: teenagers | B59: biological | C59: person | E59: 9 | F59: 1 | G59: 1 | H59: 10 | I59: =(G59-H59)/2 -> -4.5 | J59: =(E59-F59)/2 -> 4 | K59: =MAX(1,MIN(10,ROUNDUP(I59+5,0))) -> 1 | L59: =MAX(1,MIN(10,ROUNDUP(5-J59,0))) -> 1 | M59: =MIN(E59,F59) -> 1 | N59: lexicon | O59: 0 | P59: 0 | Q59: adolescent, stripling, teen, teenager | T59: juvenile (is-a), punk (kind-of), maturity (definition)
A60: subscribers | B60: biological | C60: person | E60: 9 | F60: 1 | G60: 1 | H60: 10 | I60: =(G60-H60)/2 -> -4.5 | J60: =(E60-F60)/2 -> 4 | K60: =MAX(1,MIN(10,ROUNDUP(I60+5,0))) -> 1 | L60: =MAX(1,MIN(10,ROUNDUP(5-J60,0))) -> 1 | M60: =MIN(E60,F60) -> 1 | N60: lexicon | O60: 0.04 | P60: 0 | Q60: endorser, indorser, ratifier, subscriber | T60: supporter (is-a), champion (is-a), friend (is-a), express (definition), strong (definition), approval (definition), contract (definition)
A61: infant | B61: biological | C61: person | E61: 9 | F61: 1 | G61: 1 | H61: 10 | I61: =(G61-H61)/2 -> -4.5 | J61: =(E61-F61)/2 -> 4 | K61: =MAX(1,MIN(10,ROUNDUP(I61+5,0))) -> 1 | L61: =MAX(1,MIN(10,ROUNDUP(5-J61,0))) -> 1 | M61: =MIN(E61,F61) -> 1 | N61: lexicon | O61: 0 | P61: 0 | Q61: babe, baby | T61: child (is-a), kid (is-a), newborn (kind-of), young (definition), birth (definition), year (definition), begin (definition)
A62: pal | B62: biological | C62: person | E62: 10 | F62: 1 | G62: 1 | H62: 10 | I62: =(G62-H62)/2 -> -4.5 | J62: =(E62-F62)/2 -> 4.5 | K62: =MAX(1,MIN(10,ROUNDUP(I62+5,0))) -> 1 | L62: =MAX(1,MIN(10,ROUNDUP(5-J62,0))) -> 1 | M62: =MIN(E62,F62) -> 1 | N62: lexicon | O62: 0.12 | P62: 0 | Q62: brother, buddy, chum, crony, sidekick | T62: friend (is-a), close (definition), accompany (definition), buddy (definition), activity (definition)
A63: successor | B63: biological | C63: person | E63: 9 | F63: 1 | G63: 1 | H63: 10 | I63: =(G63-H63)/2 -> -4.5 | J63: =(E63-F63)/2 -> 4 | K63: =MAX(1,MIN(10,ROUNDUP(I63+5,0))) -> 1 | L63: =MAX(1,MIN(10,ROUNDUP(5-J63,0))) -> 1 | M63: =MIN(E63,F63) -> 1 | N63: lexicon | O63: 0 | P63: 0 | Q63: replacement | T63: peer (is-a), equal (is-a), match (is-a), succeed (derived), follow (definition), next (definition), order (definition), immediately (definition)
A64: ancestors | B64: biological | C64: person | E64: 9 | F64: 1 | G64: 1 | H64: 10 | I64: =(G64-H64)/2 -> -4.5 | J64: =(E64-F64)/2 -> 4 | K64: =MAX(1,MIN(10,ROUNDUP(I64+5,0))) -> 1 | L64: =MAX(1,MIN(10,ROUNDUP(5-J64,0))) -> 1 | M64: =MIN(E64,F64) -> 1 | N64: lexicon | O64: 0 | P64: 0 | Q64: ancestor, antecedent, ascendant, ascendent, root | T64: relative (is-a), relation (is-a), father (kind-of), remote (definition)
A65: colleague | B65: biological | C65: person | E65: 9 | F65: 1 | G65: 1 | H65: 10 | I65: =(G65-H65)/2 -> -4.5 | J65: =(E65-F65)/2 -> 4 | K65: =MAX(1,MIN(10,ROUNDUP(I65+5,0))) -> 1 | L65: =MAX(1,MIN(10,ROUNDUP(5-J65,0))) -> 1 | M65: =MIN(E65,F65) -> 1 | N65: lexicon | O65: 0 | P65: 0.06 | Q65: co-worker, fellow worker, workfellow | T65: associate (is-a), works (definition), member (definition), class (definition), profession (definition)
A66: teammates | B66: biological | C66: person | E66: 9 | F66: 1 | G66: 1 | H66: 10 | I66: =(G66-H66)/2 -> -4.5 | J66: =(E66-F66)/2 -> 4 | K66: =MAX(1,MIN(10,ROUNDUP(I66+5,0))) -> 1 | L66: =MAX(1,MIN(10,ROUNDUP(5-J66,0))) -> 1 | M66: =MIN(E66,F66) -> 1 | N66: lexicon | O66: 0 | P66: 0 | Q66: mate, teammate | T66: associate (is-a), fellow (definition), member (definition), team (definition)
A67: cousins | B67: biological | C67: person | E67: 9 | F67: 1 | G67: 1 | H67: 10 | I67: =(G67-H67)/2 -> -4.5 | J67: =(E67-F67)/2 -> 4 | K67: =MAX(1,MIN(10,ROUNDUP(I67+5,0))) -> 1 | L67: =MAX(1,MIN(10,ROUNDUP(5-J67,0))) -> 1 | M67: =MIN(E67,F67) -> 1 | N67: lexicon | O67: 0 | P67: 0 | Q67: cousin, cousin-german, first cousin, full cousin | T67: relative (is-a), relation (is-a), child (definition), aunt (definition), uncle (definition)
A68: critic | B68: biological | C68: person | E68: 9 | F68: 1 | G68: 2 | H68: 10 | I68: =(G68-H68)/2 -> -4 | J68: =(E68-F68)/2 -> 4 | K68: =MAX(1,MIN(10,ROUNDUP(I68+5,0))) -> 1 | L68: =MAX(1,MIN(10,ROUNDUP(5-J68,0))) -> 1 | M68: =MIN(E68,F68) -> 1 | N68: lexicon | O68: 0.12 | P68: 0.04 | T68: professional (is-a), critical (derived), engage (definition), analysis (definition), interpretation (definition), works (definition), judge (is-a), reader (kind-of), referee (kind-of)
A69: spouse | B69: biological | C69: person | E69: 9 | F69: 1 | G69: 1 | H69: 10 | I69: =(G69-H69)/2 -> -4.5 | J69: =(E69-F69)/2 -> 4 | K69: =MAX(1,MIN(10,ROUNDUP(I69+5,0))) -> 1 | L69: =MAX(1,MIN(10,ROUNDUP(5-J69,0))) -> 1 | M69: =MIN(E69,F69) -> 1 | N69: lexicon | O69: 0 | P69: 0 | Q69: better half, married person, mate, partner | T69: relative (is-a), relation (is-a), wife (kind-of), husband (kind-of), marriage (part), partner (definition)
A70: pops | B70: biological | C70: person | E70: 9 | F70: 1 | G70: 1 | H70: 10 | I70: =(G70-H70)/2 -> -4.5 | J70: =(E70-F70)/2 -> 4 | K70: =MAX(1,MIN(10,ROUNDUP(I70+5,0))) -> 1 | L70: =MAX(1,MIN(10,ROUNDUP(5-J70,0))) -> 1 | M70: =MIN(E70,F70) -> 1 | N70: lexicon | O70: 0 | P70: 0 | Q70: dad, dada, daddy, pa, papa, pappa | T70: father (is-a), informal (definition), term (definition), probably (definition), baby (definition)
A71: mentor | B71: biological | C71: person | E71: 10 | F71: 1 | G71: 2 | H71: 10 | I71: =(G71-H71)/2 -> -4 | J71: =(E71-F71)/2 -> 4.5 | K71: =MAX(1,MIN(10,ROUNDUP(I71+5,0))) -> 1 | L71: =MAX(1,MIN(10,ROUNDUP(5-J71,0))) -> 1 | M71: =MIN(E71,F71) -> 1 | N71: lexicon | O71: 0.38 | P71: 0 | Q71: wise man | T71: intellectual (is-a), sage (kind-of), wise (definition), trust (definition), guide (definition), advisor (definition)
A72: papa | B72: biological | C72: person | E72: 9 | F72: 1 | G72: 1 | H72: 10 | I72: =(G72-H72)/2 -> -4.5 | J72: =(E72-F72)/2 -> 4 | K72: =MAX(1,MIN(10,ROUNDUP(I72+5,0))) -> 1 | L72: =MAX(1,MIN(10,ROUNDUP(5-J72,0))) -> 1 | M72: =MIN(E72,F72) -> 1 | N72: lexicon | O72: 0 | P72: 0 | Q72: dad, dada, daddy, pa, pappa | T72: father (is-a), informal (definition), term (definition), probably (definition), baby (definition)
A73: mommy | B73: biological | C73: person | E73: 10 | F73: 1 | G73: 1 | H73: 10 | I73: =(G73-H73)/2 -> -4.5 | J73: =(E73-F73)/2 -> 4.5 | K73: =MAX(1,MIN(10,ROUNDUP(I73+5,0))) -> 1 | L73: =MAX(1,MIN(10,ROUNDUP(5-J73,0))) -> 1 | M73: =MIN(E73,F73) -> 1 | N73: lexicon | O73: 0.88 | P73: 0 | Q73: ma, mama, mamma, mammy, mom, momma | T73: mother (is-a), informal (definition), terms (definition)
A74: grandparents | B74: biological | C74: person | E74: 9 | F74: 1 | G74: 1 | H74: 10 | I74: =(G74-H74)/2 -> -4.5 | J74: =(E74-F74)/2 -> 4 | K74: =MAX(1,MIN(10,ROUNDUP(I74+5,0))) -> 1 | L74: =MAX(1,MIN(10,ROUNDUP(5-J74,0))) -> 1 | M74: =MIN(E74,F74) -> 1 | N74: lexicon | O74: 0 | P74: 0 | Q74: grandparent | T74: grandmother (kind-of), grandfather (kind-of), grandma (kind-of), parent (definition), father (definition), mother (definition)
A75: mistress | B75: biological | C75: person | E75: 9 | F75: 1 | G75: 1 | H75: 10 | I75: =(G75-H75)/2 -> -4.5 | J75: =(E75-F75)/2 -> 4 | K75: =MAX(1,MIN(10,ROUNDUP(I75+5,0))) -> 1 | L75: =MAX(1,MIN(10,ROUNDUP(5-J75,0))) -> 1 | M75: =MIN(E75,F75) -> 1 | N75: lexicon | O75: 0 | P75: 0 | Q75: fancy woman, kept woman | T75: woman (is-a), lover (is-a), ongoing (definition), sexual (definition), relationship (definition), man (definition)
A76: grandson | B76: biological | C76: person | E76: 9 | F76: 1 | G76: 1 | H76: 10 | I76: =(G76-H76)/2 -> -4.5 | J76: =(E76-F76)/2 -> 4 | K76: =MAX(1,MIN(10,ROUNDUP(I76+5,0))) -> 1 | L76: =MAX(1,MIN(10,ROUNDUP(5-J76,0))) -> 1 | M76: =MIN(E76,F76) -> 1 | N76: lexicon | O76: 0 | P76: 0 | T76: male (definition)
A77: poets | B77: biological | C77: person | E77: 10 | F77: 1 | G77: 2 | H77: 10 | I77: =(G77-H77)/2 -> -4 | J77: =(E77-F77)/2 -> 4.5 | K77: =MAX(1,MIN(10,ROUNDUP(I77+5,0))) -> 1 | L77: =MAX(1,MIN(10,ROUNDUP(5-J77,0))) -> 1 | M77: =MIN(E77,F77) -> 1 | N77: lexicon | O77: 0.5 | P77: 0 | Q77: poet | T77: author (is-a), writer (is-a), poem (definition), term (definition), reserve (definition), good (definition)
A78: teammate | B78: biological | C78: person | E78: 9 | F78: 1 | G78: 1 | H78: 10 | I78: =(G78-H78)/2 -> -4.5 | J78: =(E78-F78)/2 -> 4 | K78: =MAX(1,MIN(10,ROUNDUP(I78+5,0))) -> 1 | L78: =MAX(1,MIN(10,ROUNDUP(5-J78,0))) -> 1 | M78: =MIN(E78,F78) -> 1 | N78: lexicon | O78: 0 | P78: 0 | Q78: mate | T78: associate (is-a), fellow (definition), member (definition), team (definition)
A79: niece | B79: biological | C79: person | E79: 9 | F79: 1 | G79: 1 | H79: 10 | I79: =(G79-H79)/2 -> -4.5 | J79: =(E79-F79)/2 -> 4 | K79: =MAX(1,MIN(10,ROUNDUP(I79+5,0))) -> 1 | L79: =MAX(1,MIN(10,ROUNDUP(5-J79,0))) -> 1 | M79: =MIN(E79,F79) -> 1 | N79: lexicon | O79: 0 | P79: 0 | T79: daughter (definition), brother (definition), sister (definition) | V79: nephew
A80: buddies | B80: biological | C80: person | E80: 10 | F80: 1 | G80: 1 | H80: 10 | I80: =(G80-H80)/2 -> -4.5 | J80: =(E80-F80)/2 -> 4.5 | K80: =MAX(1,MIN(10,ROUNDUP(I80+5,0))) -> 1 | L80: =MAX(1,MIN(10,ROUNDUP(5-J80,0))) -> 1 | M80: =MIN(E80,F80) -> 1 | N80: lexicon | O80: 0.12 | P80: 0 | Q80: brother, buddy, chum, crony, pal, sidekick | T80: friend (is-a), close (definition), accompany (definition), buddy (definition), activity (definition)
A81: roommate | B81: biological | C81: person | E81: 9 | F81: 1 | G81: 1 | H81: 10 | I81: =(G81-H81)/2 -> -4.5 | J81: =(E81-F81)/2 -> 4 | K81: =MAX(1,MIN(10,ROUNDUP(I81+5,0))) -> 1 | L81: =MAX(1,MIN(10,ROUNDUP(5-J81,0))) -> 1 | M81: =MIN(E81,F81) -> 1 | N81: lexicon | O81: 0 | P81: 0 | Q81: roomie, roomy | T81: friend (is-a), associate (definition), share (definition), room (definition)
A82: companions | B82: biological | C82: person | E82: 9 | F82: 1 | G82: 1 | H82: 10 | I82: =(G82-H82)/2 -> -4.5 | J82: =(E82-F82)/2 -> 4 | K82: =MAX(1,MIN(10,ROUNDUP(I82+5,0))) -> 1 | L82: =MAX(1,MIN(10,ROUNDUP(5-J82,0))) -> 1 | M82: =MIN(E82,F82) -> 1 | N82: lexicon | O82: 0 | P82: 0 | Q82: associate, companion, comrade, familiar, fellow | T82: friend (is-a), date (kind-of), escort (kind-of), frequently (definition), company (definition), accompany (definition)
A83: grandchildren | B83: biological | C83: person | E83: 9 | F83: 1 | G83: 1 | H83: 10 | I83: =(G83-H83)/2 -> -4.5 | J83: =(E83-F83)/2 -> 4 | K83: =MAX(1,MIN(10,ROUNDUP(I83+5,0))) -> 1 | L83: =MAX(1,MIN(10,ROUNDUP(5-J83,0))) -> 1 | M83: =MIN(E83,F83) -> 1 | N83: lexicon | O83: 0 | P83: 0 | Q83: grandchild | T83: issue (is-a), grandson (kind-of), child (definition), son (definition), daughter (definition)
A84: participant | B84: biological | C84: person | E84: 9 | F84: 1 | G84: 1 | H84: 10 | I84: =(G84-H84)/2 -> -4.5 | J84: =(E84-F84)/2 -> 4 | K84: =MAX(1,MIN(10,ROUNDUP(I84+5,0))) -> 1 | L84: =MAX(1,MIN(10,ROUNDUP(5-J84,0))) -> 1 | M84: =MIN(E84,F84) -> 1 | N84: lexicon | O84: 0 | P84: 0 | Q84: player | T84: associate (is-a), bride (kind-of), player (kind-of), participate (derived), take (definition), part (definition), activity (definition), mvp (kind-of), skilled (definition)
A85: girlfriend | B85: biological | C85: person | E85: 9 | F85: 1 | G85: 1 | H85: 10 | I85: =(G85-H85)/2 -> -4.5 | J85: =(E85-F85)/2 -> 4 | K85: =MAX(1,MIN(10,ROUNDUP(I85+5,0))) -> 1 | L85: =MAX(1,MIN(10,ROUNDUP(5-J85,0))) -> 1 | M85: =MIN(E85,F85) -> 1 | N85: lexicon | O85: 0 | P85: 0 | Q85: girl, lady friend | T85: friend (is-a), woman (is-a), female (definition), lover (is-a), girl (definition), young (definition), man (definition)
A86: boyfriend | B86: biological | C86: person | E86: 9 | F86: 1 | G86: 1 | H86: 10 | I86: =(G86-H86)/2 -> -4.5 | J86: =(E86-F86)/2 -> 4 | K86: =MAX(1,MIN(10,ROUNDUP(I86+5,0))) -> 1 | L86: =MAX(1,MIN(10,ROUNDUP(5-J86,0))) -> 1 | M86: =MIN(E86,F86) -> 1 | N86: lexicon | O86: 0 | P86: 0 | Q86: beau, fellow, swain, young man | T86: man (is-a), lover (is-a), girl (definition), young (definition), woman (definition)
A87: siblings | B87: biological | C87: person | E87: 9 | F87: 1 | G87: 1 | H87: 10 | I87: =(G87-H87)/2 -> -4.5 | J87: =(E87-F87)/2 -> 4 | K87: =MAX(1,MIN(10,ROUNDUP(I87+5,0))) -> 1 | L87: =MAX(1,MIN(10,ROUNDUP(5-J87,0))) -> 1 | M87: =MIN(E87,F87) -> 1 | N87: lexicon | O87: 0 | P87: 0 | Q87: sib, sibling | T87: relative (is-a), relation (is-a), twin (kind-of), family (part), brother (definition), sister (definition)
A88: affiliate | B88: biological | C88: person | E88: 9 | F88: 1 | G88: 1 | H88: 10 | I88: =(G88-H88)/2 -> -4.5 | J88: =(E88-F88)/2 -> 4 | K88: =MAX(1,MIN(10,ROUNDUP(I88+5,0))) -> 1 | L88: =MAX(1,MIN(10,ROUNDUP(5-J88,0))) -> 1 | M88: =MIN(E88,F88) -> 1 | N88: lexicon | O88: 0 | P88: 0 | T88: associate (is-a), subsidiary (definition), organization (definition), organisation (is-a)
A89: moms | B89: biological | C89: person | E89: 10 | F89: 1 | G89: 1 | H89: 10 | I89: =(G89-H89)/2 -> -4.5 | J89: =(E89-F89)/2 -> 4.5 | K89: =MAX(1,MIN(10,ROUNDUP(I89+5,0))) -> 1 | L89: =MAX(1,MIN(10,ROUNDUP(5-J89,0))) -> 1 | M89: =MIN(E89,F89) -> 1 | N89: lexicon | O89: 0.88 | P89: 0 | Q89: ma, mama, mamma, mammy, mom, momma | T89: mother (is-a), informal (definition), terms (definition)
A90: superstar | B90: biological | C90: person | E90: 9 | F90: 1 | G90: 2 | H90: 10 | I90: =(G90-H90)/2 -> -4 | J90: =(E90-F90)/2 -> 4 | K90: =MAX(1,MIN(10,ROUNDUP(I90+5,0))) -> 1 | L90: =MAX(1,MIN(10,ROUNDUP(5-J90,0))) -> 1 | M90: =MIN(E90,F90) -> 1 | N90: lexicon | O90: 0.12 | P90: 0 | Q90: ace, adept, champion, genius, hotshot, maven | T90: expert (is-a), skilled (definition), field (definition)
A91: toddler | B91: biological | C91: person | E91: 9 | F91: 1 | G91: 1 | H91: 10 | I91: =(G91-H91)/2 -> -4.5 | J91: =(E91-F91)/2 -> 4 | K91: =MAX(1,MIN(10,ROUNDUP(I91+5,0))) -> 1 | L91: =MAX(1,MIN(10,ROUNDUP(5-J91,0))) -> 1 | M91: =MIN(E91,F91) -> 1 | N91: lexicon | O91: 0 | P91: 0 | Q91: bambino, tot, yearling | T91: child (is-a), kid (is-a), minor (is-a), young (definition)
A92: grandpa | B92: biological | C92: person | E92: 9 | F92: 1 | G92: 1 | H92: 10 | I92: =(G92-H92)/2 -> -4.5 | J92: =(E92-F92)/2 -> 4 | K92: =MAX(1,MIN(10,ROUNDUP(I92+5,0))) -> 1 | L92: =MAX(1,MIN(10,ROUNDUP(5-J92,0))) -> 1 | M92: =MIN(E92,F92) -> 1 | N92: lexicon | O92: 0 | P92: 0 | Q92: gramps, grandad, granddad, granddaddy, grandfather | T92: father (definition), mother (definition)
A93: father | B93: biological | C93: person | E93: 9 | F93: 1 | G93: 3 | H93: 9 | I93: =(G93-H93)/2 -> -3 | J93: =(E93-F93)/2 -> 4 | K93: =MAX(1,MIN(10,ROUNDUP(I93+5,0))) -> 2 | L93: =MAX(1,MIN(10,ROUNDUP(5-J93,0))) -> 1 | M93: =MIN(E93,F93) -> 1 | N93: concept+lexicon | O93: 0 | P93: 0 | Q93: begetter, male parent | R93: identity, family | T93: parent (is-a), papa (kind-of), pa (kind-of), dad (kind-of), male (definition), term (definition), address (definition), root (is-a), founder (definition) | V93: mother
A94: mother | B94: biological | C94: person | E94: 9 | F94: 1 | G94: 3 | H94: 9 | I94: =(G94-H94)/2 -> -3 | J94: =(E94-F94)/2 -> 4 | K94: =MAX(1,MIN(10,ROUNDUP(I94+5,0))) -> 2 | L94: =MAX(1,MIN(10,ROUNDUP(5-J94,0))) -> 1 | M94: =MIN(E94,F94) -> 1 | N94: concept+lexicon | O94: 0 | P94: 0 | Q94: female parent | R94: identity, family | T94: parent (is-a), ma (kind-of), mama (kind-of), mommy (kind-of), woman (definition), given (definition), birth (definition), child (definition) | V94: father
A95: santa | B95: biological | C95: person | E95: 9 | F95: 1 | G95: 3 | H95: 8 | I95: =(G95-H95)/2 -> -2.5 | J95: =(E95-F95)/2 -> 4 | K95: =MAX(1,MIN(10,ROUNDUP(I95+5,0))) -> 3 | L95: =MAX(1,MIN(10,ROUNDUP(5-J95,0))) -> 1 | M95: =MIN(E95,F95) -> 1 | N95: lexicon | O95: 0.25 | P95: 0 | Q95: Father Christmas, Kriss Kringle, Saint Nicholas, Saint Nick, Santa Claus | T95: legendary (definition), saint (definition), child (definition), imaginary (definition)
A96: researchers | B96: biological | C96: person | E96: 10 | F96: 1 | G96: 3 | H96: 8 | I96: =(G96-H96)/2 -> -2.5 | J96: =(E96-F96)/2 -> 4.5 | K96: =MAX(1,MIN(10,ROUNDUP(I96+5,0))) -> 3 | L96: =MAX(1,MIN(10,ROUNDUP(5-J96,0))) -> 1 | M96: =MIN(E96,F96) -> 1 | N96: lexicon | O96: 1 | P96: 0 | Q96: investigator, research worker, researcher | T96: scientist (is-a), himself (definition), do (definition), research (definition)
A97: masters | B97: biological | C97: person | E97: 9 | F97: 1 | G97: 3 | H97: 8 | I97: =(G97-H97)/2 -> -2.5 | J97: =(E97-F97)/2 -> 4 | K97: =MAX(1,MIN(10,ROUNDUP(I97+5,0))) -> 3 | L97: =MAX(1,MIN(10,ROUNDUP(5-J97,0))) -> 1 | M97: =MIN(E97,F97) -> 1 | N97: lexicon | O97: 0.33 | P97: 0 | Q97: Edgar Lee Masters | T97: poet (is-a), unite (definition), state (definition), artist (is-a), skill (definition)
A98: fool | B98: biological | C98: person | E98: 9 | F98: 1 | G98: 3 | H98: 8 | I98: =(G98-H98)/2 -> -2.5 | J98: =(E98-F98)/2 -> 4 | K98: =MAX(1,MIN(10,ROUNDUP(I98+5,0))) -> 3 | L98: =MAX(1,MIN(10,ROUNDUP(5-J98,0))) -> 1 | M98: =MIN(E98,F98) -> 1 | N98: lexicon | O98: 0.25 | P98: 0.04 | Q98: muggins, sap, saphead, tomfool | T98: simple (is-a), ass (kind-of), clown (kind-of), goose (kind-of), lack (definition), good (definition), judgment (definition), victim (is-a), easy (definition)
A99: researcher | B99: biological | C99: person | E99: 10 | F99: 1 | G99: 3 | H99: 8 | I99: =(G99-H99)/2 -> -2.5 | J99: =(E99-F99)/2 -> 4.5 | K99: =MAX(1,MIN(10,ROUNDUP(I99+5,0))) -> 3 | L99: =MAX(1,MIN(10,ROUNDUP(5-J99,0))) -> 1 | M99: =MIN(E99,F99) -> 1 | N99: lexicon | O99: 1 | P99: 0 | Q99: investigator, research worker | T99: scientist (is-a), research (derived), himself (definition), do (definition)
A100: fools | B100: biological | C100: person | E100: 9 | F100: 1 | G100: 3 | H100: 8 | I100: =(G100-H100)/2 -> -2.5 | J100: =(E100-F100)/2 -> 4 | K100: =MAX(1,MIN(10,ROUNDUP(I100+5,0))) -> 3 | L100: =MAX(1,MIN(10,ROUNDUP(5-J100,0))) -> 1 | M100: =MIN(E100,F100) -> 1 | N100: lexicon | O100: 0.25 | P100: 0.04 | Q100: fool, muggins, sap, saphead, tomfool | T100: simple (is-a), ass (kind-of), clown (kind-of), goose (kind-of), lack (definition), good (definition), judgment (definition), victim (is-a), easy (definition)
A101: investigators | B101: biological | C101: person | E101: 9 | F101: 1 | G101: 3 | H101: 8 | I101: =(G101-H101)/2 -> -2.5 | J101: =(E101-F101)/2 -> 4 | K101: =MAX(1,MIN(10,ROUNDUP(I101+5,0))) -> 3 | L101: =MAX(1,MIN(10,ROUNDUP(5-J101,0))) -> 1 | M101: =MIN(E101,F101) -> 1 | N101: lexicon | O101: 0.33 | P101: 0 | Q101: investigator, research worker, researcher | T101: scientist (is-a), himself (definition), do (definition), research (definition), expert (is-a), detective (kind-of), inspector (kind-of), investigate (definition)
...

Sheet Concepts_nodes
A1: Word | B1: Type | C1: Category | D1: Subtype | E1: V | F1: I | G1: Lv | H1: Gv | I1: x | J1: y | K1: Col | L1: Row | M1: τ | N1: Source | O1: Sent+ | P1: Sent− | Q1: Synonyms | R1: Related (nodes) | S1: Related (labels without a node) | T1: Related (WordNet) | U1: Related (manual) | V1: Opposites
A2: excellent | B2: quality | C2: quality | D2: evaluative | E2: 9 | F2: 1 | G2: 1 | H2: 9 | I2: =(G2-H2)/2 -> -4 | J2: =(E2-F2)/2 -> 4 | K2: =MAX(1,MIN(10,ROUNDUP(I2+5,0))) -> 1 | L2: =MAX(1,MIN(10,ROUNDUP(5-J2,0))) -> 1 | M2: =MIN(E2,F2) -> 1 | N2: lexicon | O2: 1 | P2: 0 | Q2: fantabulous, first-class, splendid | T2: superior (similar), excellence (derived), good (definition), high (definition), quality (definition) | V2: inferior
A3: dream | B3: non_biological | C3: cognition | E3: 10 | F3: 2 | G3: 3 | H3: 8 | I3: =(G3-H3)/2 -> -2.5 | J3: =(E3-F3)/2 -> 4 | K3: =MAX(1,MIN(10,ROUNDUP(I3+5,0))) -> 3 | L3: =MAX(1,MIN(10,ROUNDUP(5-J3,0))) -> 1 | M3: =MIN(E3,F3) -> 2 | N3: lexicon | O3: 0.29 | P3: 0.08 | Q3: dreaming | T3: imagination (is-a), imagery (is-a), imaging (is-a), nightmare (kind-of), sleeping (part), series (definition), mental (definition), image (definition), emotion (definition) | U3: sleep, night, hope, fear, story
A4: passion | B4: non_biological | C4: emotion | E4: 9 | F4: 1 | G4: 8 | H4: 2 | I4: =(G4-H4)/2 -> 3 | J4: =(E4-F4)/2 -> 4 | K4: =MAX(1,MIN(10,ROUNDUP(I4+5,0))) -> 8 | L4: =MAX(1,MIN(10,ROUNDUP(5-J4,0))) -> 1 | M4: =MIN(E4,F4) -> 1 | N4: concept+lexicon | O4: 0.54 | P4: 0.04 | Q4: passionateness | R4: self | T4: feeling (is-a), fire (kind-of), abandon (kind-of), strong (definition), emotion (definition), emotional (definition)
A5: favour | B5: non_biological | C5: emotion | E5: 9 | F5: 1 | G5: 8 | H5: 2 | I5: =(G5-H5)/2 -> 3 | J5: =(E5-F5)/2 -> 4 | K5: =MAX(1,MIN(10,ROUNDUP(I5+5,0))) -> 8 | L5: =MAX(1,MIN(10,ROUNDUP(5-J5,0))) -> 1 | M5: =MIN(E5,F5) -> 1 | N5: concept+lexicon | O5: 0.46 | P5: 0.04 | Q5: favor | R5: self | T5: approval (is-a), feeling (definition), favorable (definition), regard (definition), tendency (is-a), approve (definition)
A6: desired | B6: non_biological | C6: emotion | D6: emotion | E6: 9 | F6: 1 | G6: 8 | H6: 2 | I6: =(G6-H6)/2 -> 3 | J6: =(E6-F6)/2 -> 4 | K6: =MAX(1,MIN(10,ROUNDUP(I6+5,0))) -> 8 | L6: =MAX(1,MIN(10,ROUNDUP(5-J6,0))) -> 1 | M6: =MIN(E6,F6) -> 1 | N6: concept+lexicon | O6: 0.56 | P6: 0 | Q6: desire, want | R6: self
A7: hope | B7: non_biological | C7: emotion | E7: 10 | F7: 1 | G7: 10 | H7: 2 | I7: =(G7-H7)/2 -> 4 | J7: =(E7-F7)/2 -> 4.5 | K7: =MAX(1,MIN(10,ROUNDUP(I7+5,0))) -> 9 | L7: =MAX(1,MIN(10,ROUNDUP(5-J7,0))) -> 1 | M7: =MIN(E7,F7) -> 1 | N7: concept+lexicon | O7: 0.25 | P7: 0.12 | Q7: promise | R7: self | T7: specific (definition), instance (definition), feeling (definition), hopeful (definition), encouragement (kind-of) | U7: future, dream, happy, journey | V7: despair
A8: ambition | B8: non_biological | C8: emotion | E8: 10 | F8: 0 | G8: 10 | H8: 2 | I8: =(G8-H8)/2 -> 4 | J8: =(E8-F8)/2 -> 5 | K8: =MAX(1,MIN(10,ROUNDUP(I8+5,0))) -> 9 | L8: =MAX(1,MIN(10,ROUNDUP(5-J8,0))) -> 1 | M8: =MIN(E8,F8) -> 0 | N8: concept+lexicon | O8: 0.38 | P8: 0.06 | Q8: aspiration, dream | R8: self | T8: desire (is-a), nationalism (kind-of), ambitious (derived), drive (is-a), strong (definition), success (definition)
A9: best | B9: quality | C9: quality | D9: evaluative | E9: 7 | F9: 1 | G9: 1 | H9: 9 | I9: =(G9-H9)/2 -> -4 | J9: =(E9-F9)/2 -> 3 | K9: =MAX(1,MIN(10,ROUNDUP(I9+5,0))) -> 1 | L9: =MAX(1,MIN(10,ROUNDUP(5-J9,0))) -> 2 | M9: =MIN(E9,F9) -> 1 | N9: lexicon | O9: 0.75 | P9: 0 | Q9: better, good | T9: good (similar), superior (similar), top (similar), positive (definition), quality (definition), well (definition), wise (definition) | V9: worst
A10: better | B10: quality | C10: quality | D10: evaluative | E10: 8 | F10: 1 | G10: 1 | H10: 9 | I10: =(G10-H10)/2 -> -4 | J10: =(E10-F10)/2 -> 3.5 | K10: =MAX(1,MIN(10,ROUNDUP(I10+5,0))) -> 1 | L10: =MAX(1,MIN(10,ROUNDUP(5-J10,0))) -> 2 | M10: =MIN(E10,F10) -> 1 | N10: lexicon | O10: 0.83 | P10: 0 | Q10: best | T10: improved (similar), amended (similar), good (definition), superior (definition), class (definition), set (definition), healthier (similar) | V10: worse
A11: nice | B11: quality | C11: quality | D11: evaluative | E11: 8 | F11: 1 | G11: 1 | H11: 9 | I11: =(G11-H11)/2 -> -4 | J11: =(E11-F11)/2 -> 3.5 | K11: =MAX(1,MIN(10,ROUNDUP(I11+5,0))) -> 1 | L11: =MAX(1,MIN(10,ROUNDUP(5-J11,0))) -> 2 | M11: =MIN(E11,F11) -> 1 | N11: lexicon | O11: 0.83 | P11: 0 | Q11: decent, skillful | T11: pleasant (similar), good (similar), nature (definition), appearance (definition), george (definition), socially (definition) | V11: nasty
A12: beautiful | B12: quality | C12: quality | D12: aesthetic | E12: 8 | F12: 1 | G12: 1 | H12: 9 | I12: =(G12-H12)/2 -> -4 | J12: =(E12-F12)/2 -> 3.5 | K12: =MAX(1,MIN(10,ROUNDUP(I12+5,0))) -> 1 | L12: =MAX(1,MIN(10,ROUNDUP(5-J12,0))) -> 2 | M12: =MIN(E12,F12) -> 1 | N12: lexicon | O12: 0.69 | P12: 0 | T12: pretty (similar), lovely (similar), handsome (similar), delight (definition), sense (definition), intellectual (definition), emotional (definition) | V12: ugly, unpleasant
A13: perfect | B13: quality | C13: quality | D13: evaluative | E13: 7 | F13: 1 | G13: 1 | H13: 9 | I13: =(G13-H13)/2 -> -4 | J13: =(E13-F13)/2 -> 3 | K13: =MAX(1,MIN(10,ROUNDUP(I13+5,0))) -> 1 | L13: =MAX(1,MIN(10,ROUNDUP(5-J13,0))) -> 2 | M13: =MIN(E13,F13) -> 1 | N13: lexicon | O13: 0.67 | P13: 0.04 | Q13: arrant, complete, consummate, double-dyed, everlasting, gross | T13: exact (similar), ideal (similar), complete (similar), qualification (definition)
A14: successful | B14: quality | C14: quality | D14: evaluative | E14: 7 | F14: 1 | G14: 1 | H14: 9 | I14: =(G14-H14)/2 -> -4 | J14: =(E14-F14)/2 -> 3 | K14: =MAX(1,MIN(10,ROUNDUP(I14+5,0))) -> 1 | L14: =MAX(1,MIN(10,ROUNDUP(5-J14,0))) -> 2 | M14: =MIN(E14,F14) -> 1 | N14: lexicon | O14: 0.62 | P14: 0 | T14: productive (similar), fortunate (similar), winning (similar), succeed (definition), mark (definition), favorable (definition), outcome (definition)
A15: awesome | B15: quality | C15: quality | D15: evaluative | E15: 8 | F15: 2 | G15: 1 | H15: 9 | I15: =(G15-H15)/2 -> -4 | J15: =(E15-F15)/2 -> 3 | K15: =MAX(1,MIN(10,ROUNDUP(I15+5,0))) -> 1 | L15: =MAX(1,MIN(10,ROUNDUP(5-J15,0))) -> 2 | M15: =MIN(E15,F15) -> 2 | N15: lexicon | O15: 0.88 | P15: 0.12 | Q15: amazing, awe-inspiring, awful, awing | T15: impressive (similar), inspire (definition), awe (definition), wonder (definition)
A16: wonderful | B16: quality | C16: quality | D16: evaluative | E16: 7 | F16: 1 | G16: 1 | H16: 9 | I16: =(G16-H16)/2 -> -4 | J16: =(E16-F16)/2 -> 3 | K16: =MAX(1,MIN(10,ROUNDUP(I16+5,0))) -> 1 | L16: =MAX(1,MIN(10,ROUNDUP(5-J16,0))) -> 2 | M16: =MIN(E16,F16) -> 1 | N16: lexicon | O16: 0.75 | P16: 0 | Q16: fantastic, grand, howling, marvellous, marvelous, rattling | T16: extraordinary (similar), good (definition), great (definition) | V16: ordinary
A17: lucky | B17: quality | C17: quality | D17: evaluative | E17: 8 | F17: 1 | G17: 1 | H17: 9 | I17: =(G17-H17)/2 -> -4 | J17: =(E17-F17)/2 -> 3.5 | K17: =MAX(1,MIN(10,ROUNDUP(I17+5,0))) -> 1 | L17: =MAX(1,MIN(10,ROUNDUP(5-J17,0))) -> 2 | M17: =MIN(E17,F17) -> 1 | N17: lexicon | O17: 0.79 | P17: 0 | Q17: favorable, favourable, golden, prosperous | T17: fortunate (similar), luck (derived), occur (definition), chance (definition), hot (similar), bringing (definition), good (definition) | V17: unfortunate
A18: lovely | B18: quality | C18: quality | D18: aesthetic | E18: 7 | F18: 1 | G18: 1 | H18: 9 | I18: =(G18-H18)/2 -> -4 | J18: =(E18-F18)/2 -> 3 | K18: =MAX(1,MIN(10,ROUNDUP(I18+5,0))) -> 1 | L18: =MAX(1,MIN(10,ROUNDUP(5-J18,0))) -> 2 | M18: =MIN(E18,F18) -> 1 | N18: lexicon | O18: 0.56 | P18: 0 | Q18: adorable, endearing | T18: beautiful (similar), appeal (definition), emotion (definition), well (definition), eye (definition) | V18: ugly
A19: cute | B19: quality | C19: quality | D19: aesthetic | E19: 7 | F19: 1 | G19: 1 | H19: 9 | I19: =(G19-H19)/2 -> -4 | J19: =(E19-F19)/2 -> 3 | K19: =MAX(1,MIN(10,ROUNDUP(I19+5,0))) -> 1 | L19: =MAX(1,MIN(10,ROUNDUP(5-J19,0))) -> 2 | M19: =MIN(E19,F19) -> 1 | N19: lexicon | O19: 0.56 | P19: 0 | Q19: cunning | T19: attractive (similar), means (definition), obviously (definition), charm (definition)
A20: decent | B20: quality | C20: quality | D20: evaluative | E20: 7 | F20: 1 | G20: 1 | H20: 9 | I20: =(G20-H20)/2 -> -4 | J20: =(E20-F20)/2 -> 3 | K20: =MAX(1,MIN(10,ROUNDUP(I20+5,0))) -> 1 | L20: =MAX(1,MIN(10,ROUNDUP(5-J20,0))) -> 2 | M20: =MIN(E20,F20) -> 1 | N20: lexicon | O20: 0.71 | P20: 0 | Q20: nice | T20: socially (definition), correct (definition), proper (similar), accord (definition), custom (definition)
A21: gorgeous | B21: quality | C21: quality | D21: aesthetic | E21: 8 | F21: 1 | G21: 1 | H21: 9 | I21: =(G21-H21)/2 -> -4 | J21: =(E21-F21)/2 -> 3.5 | K21: =MAX(1,MIN(10,ROUNDUP(I21+5,0))) -> 1 | L21: =MAX(1,MIN(10,ROUNDUP(5-J21,0))) -> 2 | M21: =MIN(E21,F21) -> 1 | N21: lexicon | O21: 0.75 | P21: 0 | T21: beautiful (similar) | V21: ugly
A22: precious | B22: quality | C22: quality | D22: aesthetic | E22: 8 | F22: 1 | G22: 1 | H22: 9 | I22: =(G22-H22)/2 -> -4 | J22: =(E22-F22)/2 -> 3.5 | K22: =MAX(1,MIN(10,ROUNDUP(I22+5,0))) -> 1 | L22: =MAX(1,MIN(10,ROUNDUP(5-J22,0))) -> 2 | M22: =MIN(E22,F22) -> 1 | N22: lexicon | O22: 0.62 | P22: 0.08 | Q22: cherished, treasured, wanted | T22: loved (similar), feeling (definition), showing (definition), fond (definition), affection (definition), valuable (similar) | V22: worthless
A23: handsome | B23: quality | C23: quality | D23: aesthetic | E23: 7 | F23: 1 | G23: 1 | H23: 9 | I23: =(G23-H23)/2 -> -4 | J23: =(E23-F23)/2 -> 3 | K23: =MAX(1,MIN(10,ROUNDUP(I23+5,0))) -> 1 | L23: =MAX(1,MIN(10,ROUNDUP(5-J23,0))) -> 2 | M23: =MIN(E23,F23) -> 1 | N23: lexicon | O23: 0.56 | P23: 0 | Q23: better-looking, fine-looking, good-looking, well-favored, well-favoured | T23: beautiful (similar), appearance (definition), reason (definition), ideal (definition), proportion (definition), generous (similar) | V23: ugly
A24: pleasant | B24: quality | C24: quality | D24: evaluative | E24: 7 | F24: 1 | G24: 1 | H24: 9 | I24: =(G24-H24)/2 -> -4 | J24: =(E24-F24)/2 -> 3 | K24: =MAX(1,MIN(10,ROUNDUP(I24+5,0))) -> 1 | L24: =MAX(1,MIN(10,ROUNDUP(5-J24,0))) -> 2 | M24: =MIN(E24,F24) -> 1 | N24: lexicon | O24: 0.69 | P24: 0.06 | T24: nice (similar), enjoyable (similar), beautiful (similar), please (derived), afford (definition), pleasure (definition), harmony (definition), taste (definition) | V24: unpleasant, nasty
A25: mild | B25: quality | C25: quality | D25: evaluative | E25: 7 | F25: 1 | G25: 1 | H25: 9 | I25: =(G25-H25)/2 -> -4 | J25: =(E25-F25)/2 -> 3 | K25: =MAX(1,MIN(10,ROUNDUP(I25+5,0))) -> 1 | L25: =MAX(1,MIN(10,ROUNDUP(5-J25,0))) -> 2 | M25: =MIN(E25,F25) -> 1 | N25: lexicon | O25: 0.62 | P25: 0.04 | Q25: balmy, meek, modest, soft | T25: moderate (similar), gentle (similar), soft (similar), degree (definition), effect (definition), force (definition), extreme (definition) | V25: intense, proud
A26: adorable | B26: quality | C26: quality | D26: aesthetic | E26: 7 | F26: 1 | G26: 1 | H26: 9 | I26: =(G26-H26)/2 -> -4 | J26: =(E26-F26)/2 -> 3 | K26: =MAX(1,MIN(10,ROUNDUP(I26+5,0))) -> 1 | L26: =MAX(1,MIN(10,ROUNDUP(5-J26,0))) -> 2 | M26: =MIN(E26,F26) -> 1 | N26: lexicon | O26: 0.5 | P26: 0 | Q26: endearing, lovely
A27: aesthetic | B27: quality | C27: quality | D27: aesthetic | E27: 7 | F27: 1 | G27: 1 | H27: 9 | I27: =(G27-H27)/2 -> -4 | J27: =(E27-F27)/2 -> 3 | K27: =MAX(1,MIN(10,ROUNDUP(I27+5,0))) -> 1 | L27: =MAX(1,MIN(10,ROUNDUP(5-J27,0))) -> 2 | M27: =MIN(E27,F27) -> 1 | N27: lexicon | O27: 0.5 | P27: 0 | Q27: esthetic | T27: relate (definition), dealing (definition), subject (definition), artistic (similar), concern (definition)
A28: beneficial | B28: quality | C28: quality | D28: evaluative | E28: 7 | F28: 1 | G28: 1 | H28: 9 | I28: =(G28-H28)/2 -> -4 | J28: =(E28-F28)/2 -> 3 | K28: =MAX(1,MIN(10,ROUNDUP(I28+5,0))) -> 1 | L28: =MAX(1,MIN(10,ROUNDUP(5-J28,0))) -> 2 | M28: =MIN(E28,F28) -> 1 | N28: lexicon | O28: 0.62 | P28: 0 | Q28: good | T28: benefit (derived), promote (definition), enhance (definition), well (definition)
A29: competent | B29: quality | C29: quality | D29: evaluative | E29: 7 | F29: 1 | G29: 1 | H29: 9 | I29: =(G29-H29)/2 -> -4 | J29: =(E29-F29)/2 -> 3 | K29: =MAX(1,MIN(10,ROUNDUP(I29+5,0))) -> 1 | L29: =MAX(1,MIN(10,ROUNDUP(5-J29,0))) -> 2 | M29: =MIN(E29,F29) -> 1 | N29: lexicon | O29: 0.58 | P29: 0 | T29: capable (similar), effective (similar), skilled (similar), properly (definition), sufficiently (definition), qualify (definition), efficient (definition) | V29: inadequate
A30: constructive | B30: quality | C30: quality | D30: evaluative | E30: 7 | F30: 1 | G30: 1 | H30: 9 | I30: =(G30-H30)/2 -> -4 | J30: =(E30-F30)/2 -> 3 | K30: =MAX(1,MIN(10,ROUNDUP(I30+5,0))) -> 1 | L30: =MAX(1,MIN(10,ROUNDUP(5-J30,0))) -> 2 | M30: =MIN(E30,F30) -> 1 | N30: lexicon | O30: 0.69 | P30: 0 | T30: positive (similar), creative (similar), structural (similar), construct (definition), improve (definition), promote (definition), development (definition) | V30: destructive, negative, neutral
A31: fortunate | B31: quality | C31: quality | D31: evaluative | E31: 8 | F31: 1 | G31: 1 | H31: 9 | I31: =(G31-H31)/2 -> -4 | J31: =(E31-F31)/2 -> 3.5 | K31: =MAX(1,MIN(10,ROUNDUP(I31+5,0))) -> 1 | L31: =MAX(1,MIN(10,ROUNDUP(5-J31,0))) -> 2 | M31: =MIN(E31,F31) -> 1 | N31: lexicon | O31: 0.79 | P31: 0 | Q31: golden, rosy | T31: successful (similar), lucky (similar), privileged (similar), unexpected (definition), good (definition), fortune (definition), favor (definition) | V31: unfortunate
A32: superb | B32: quality | C32: quality | D32: evaluative | E32: 8 | F32: 1 | G32: 1 | H32: 9 | I32: =(G32-H32)/2 -> -4 | J32: =(E32-F32)/2 -> 3.5 | K32: =MAX(1,MIN(10,ROUNDUP(I32+5,0))) -> 1 | L32: =MAX(1,MIN(10,ROUNDUP(5-J32,0))) -> 2 | M32: =MIN(E32,F32) -> 1 | N32: lexicon | O32: 0.88 | P32: 0 | Q32: brilliant | T32: superior (similar), excellence (definition), good (similar) | V32: inferior, bad
A33: prestigious | B33: quality | C33: quality | D33: social | E33: 7 | F33: 1 | G33: 1 | H33: 9 | I33: =(G33-H33)/2 -> -4 | J33: =(E33-F33)/2 -> 3 | K33: =MAX(1,MIN(10,ROUNDUP(I33+5,0))) -> 1 | L33: =MAX(1,MIN(10,ROUNDUP(5-J33,0))) -> 2 | M33: =MIN(E33,F33) -> 1 | N33: lexicon | O33: 0.62 | P33: 0 | Q33: esteemed, honored | T33: reputation (definition), respect (definition), influential (similar), influence (definition), reason (definition)
A34: important | B34: quality | C34: quality | D34: importance | E34: 8 | F34: 1 | G34: 2 | H34: 8 | I34: =(G34-H34)/2 -> -3 | J34: =(E34-F34)/2 -> 3.5 | K34: =MAX(1,MIN(10,ROUNDUP(I34+5,0))) -> 2 | L34: =MAX(1,MIN(10,ROUNDUP(5-J34,0))) -> 2 | M34: =MIN(E34,F34) -> 1 | N34: lexicon | O34: 0.58 | P34: 0.08 | Q34: of import | T34: great (similar), main (similar), principal (similar), importance (derived), significance (definition), value (definition), effect (definition), meaning (definition)
A35: happy | B35: quality | C35: quality | D35: emotional | E35: 7 | F35: 1 | G35: 2 | H35: 8 | I35: =(G35-H35)/2 -> -3 | J35: =(E35-F35)/2 -> 3 | K35: =MAX(1,MIN(10,ROUNDUP(I35+5,0))) -> 2 | L35: =MAX(1,MIN(10,ROUNDUP(5-J35,0))) -> 2 | M35: =MIN(E35,F35) -> 1 | N35: lexicon | O35: 0.71 | P35: 0 | Q35: felicitous, glad | T35: glad (similar), golden (similar), blessed (similar), happiness (derived), enjoy (definition), showing (definition), mark (definition), joy (definition) | V35: unhappy, unfortunate
A36: smart | B36: quality | C36: quality | D36: personality | E36: 7 | F36: 1 | G36: 2 | H36: 8 | I36: =(G36-H36)/2 -> -3 | J36: =(E36-F36)/2 -> 3 | K36: =MAX(1,MIN(10,ROUNDUP(I36+5,0))) -> 2 | L36: =MAX(1,MIN(10,ROUNDUP(5-J36,0))) -> 2 | M36: =MIN(E36,F36) -> 1 | N36: lexicon | O36: 0.58 | P36: 0 | Q36: bright, chic, voguish | T36: sharp (similar), intelligent (similar), clever (similar), showing (definition), mental (definition), elegant (definition) | V36: stupid
A37: healthy | B37: quality | C37: quality | D37: physical | E37: 7 | F37: 1 | G37: 2 | H37: 8 | I37: =(G37-H37)/2 -> -3 | J37: =(E37-F37)/2 -> 3 | K37: =MAX(1,MIN(10,ROUNDUP(I37+5,0))) -> 2 | L37: =MAX(1,MIN(10,ROUNDUP(5-J37,0))) -> 2 | M37: =MIN(E37,F37) -> 1 | N37: lexicon | O37: 0.71 | P37: 0 | Q37: good for you, salubrious | T37: well (similar), fit (similar), firm (similar), health (derived), indicate (definition), good (definition), body (definition), mind (definition)
A38: correct | B38: quality | C38: quality | D38: certainty | E38: 7 | F38: 1 | G38: 1 | H38: 8 | I38: =(G38-H38)/2 -> -3.5 | J38: =(E38-F38)/2 -> 3 | K38: =MAX(1,MIN(10,ROUNDUP(I38+5,0))) -> 2 | L38: =MAX(1,MIN(10,ROUNDUP(5-J38,0))) -> 2 | M38: =MIN(E38,F38) -> 1 | N38: lexicon | O38: 0.62 | P38: 0 | Q38: right | T38: true (similar), proper (similar), accurate (similar), free (definition), error (definition), fact (definition), truth (definition) | V38: incorrect
A39: intellectual | B39: quality | C39: quality | D39: cognitive | E39: 7 | F39: 1 | G39: 1 | H39: 8 | I39: =(G39-H39)/2 -> -3.5 | J39: =(E39-F39)/2 -> 3 | K39: =MAX(1,MIN(10,ROUNDUP(I39+5,0))) -> 2 | L39: =MAX(1,MIN(10,ROUNDUP(5-J39,0))) -> 2 | M39: =MIN(E39,F39) -> 1 | N39: lexicon | O39: 0.58 | P39: 0.08 | Q39: noetic, rational | T39: mental (similar), associate (definition), require (definition), mind (definition), educated (similar), serious (similar), appeal (definition) | V39: physical
A40: worthy | B40: quality | C40: quality | D40: importance | E40: 8 | F40: 1 | G40: 2 | H40: 8 | I40: =(G40-H40)/2 -> -3 | J40: =(E40-F40)/2 -> 3.5 | K40: =MAX(1,MIN(10,ROUNDUP(I40+5,0))) -> 2 | L40: =MAX(1,MIN(10,ROUNDUP(5-J40,0))) -> 2 | M40: =MIN(E40,F40) -> 1 | N40: lexicon | O40: 0.75 | P40: 0 | Q40: desirable, suitable | T40: valuable (similar), worth (similar), good (similar), merit (definition), value (definition), honorable (definition), chosen (definition)
A41: skilled | B41: quality | C41: quality | D41: personality | E41: 7 | F41: 1 | G41: 2 | H41: 8 | I41: =(G41-H41)/2 -> -3 | J41: =(E41-F41)/2 -> 3 | K41: =MAX(1,MIN(10,ROUNDUP(I41+5,0))) -> 2 | L41: =MAX(1,MIN(10,ROUNDUP(5-J41,0))) -> 2 | M41: =MIN(E41,F41) -> 1 | N41: lexicon | O41: 0.62 | P41: 0 | T41: experienced (similar), competent (similar), delicate (similar), showing (definition), require (definition), special (definition), skill (definition)
A42: happier | B42: quality | C42: quality | D42: emotional | E42: 7 | F42: 1 | G42: 2 | H42: 8 | I42: =(G42-H42)/2 -> -3 | J42: =(E42-F42)/2 -> 3 | K42: =MAX(1,MIN(10,ROUNDUP(I42+5,0))) -> 2 | L42: =MAX(1,MIN(10,ROUNDUP(5-J42,0))) -> 2 | M42: =MIN(E42,F42) -> 1 | N42: lexicon | O42: 0.71 | P42: 0 | Q42: happy | T42: glad (similar), golden (similar), blessed (similar), enjoy (definition), showing (definition), mark (definition), joy (definition) | V42: unfortunate
A43: healthier | B43: quality | C43: quality | D43: physical | E43: 7 | F43: 1 | G43: 2 | H43: 8 | I43: =(G43-H43)/2 -> -3 | J43: =(E43-F43)/2 -> 3 | K43: =MAX(1,MIN(10,ROUNDUP(I43+5,0))) -> 2 | L43: =MAX(1,MIN(10,ROUNDUP(5-J43,0))) -> 2 | M43: =MIN(E43,F43) -> 1 | N43: lexicon | O43: 0.58 | P43: 0 | Q43: fitter | T43: better (similar), improve (definition), health (definition), physical (definition), condition (definition), well (similar), fit (similar) | V43: worse
A44: honorable | B44: quality | C44: quality | D44: personality | E44: 7 | F44: 1 | G44: 2 | H44: 8 | I44: =(G44-H44)/2 -> -3 | J44: =(E44-F44)/2 -> 3 | K44: =MAX(1,MIN(10,ROUNDUP(I44+5,0))) -> 2 | L44: =MAX(1,MIN(10,ROUNDUP(5-J44,0))) -> 2 | M44: =MIN(E44,F44) -> 1 | N44: lexicon | O44: 0.62 | P44: 0.08 | Q44: honest | T44: true (similar), genuine (similar), sincere (similar), cheat (definition), worthy (definition), honor (definition), respect (definition) | V44: wrong
A45: righteous | B45: quality | C45: quality | D45: personality | E45: 8 | F45: 1 | G45: 2 | H45: 8 | I45: =(G45-H45)/2 -> -3 | J45: =(E45-F45)/2 -> 3.5 | K45: =MAX(1,MIN(10,ROUNDUP(I45+5,0))) -> 2 | L45: =MAX(1,MIN(10,ROUNDUP(5-J45,0))) -> 2 | M45: =MIN(E45,F45) -> 1 | N45: lexicon | O45: 0.81 | P45: 0 | T45: worthy (similar), good (similar), innocent (similar), accept (definition), standard (definition), morality (definition), justice (definition)
A46: smarter | B46: quality | C46: quality | D46: cognitive | E46: 7 | F46: 1 | G46: 1 | H46: 8 | I46: =(G46-H46)/2 -> -3.5 | J46: =(E46-F46)/2 -> 3 | K46: =MAX(1,MIN(10,ROUNDUP(I46+5,0))) -> 2 | L46: =MAX(1,MIN(10,ROUNDUP(5-J46,0))) -> 2 | M46: =MIN(E46,F46) -> 1 | N46: lexicon | O46: 0.58 | P46: 0 | Q46: smart | T46: sharp (similar), intelligent (similar), clever (similar), showing (definition), mental (definition), elegant (definition)
A47: thorough | B47: quality | C47: quality | D47: cognitive | E47: 8 | F47: 1 | G47: 1 | H47: 8 | I47: =(G47-H47)/2 -> -3.5 | J47: =(E47-F47)/2 -> 3.5 | K47: =MAX(1,MIN(10,ROUNDUP(I47+5,0))) -> 2 | L47: =MAX(1,MIN(10,ROUNDUP(5-J47,0))) -> 2 | M47: =MIN(E47,F47) -> 1 | N47: lexicon | O47: 0.81 | P47: 0 | Q47: exhaustive, thoroughgoing | T47: careful (similar), accurate (definition), complete (similar), perform (definition), completely (definition) | V47: incomplete
A48: sustainable | B48: quality | C48: quality | D48: relational | E48: 7 | F48: 1 | G48: 2 | H48: 8 | I48: =(G48-H48)/2 -> -3 | J48: =(E48-F48)/2 -> 3 | K48: =MAX(1,MIN(10,ROUNDUP(I48+5,0))) -> 2 | L48: =MAX(1,MIN(10,ROUNDUP(5-J48,0))) -> 2 | M48: =MIN(E48,F48) -> 1 | N48: lexicon | O48: 0.62 | P48: 0 | T48: sustain (derived), capable (definition)
A49: brilliant | B49: quality | C49: quality | D49: cognitive | E49: 7 | F49: 1 | G49: 1 | H49: 8 | I49: =(G49-H49)/2 -> -3.5 | J49: =(E49-F49)/2 -> 3 | K49: =MAX(1,MIN(10,ROUNDUP(I49+5,0))) -> 2 | L49: =MAX(1,MIN(10,ROUNDUP(5-J49,0))) -> 2 | M49: =MIN(E49,F49) -> 1 | N49: lexicon | O49: 0.62 | P49: 0.08 | Q49: superb | T49: superior (similar), excellence (definition), intelligent (similar), mark (definition), unusual (definition), impressive (definition) | V49: inferior
A50: plan | B50: non_biological | C50: cognition | E50: 8 | F50: 2 | G50: 3 | H50: 8 | I50: =(G50-H50)/2 -> -2.5 | J50: =(E50-F50)/2 -> 3 | K50: =MAX(1,MIN(10,ROUNDUP(I50+5,0))) -> 3 | L50: =MAX(1,MIN(10,ROUNDUP(5-J50,0))) -> 2 | M50: =MIN(E50,F50) -> 2 | N50: lexicon | O50: 0 | P50: 0 | Q50: program, programme | T50: idea (is-a), thought (is-a), schedule (kind-of), agenda (kind-of), budget (kind-of), series (definition), steps (definition), carry (definition), goal (definition), organization (is-a)
A51: goal | B51: non_biological | C51: cognition | E51: 8 | F51: 2 | G51: 3 | H51: 8 | I51: =(G51-H51)/2 -> -2.5 | J51: =(E51-F51)/2 -> 3 | K51: =MAX(1,MIN(10,ROUNDUP(I51+5,0))) -> 3 | L51: =MAX(1,MIN(10,ROUNDUP(5-J51,0))) -> 2 | M51: =MIN(E51,F51) -> 2 | N51: lexicon | O51: 0 | P51: 0 | Q51: end | T51: content (is-a), purpose (kind-of), objective (kind-of), aim (kind-of), affairs (definition), plan (definition), intend (definition), achieve (definition), end (is-a), terminal (is-a)
A52: joke | B52: non_biological | C52: communication | E52: 9 | F52: 3 | G52: 4 | H52: 8 | I52: =(G52-H52)/2 -> -2 | J52: =(E52-F52)/2 -> 3 | K52: =MAX(1,MIN(10,ROUNDUP(I52+5,0))) -> 3 | L52: =MAX(1,MIN(10,ROUNDUP(5-J52,0))) -> 2 | M52: =MIN(E52,F52) -> 3 | N52: lexicon | O52: 0.58 | P52: 0.08 | Q52: gag, jape, jest, laugh | T52: wit (is-a), humor (is-a), humour (is-a), funny (kind-of), riot (kind-of), scream (kind-of), intend (definition), laughter (definition), activity (definition), good (definition)
A53: vision | B53: non_biological | C53: cognition | E53: 8 | F53: 2 | G53: 3 | H53: 8 | I53: =(G53-H53)/2 -> -2.5 | J53: =(E53-F53)/2 -> 3 | K53: =MAX(1,MIN(10,ROUNDUP(I53+5,0))) -> 3 | L53: =MAX(1,MIN(10,ROUNDUP(5-J53,0))) -> 2 | M53: =MIN(E53,F53) -> 2 | N53: lexicon | O53: 0.08 | P53: 0.08 | Q53: sight, visual modality, visual sensation, visual sense | T53: imagination (is-a), imagery (is-a), imaging (is-a), mental (definition), image (definition), seeing (kind-of), ability (definition), see (definition)
A54: intention | B54: non_biological | C54: cognition | E54: 8 | F54: 2 | G54: 3 | H54: 8 | I54: =(G54-H54)/2 -> -2.5 | J54: =(E54-F54)/2 -> 3 | K54: =MAX(1,MIN(10,ROUNDUP(I54+5,0))) -> 3 | L54: =MAX(1,MIN(10,ROUNDUP(5-J54,0))) -> 2 | M54: =MIN(E54,F54) -> 2 | N54: lexicon | O54: 0 | P54: 0 | Q54: aim, design, intent, purpose | T54: goal (is-a), end (is-a), will (kind-of), idea (kind-of), view (kind-of), outcome (definition), intend (definition), guide (definition), plan (definition)
A55: jokes | B55: non_biological | C55: communication | E55: 9 | F55: 3 | G55: 4 | H55: 8 | I55: =(G55-H55)/2 -> -2 | J55: =(E55-F55)/2 -> 3 | K55: =MAX(1,MIN(10,ROUNDUP(I55+5,0))) -> 3 | L55: =MAX(1,MIN(10,ROUNDUP(5-J55,0))) -> 2 | M55: =MIN(E55,F55) -> 3 | N55: lexicon | O55: 0.58 | P55: 0.08 | Q55: gag, jape, jest, joke, laugh | T55: wit (is-a), humor (is-a), humour (is-a), funny (kind-of), riot (kind-of), scream (kind-of), intend (definition), laughter (definition), activity (definition), good (definition)
A56: expectation | B56: non_biological | C56: cognition | E56: 9 | F56: 2 | G56: 3 | H56: 8 | I56: =(G56-H56)/2 -> -2.5 | J56: =(E56-F56)/2 -> 3.5 | K56: =MAX(1,MIN(10,ROUNDUP(I56+5,0))) -> 3 | L56: =MAX(1,MIN(10,ROUNDUP(5-J56,0))) -> 2 | M56: =MIN(E56,F56) -> 2 | N56: lexicon | O56: 0.17 | P56: 0.04 | Q56: outlook, prospect | T56: belief (is-a), possibility (kind-of), hope (kind-of), promise (kind-of), expect (derived), mental (definition), picture (definition), future (definition), confidence (definition)
A57: respected | B57: action | C57: action | D57: cognition | E57: 8 | F57: 2 | G57: 3 | H57: 8 | I57: =(G57-H57)/2 -> -2.5 | J57: =(E57-F57)/2 -> 3 | K57: =MAX(1,MIN(10,ROUNDUP(I57+5,0))) -> 3 | L57: =MAX(1,MIN(10,ROUNDUP(5-J57,0))) -> 2 | M57: =MIN(E57,F57) -> 2 | N57: lexicon | O57: 0.44 | P57: 0 | Q57: esteem, prise, prize, respect, value | T57: consider (is-a), see (is-a), regard (is-a), admire (kind-of), fear (kind-of), highly (definition), think (definition), celebrate (kind-of), show (definition), respect (definition)
A58: just | B58: quality | C58: quality | D58: quantity | E58: 7 | F58: 1 | G58: 2 | H58: 7 | I58: =(G58-H58)/2 -> -2.5 | J58: =(E58-F58)/2 -> 3 | K58: =MAX(1,MIN(10,ROUNDUP(I58+5,0))) -> 3 | L58: =MAX(1,MIN(10,ROUNDUP(5-J58,0))) -> 2 | M58: =MIN(E58,F58) -> 1 | N58: lexicon | O58: 0.58 | P58: 0 | Q58: but, merely, only, simply | T58: fair (similar), right (similar), fitting (similar), legally (definition), proper (definition), lincoln (definition), party (definition)
A59: well | B59: quality | C59: quality | D59: quantity | E59: 7 | F59: 1 | G59: 2 | H59: 7 | I59: =(G59-H59)/2 -> -2.5 | J59: =(E59-F59)/2 -> 3 | K59: =MAX(1,MIN(10,ROUNDUP(I59+5,0))) -> 3 | L59: =MAX(1,MIN(10,ROUNDUP(5-J59,0))) -> 2 | M59: =MIN(E59,F59) -> 1 | N59: lexicon | O59: 0.67 | P59: 0 | Q59: good | T59: healthy (similar), fit (similar), recovered (similar), good (definition), health (definition), suffer (definition), illness (definition) | V59: ill, unfortunate
A60: sexy | B60: quality | C60: quality | D60: emotional | E60: 7 | F60: 1 | G60: 5 | H60: 5 | I60: =(G60-H60)/2 -> 0 | J60: =(E60-F60)/2 -> 3 | K60: =MAX(1,MIN(10,ROUNDUP(I60+5,0))) -> 5 | L60: =MAX(1,MIN(10,ROUNDUP(5-J60,0))) -> 2 | M60: =MIN(E60,F60) -> 1 | N60: lexicon | O60: 0.62 | P60: 0 | Q60: aphrodisiac, aphrodisiacal | T60: exciting (similar), hot (similar), adult (similar), sex (derived), mark (definition), sexual (definition), desire (definition), interest (definition)
A61: enthusiastic | B61: quality | C61: quality | D61: emotional | E61: 7 | F61: 1 | G61: 5 | H61: 5 | I61: =(G61-H61)/2 -> 0 | J61: =(E61-F61)/2 -> 3 | K61: =MAX(1,MIN(10,ROUNDUP(I61+5,0))) -> 5 | L61: =MAX(1,MIN(10,ROUNDUP(5-J61,0))) -> 2 | M61: =MIN(E61,F61) -> 1 | N61: lexicon | O61: 0.62 | P61: 0 | T61: passionate (similar), crazy (similar), warm (similar), enthusiasm (derived), showing (definition), great (definition), excitement (definition), interest (definition)
A62: captured | B62: action | C62: action | D62: creation | E62: 7 | F62: 1 | G62: 6 | H62: 5 | I62: =(G62-H62)/2 -> 0.5 | J62: =(E62-F62)/2 -> 3 | K62: =MAX(1,MIN(10,ROUNDUP(I62+5,0))) -> 6 | L62: =MAX(1,MIN(10,ROUNDUP(5-J62,0))) -> 2 | M62: =MIN(E62,F62) -> 1 | N62: lexicon | O62: 0.17 | P62: 0.04 | Q62: capture | T62: interpret (is-a), represent (is-a), succeed (definition), express (definition), attract (is-a), hold (kind-of), work (kind-of), cause (definition)
A63: capture | B63: action | C63: action | D63: creation | E63: 7 | F63: 1 | G63: 6 | H63: 5 | I63: =(G63-H63)/2 -> 0.5 | J63: =(E63-F63)/2 -> 3 | K63: =MAX(1,MIN(10,ROUNDUP(I63+5,0))) -> 6 | L63: =MAX(1,MIN(10,ROUNDUP(5-J63,0))) -> 2 | M63: =MIN(E63,F63) -> 1 | N63: lexicon | O63: 0.17 | P63: 0.04 | Q63: becharm, beguile, bewitch, captivate, catch, charm | T63: interpret (is-a), represent (is-a), succeed (definition), express (definition), attract (is-a), hold (kind-of), work (kind-of), cause (definition), arrest (kind-of), owner (definition)
A64: renewed | B64: action | C64: action | D64: creation | E64: 7 | F64: 1 | G64: 6 | H64: 5 | I64: =(G64-H64)/2 -> 0.5 | J64: =(E64-F64)/2 -> 3 | K64: =MAX(1,MIN(10,ROUNDUP(I64+5,0))) -> 6 | L64: =MAX(1,MIN(10,ROUNDUP(5-J64,0))) -> 2 | M64: =MIN(E64,F64) -> 1 | N64: lexicon | O64: 0.12 | P64: 0 | Q64: regenerate, renew | T64: replace (kind-of), restore (kind-of), new (definition), improve (definition), basis (definition), cause (definition)
A65: decorated | B65: action | C65: action | D65: creation | E65: 8 | F65: 1 | G65: 6 | H65: 5 | I65: =(G65-H65)/2 -> 0.5 | J65: =(E65-F65)/2 -> 3.5 | K65: =MAX(1,MIN(10,ROUNDUP(I65+5,0))) -> 6 | L65: =MAX(1,MIN(10,ROUNDUP(5-J65,0))) -> 2 | M65: =MIN(E65,F65) -> 1 | N65: lexicon | O65: 0.29 | P65: 0 | Q65: adorn, beautify, decorate, embellish, grace, ornament | T65: change (is-a), alter (is-a), modify (is-a), panel (kind-of), trim (kind-of), color (kind-of), attractive (definition), add (definition), colour (definition), beautiful (definition)
A66: fulfill | B66: action | C66: action | D66: creation | E66: 7 | F66: 1 | G66: 6 | H66: 5 | I66: =(G66-H66)/2 -> 0.5 | J66: =(E66-F66)/2 -> 3 | K66: =MAX(1,MIN(10,ROUNDUP(I66+5,0))) -> 6 | L66: =MAX(1,MIN(10,ROUNDUP(5-J66,0))) -> 2 | M66: =MIN(E66,F66) -> 1 | N66: lexicon | O66: 0.21 | P66: 0 | Q66: accomplish, action, carry out, carry through, execute, fulfil | T66: complete (is-a), finish (is-a), effect (is-a), do (kind-of), discharge (kind-of), perform (kind-of), implement (similar), put (definition), meet (definition), requirement (definition), expectation (definition)
A67: copied | B67: action | C67: action | D67: creation | E67: 7 | F67: 1 | G67: 6 | H67: 5 | I67: =(G67-H67)/2 -> 0.5 | J67: =(E67-F67)/2 -> 3 | K67: =MAX(1,MIN(10,ROUNDUP(I67+5,0))) -> 6 | L67: =MAX(1,MIN(10,ROUNDUP(5-J67,0))) -> 2 | M67: =MIN(E67,F67) -> 1 | N67: lexicon | O67: 0.12 | P67: 0.08 | Q67: copy | T67: write (is-a), copy (definition), follow (kind-of), pattern (kind-of), model (kind-of), behavior (definition), look (definition)
A68: enjoy | B68: action | C68: action | D68: emotion | E68: 8 | F68: 2 | G68: 8 | H68: 4 | I68: =(G68-H68)/2 -> 2 | J68: =(E68-F68)/2 -> 3 | K68: =MAX(1,MIN(10,ROUNDUP(I68+5,0))) -> 7 | L68: =MAX(1,MIN(10,ROUNDUP(5-J68,0))) -> 2 | M68: =MIN(E68,F68) -> 2 | N68: lexicon | O68: 0.62 | P68: 0 | Q68: bask, relish, savor, savour | T68: enjoyment (derived), receive (definition), pleasure (definition), get (definition), take (definition), use (is-a), apply (is-a), employ (is-a)
A69: loved | B69: action | C69: action | D69: emotion | E69: 8 | F69: 2 | G69: 8 | H69: 4 | I69: =(G69-H69)/2 -> 2 | J69: =(E69-F69)/2 -> 3 | K69: =MAX(1,MIN(10,ROUNDUP(I69+5,0))) -> 7 | L69: =MAX(1,MIN(10,ROUNDUP(5-J69,0))) -> 2 | M69: =MIN(E69,F69) -> 2 | N69: lexicon | O69: 0.71 | P69: 0 | Q69: love | T69: love (kind-of), treasure (kind-of), have (definition), great (definition), affection (definition), liking (definition)
A70: loves | B70: action | C70: action | D70: emotion | E70: 8 | F70: 2 | G70: 8 | H70: 4 | I70: =(G70-H70)/2 -> 2 | J70: =(E70-F70)/2 -> 3 | K70: =MAX(1,MIN(10,ROUNDUP(I70+5,0))) -> 7 | L70: =MAX(1,MIN(10,ROUNDUP(5-J70,0))) -> 2 | M70: =MIN(E70,F70) -> 2 | N70: lexicon | O70: 0.71 | P70: 0 | Q70: love | T70: love (kind-of), treasure (kind-of), have (definition), great (definition), affection (definition), liking (definition), emotion (is-a), loyalty (kind-of)
A71: enjoyed | B71: action | C71: action | D71: emotion | E71: 8 | F71: 2 | G71: 8 | H71: 4 | I71: =(G71-H71)/2 -> 2 | J71: =(E71-F71)/2 -> 3 | K71: =MAX(1,MIN(10,ROUNDUP(I71+5,0))) -> 7 | L71: =MAX(1,MIN(10,ROUNDUP(5-J71,0))) -> 2 | M71: =MIN(E71,F71) -> 2 | N71: lexicon | O71: 0.62 | P71: 0 | Q71: bask, enjoy, relish, savor, savour | T71: receive (definition), pleasure (definition), get (definition), enjoyment (definition), use (is-a), apply (is-a), employ (is-a)
A72: loving | B72: action | C72: action | D72: emotion | E72: 8 | F72: 2 | G72: 8 | H72: 4 | I72: =(G72-H72)/2 -> 2 | J72: =(E72-F72)/2 -> 3 | K72: =MAX(1,MIN(10,ROUNDUP(I72+5,0))) -> 7 | L72: =MAX(1,MIN(10,ROUNDUP(5-J72,0))) -> 2 | M72: =MIN(E72,F72) -> 2 | N72: lexicon | O72: 0.71 | P72: 0 | Q72: love | T72: love (kind-of), treasure (kind-of), have (definition), great (definition), affection (definition), liking (definition)
A73: enjoying | B73: action | C73: action | D73: emotion | E73: 8 | F73: 2 | G73: 8 | H73: 4 | I73: =(G73-H73)/2 -> 2 | J73: =(E73-F73)/2 -> 3 | K73: =MAX(1,MIN(10,ROUNDUP(I73+5,0))) -> 7 | L73: =MAX(1,MIN(10,ROUNDUP(5-J73,0))) -> 2 | M73: =MIN(E73,F73) -> 2 | N73: lexicon | O73: 0.62 | P73: 0 | Q73: bask, enjoy, relish, savor, savour | T73: receive (definition), pleasure (definition), get (definition), enjoyment (definition), use (is-a), apply (is-a), employ (is-a)
... A75: enjoys | B75: action | C75: action | D75: emotion | E75: 8 | F75: 2 | G75: 8 | H75: 4 | I75: =(G75-H75)/2 -> 2 | J75: =(E75-F75)/2 -> 3 | K75: =MAX(1,MIN(10,ROUNDUP(I75+5,0))) -> 7 | L75: =MAX(1,MIN(10,ROUNDUP(5-J75,0))) -> 2 | M75: =MIN(E75,F75) -> 2 | N75: lexicon | O75: 0.62 | P75: 0 | Q75: bask, enjoy, relish, savor, savour | T75: receive (definition), pleasure (definition), get (definition), enjoyment (definition), use (is-a), apply (is-a), employ (is-a)
A76: desire | B76: non_biological | C76: emotion | E76: 7 | F76: 1 | G76: 8 | H76: 2 | I76: =(G76-H76)/2 -> 3 | J76: =(E76-F76)/2 -> 3 | K76: =MAX(1,MIN(10,ROUNDUP(I76+5,0))) -> 8 | L76: =MAX(1,MIN(10,ROUNDUP(5-J76,0))) -> 2 | M76: =MIN(E76,F76) -> 1 | N76: concept+lexicon | O76: 0.17 | P76: 0.04 | R76: self | T76: feeling (is-a), ambition (kind-of), wish (kind-of), dream (kind-of), accompany (definition), tendency (is-a), want (definition)
A77: pleasure | B77: non_biological | C77: emotion | E77: 7 | F77: 1 | G77: 8 | H77: 2 | I77: =(G77-H77)/2 -> 3 | J77: =(E77-F77)/2 -> 3 | K77: =MAX(1,MIN(10,ROUNDUP(I77+5,0))) -> 8 | L77: =MAX(1,MIN(10,ROUNDUP(5-J77,0))) -> 2 | M77: =MIN(E77,F77) -> 1 | N77: concept+lexicon | O77: 0.12 | P77: 0 | Q77: pleasance | R77: self | T77: feeling (is-a), delight (kind-of), enjoyment (kind-of), comfort (kind-of), please (derived), fundamental (definition), hard (definition), define (definition), desire (definition) | V77: pain
A78: joy | B78: non_biological | C78: emotion | E78: 9 | F78: 2 | G78: 8 | H78: 2 | I78: =(G78-H78)/2 -> 3 | J78: =(E78-F78)/2 -> 3.5 | K78: =MAX(1,MIN(10,ROUNDUP(I78+5,0))) -> 8 | L78: =MAX(1,MIN(10,ROUNDUP(5-J78,0))) -> 2 | M78: =MIN(E78,F78) -> 2 | N78: concept+lexicon | O78: 0.44 | P78: 0.12 | Q78: joyfulness, joyousness | R78: self | T78: emotion (is-a), excitement (kind-of), great (definition), happiness (definition), provide (definition), source (definition)
A79: emotions | B79: non_biological | C79: emotion | E79: 7 | F79: 1 | G79: 8 | H79: 2 | I79: =(G79-H79)/2 -> 3 | J79: =(E79-F79)/2 -> 3 | K79: =MAX(1,MIN(10,ROUNDUP(I79+5,0))) -> 8 | L79: =MAX(1,MIN(10,ROUNDUP(5-J79,0))) -> 2 | M79: =MIN(E79,F79) -> 1 | N79: concept+lexicon | O79: 0.62 | P79: 0 | Q79: emotion | R79: self | T79: feeling (is-a), fear (kind-of), love (kind-of), anger (kind-of), strong (definition)
A80: emotion | B80: non_biological | C80: emotion | E80: 7 | F80: 1 | G80: 8 | H80: 2 | I80: =(G80-H80)/2 -> 3 | J80: =(E80-F80)/2 -> 3 | K80: =MAX(1,MIN(10,ROUNDUP(I80+5,0))) -> 8 | L80: =MAX(1,MIN(10,ROUNDUP(5-J80,0))) -> 2 | M80: =MIN(E80,F80) -> 1 | N80: concept+lexicon | O80: 0.62 | P80: 0 | R80: self | T80: feeling (is-a), fear (kind-of), love (kind-of), anger (kind-of), emotional (derived), strong (definition)
A81: preference | B81: non_biological | C81: emotion | E81: 7 | F81: 1 | G81: 8 | H81: 2 | I81: =(G81-H81)/2 -> 3 | J81: =(E81-F81)/2 -> 3 | K81: =MAX(1,MIN(10,ROUNDUP(I81+5,0))) -> 8 | L81: =MAX(1,MIN(10,ROUNDUP(5-J81,0))) -> 2 | M81: =MIN(E81,F81) -> 1 | N81: concept+lexicon | O81: 0.21 | P81: 0 | Q81: penchant, predilection, taste | R81: self | T81: liking (is-a), weakness (kind-of), prefer (derived), strong (definition), favor (definition)
A82: enthusiasm | B82: non_biological | C82: emotion | E82: 9 | F82: 2 | G82: 8 | H82: 2 | I82: =(G82-H82)/2 -> 3 | J82: =(E82-F82)/2 -> 3.5 | K82: =MAX(1,MIN(10,ROUNDUP(I82+5,0))) -> 8 | L82: =MAX(1,MIN(10,ROUNDUP(5-J82,0))) -> 2 | M82: =MIN(E82,F82) -> 2 | N82: concept+lexicon | O82: 0.46 | P82: 0.21 | Q82: ebullience, exuberance | R82: self | T82: feeling (is-a), enthusiastic (derived), excitement (definition), life (is-a), spirit (is-a), madness (kind-of), eager (definition), enjoyment (definition), approval (definition)
A83: desires | B83: non_biological | C83: emotion | E83: 7 | F83: 1 | G83: 8 | H83: 2 | I83: =(G83-H83)/2 -> 3 | J83: =(E83-F83)/2 -> 3 | K83: =MAX(1,MIN(10,ROUNDUP(I83+5,0))) -> 8 | L83: =MAX(1,MIN(10,ROUNDUP(5-J83,0))) -> 2 | M83: =MIN(E83,F83) -> 1 | N83: concept+lexicon | O83: 0.17 | P83: 0.04 | Q83: desire | R83: self | T83: feeling (is-a), ambition (kind-of), wish (kind-of), dream (kind-of), accompany (definition), tendency (is-a), want (definition)
A84: liking | B84: non_biological | C84: emotion | E84: 9 | F84: 3 | G84: 8 | H84: 2 | I84: =(G84-H84)/2 -> 3 | J84: =(E84-F84)/2 -> 3 | K84: =MAX(1,MIN(10,ROUNDUP(I84+5,0))) -> 8 | L84: =MAX(1,MIN(10,ROUNDUP(5-J84,0))) -> 2 | M84: =MIN(E84,F84) -> 3 | N84: concept+lexicon | O84: 0.5 | P84: 0.25 | R84: self | T84: feeling (is-a), taste (kind-of), approval (kind-of), preference (kind-of), pleasure (definition), enjoyment (definition) | V84: dislike
A85: delight | B85: non_biological | C85: emotion | E85: 8 | F85: 2 | G85: 8 | H85: 2 | I85: =(G85-H85)/2 -> 3 | J85: =(E85-F85)/2 -> 3 | K85: =MAX(1,MIN(10,ROUNDUP(I85+5,0))) -> 8 | L85: =MAX(1,MIN(10,ROUNDUP(5-J85,0))) -> 2 | M85: =MIN(E85,F85) -> 2 | N85: concept+lexicon | O85: 0.38 | P85: 0.19 | Q85: delectation | R85: self | T85: pleasure (is-a), feeling (definition), extreme (definition), satisfaction (definition), provide (definition)
A86: affection | B86: non_biological | C86: emotion | E86: 10 | F86: 3 | G86: 8 | H86: 3 | I86: =(G86-H86)/2 -> 2.5 | J86: =(E86-F86)/2 -> 3.5 | K86: =MAX(1,MIN(10,ROUNDUP(I86+5,0))) -> 8 | L86: =MAX(1,MIN(10,ROUNDUP(5-J86,0))) -> 2 | M86: =MIN(E86,F86) -> 3 | N86: concept+lexicon | O86: 0.62 | P86: 0.25 | Q86: affectionateness, fondness, heart, philia, tenderness | R86: self | T86: feeling (is-a), attachment (kind-of), regard (kind-of), respect (kind-of), positive (definition), liking (definition)
A87: preferences | B87: non_biological | C87: emotion | E87: 7 | F87: 1 | G87: 8 | H87: 2 | I87: =(G87-H87)/2 -> 3 | J87: =(E87-F87)/2 -> 3 | K87: =MAX(1,MIN(10,ROUNDUP(I87+5,0))) -> 8 | L87: =MAX(1,MIN(10,ROUNDUP(5-J87,0))) -> 2 | M87: =MIN(E87,F87) -> 1 | N87: concept+lexicon | O87: 0.21 | P87: 0 | Q87: penchant, predilection, preference, taste | R87: self | T87: liking (is-a), weakness (kind-of), strong (definition), favor (definition)
A88: forgiveness | B88: non_biological | C88: emotion | E88: 7 | F88: 1 | G88: 8 | H88: 3 | I88: =(G88-H88)/2 -> 2.5 | J88: =(E88-F88)/2 -> 3 | K88: =MAX(1,MIN(10,ROUNDUP(I88+5,0))) -> 8 | L88: =MAX(1,MIN(10,ROUNDUP(5-J88,0))) -> 2 | M88: =MIN(E88,F88) -> 1 | N88: concept+lexicon | O88: 0.12 | P88: 0.06 | Q88: pardon | R88: self | T88: mercy (is-a), feelings (definition), support (definition), willingness (definition), forgive (definition), kindness (is-a)
A89: enjoyment | B89: non_biological | C89: emotion | E89: 7 | F89: 1 | G89: 8 | H89: 2 | I89: =(G89-H89)/2 -> 3 | J89: =(E89-F89)/2 -> 3 | K89: =MAX(1,MIN(10,ROUNDUP(I89+5,0))) -> 8 | L89: =MAX(1,MIN(10,ROUNDUP(5-J89,0))) -> 2 | M89: =MIN(E89,F89) -> 1 | N89: concept+lexicon | O89: 0.17 | P89: 0 | Q89: delectation, use | R89: self | T89: pleasure (is-a), enjoy (derived), felt (definition), good (definition), time (definition), activity (is-a), receive (definition)
A90: pride | B90: non_biological | C90: emotion | E90: 8 | F90: 2 | G90: 10 | H90: 2 | I90: =(G90-H90)/2 -> 4 | J90: =(E90-F90)/2 -> 3 | K90: =MAX(1,MIN(10,ROUNDUP(I90+5,0))) -> 9 | L90: =MAX(1,MIN(10,ROUNDUP(5-J90,0))) -> 2 | M90: =MIN(E90,F90) -> 2 | N90: concept+lexicon | O90: 0.5 | P90: 0.17 | Q90: pridefulness | R90: self | T90: feeling (is-a), dignity (kind-of), ego (kind-of), self (definition), respect (definition), personal (definition), worth (definition), satisfaction (is-a)
A91: different | B91: quality | C91: quality | D91: comparative | E91: 5 | F91: 1 | G91: 1 | H91: 9 | I91: =(G91-H91)/2 -> -4 | J91: =(E91-F91)/2 -> 2 | K91: =MAX(1,MIN(10,ROUNDUP(I91+5,0))) -> 1 | L91: =MAX(1,MIN(10,ROUNDUP(5-J91,0))) -> 3 | M91: =MIN(E91,F91) -> 1 | N91: lexicon | O91: 0.33 | P91: 0.08 | T91: various (similar), distinct (similar), varied (similar), differ (derived), difference (derived), unlike (definition), nature (definition), quality (definition), degree (definition) | V91: same
A92: fine | B92: quality | C92: quality | D92: evaluative | E92: 5 | F92: 1 | G92: 1 | H92: 9 | I92: =(G92-H92)/2 -> -4 | J92: =(E92-F92)/2 -> 2 | K92: =MAX(1,MIN(10,ROUNDUP(I92+5,0))) -> 1 | L92: =MAX(1,MIN(10,ROUNDUP(5-J92,0))) -> 3 | M92: =MIN(E92,F92) -> 1 | N92: lexicon | O92: 0.38 | P92: 0 | Q92: all right, hunky-dory, o.k., ok, okay | T92: condition (definition), precise (similar), difference (definition), meaning (definition)
A93: amazing | B93: quality | C93: quality | D93: evaluative | E93: 7 | F93: 2 | G93: 1 | H93: 9 | I93: =(G93-H93)/2 -> -4 | J93: =(E93-F93)/2 -> 2.5 | K93: =MAX(1,MIN(10,ROUNDUP(I93+5,0))) -> 1 | L93: =MAX(1,MIN(10,ROUNDUP(5-J93,0))) -> 3 | M93: =MIN(E93,F93) -> 2 | N93: lexicon | O93: 0.69 | P93: 0.19 | Q93: astonishing | T93: surprising (similar), surprise (definition), greatly (definition), impressive (similar), inspire (definition), awe (definition)
A94: interesting | B94: quality | C94: quality | D94: evaluative | E94: 5 | F94: 1 | G94: 1 | H94: 9 | I94: =(G94-H94)/2 -> -4 | J94: =(E94-F94)/2 -> 2 | K94: =MAX(1,MIN(10,ROUNDUP(I94+5,0))) -> 1 | L94: =MAX(1,MIN(10,ROUNDUP(5-J94,0))) -> 3 | M94: =MIN(E94,F94) -> 1 | N94: lexicon | O94: 0.38 | P94: 0 | T94: exciting (similar), fascinating (similar), entertaining (similar), holding (definition), attention (definition)
A95: welcome | B95: quality | C95: quality | D95: social | E95: 6 | F95: 1 | G95: 1 | H95: 9 | I95: =(G95-H95)/2 -> -4 | J95: =(E95-F95)/2 -> 2.5 | K95: =MAX(1,MIN(10,ROUNDUP(I95+5,0))) -> 1 | L95: =MAX(1,MIN(10,ROUNDUP(5-J95,0))) -> 3 | M95: =MIN(E95,F95) -> 1 | N95: lexicon | O95: 0.5 | P95: 0 | T95: wanted (similar), giving (definition), pleasure (definition), satisfaction (definition), receive (definition), acceptance (is-a), hospitality (kind-of)
A96: grand | B96: quality | C96: quality | D96: evaluative | E96: 5 | F96: 1 | G96: 1 | H96: 9 | I96: =(G96-H96)/2 -> -4 | J96: =(E96-F96)/2 -> 2 | K96: =MAX(1,MIN(10,ROUNDUP(I96+5,0))) -> 1 | L96: =MAX(1,MIN(10,ROUNDUP(5-J96,0))) -> 3 | M96: =MIN(E96,F96) -> 1 | N96: lexicon | O96: 0.33 | P96: 0.08 | Q96: expansive, heroic | T96: impressive (similar), behavior (definition), ambitious (definition), scale (definition), scope (definition), noble (similar)
A97: gay | B97: quality | C97: quality | D97: social | E97: 5 | F97: 1 | G97: 1 | H97: 9 | I97: =(G97-H97)/2 -> -4 | J97: =(E97-F97)/2 -> 2 | K97: =MAX(1,MIN(10,ROUNDUP(I97+5,0))) -> 1 | L97: =MAX(1,MIN(10,ROUNDUP(5-J97,0))) -> 3 | M97: =MIN(E97,F97) -> 1 | N97: lexicon | O97: 0.42 | P97: 0.04 | Q97: cheery, sunny | T97: bright (definition), pleasant (definition), promote (definition), feeling (definition) | V97: depressing
A98: effective | B98: quality | C98: quality | D98: evaluative | E98: 5 | F98: 1 | G98: 1 | H98: 9 | I98: =(G98-H98)/2 -> -4 | J98: =(E98-F98)/2 -> 2 | K98: =MAX(1,MIN(10,ROUNDUP(I98+5,0))) -> 1 | L98: =MAX(1,MIN(10,ROUNDUP(5-J98,0))) -> 3 | M98: =MIN(E98,F98) -> 1 | N98: lexicon | O98: 0.29 | P98: 0.04 | Q98: effectual, efficacious | T98: powerful (similar), useful (similar), efficient (similar), effect (derived), effectiveness (derived), produce (definition), capable (definition), intend (definition), result (definition)
A99: famous | B99: quality | C99: quality | D99: social | E99: 5 | F99: 1 | G99: 1 | H99: 9 | I99: =(G99-H99)/2 -> -4 | J99: =(E99-F99)/2 -> 2 | K99: =MAX(1,MIN(10,ROUNDUP(I99+5,0))) -> 1 | L99: =MAX(1,MIN(10,ROUNDUP(5-J99,0))) -> 3 | M99: =MIN(E99,F99) -> 1 | N99: lexicon | O99: 0.38 | P99: 0 | Q99: celebrated, famed, far-famed, illustrious, notable | T99: known (similar), fame (derived), know (definition), esteem (definition) | V99: unknown
A100: greatest | B100: quality | C100: quality | D100: evaluative | E100: 6 | F100: 1 | G100: 1 | H100: 9 | I100: =(G100-H100)/2 -> -4 | J100: =(E100-F100)/2 -> 2.5 | K100: =MAX(1,MIN(10,ROUNDUP(I100+5,0))) -> 1 | L100: =MAX(1,MIN(10,ROUNDUP(5-J100,0))) -> 3 | M100: =MIN(E100,F100) -> 1 | N100: lexicon | O100: 0.54 | P100: 0 | Q100: sterling, superlative | T100: superior (similar), high (definition), quality (definition), large (similar), big (similar), relatively (definition), size (definition) | V100: inferior, small, little
A101: dear | B101: quality | C101: quality | D101: social | E101: 5 | F101: 1 | G101: 1 | H101: 9 | I101: =(G101-H101)/2 -> -4 | J101: =(E101-F101)/2 -> 2 | K101: =MAX(1,MIN(10,ROUNDUP(I101+5,0))) -> 1 | L101: =MAX(1,MIN(10,ROUNDUP(5-J101,0))) -> 3 | M101: =MIN(E101,F101) -> 1 | N101: lexicon | O101: 0.33 | P101: 0 | Q101: beloved, darling | T101: loved (similar), love (definition), close (similar), intimate (definition), relationship (definition) | V101: distant
...

Sheet Connectors_nodes
A1: Word | B1: Group | C1: Relation | D1: Class | E1: V | F1: I | G1: Lv | H1: Gv | I1: x | J1: y | K1: Col | L1: Row | M1: τ | N1: Current construction | O1: Current axis | P1: Proposed axis | Q1: Compare | R1: Multi-word | S1: Ambiguous | T1: Note
A2: if | B2: contingency | C2: condition | D2: SC | E2: 9 | F2: 1 | G2: 3 | H2: 6 | I2: =(G2-H2)/2 -> -1.5 | J2: =(E2-F2)/2 -> 4 | K2: =MAX(1,MIN(10,ROUNDUP(I2+5,0))) -> 4 | L2: =MAX(1,MIN(10,ROUNDUP(5-J2,0))) -> 1 | M2: =MIN(E2,F2) -> 1 | N2: #8 | O2: North | P2: North · West | Q2: matches | T2: #8 CONDITIONAL
A3: so that | B3: contingency | C3: purpose | D3: SC | E3: 9 | F3: 1 | G3: 4 | H3: 6 | I3: =(G3-H3)/2 -> -1 | J3: =(E3-F3)/2 -> 4 | K3: =MAX(1,MIN(10,ROUNDUP(I3+5,0))) -> 4 | L3: =MAX(1,MIN(10,ROUNDUP(5-J3,0))) -> 1 | M3: =MIN(E3,F3) -> 1 | N3: #18 | O3: North | P3: North · West | Q3: matches | R3: yes | T3: #18 PURPOSE
A4: in order to | B4: contingency | C4: purpose | D4: SC | E4: 9 | F4: 1 | G4: 4 | H4: 6 | I4: =(G4-H4)/2 -> -1 | J4: =(E4-F4)/2 -> 4 | K4: =MAX(1,MIN(10,ROUNDUP(I4+5,0))) -> 4 | L4: =MAX(1,MIN(10,ROUNDUP(5-J4,0))) -> 1 | M4: =MIN(E4,F4) -> 1 | N4: #18 | O4: North | P4: North · West | Q4: matches | R4: yes | T4: #18 PURPOSE
A5: in order that | B5: contingency | C5: purpose | D5: SC | E5: 9 | F5: 1 | G5: 4 | H5: 6 | I5: =(G5-H5)/2 -> -1 | J5: =(E5-F5)/2 -> 4 | K5: =MAX(1,MIN(10,ROUNDUP(I5+5,0))) -> 4 | L5: =MAX(1,MIN(10,ROUNDUP(5-J5,0))) -> 1 | M5: =MIN(E5,F5) -> 1 | N5: #18 | O5: North | P5: North · West | Q5: matches | R5: yes | T5: #18 PURPOSE
A6: moreover | B6: expansion | C6: additive (we/us) | D6: CA | E6: 9 | F6: 1 | G6: 5 | H6: 5 | I6: =(G6-H6)/2 -> 0 | J6: =(E6-F6)/2 -> 4 | K6: =MAX(1,MIN(10,ROUNDUP(I6+5,0))) -> 5 | L6: =MAX(1,MIN(10,ROUNDUP(5-J6,0))) -> 1 | M6: =MIN(E6,F6) -> 1 | P6: North | Q6: no construction
A7: furthermore | B7: expansion | C7: additive (we/us) | D7: CA | E7: 9 | F7: 1 | G7: 5 | H7: 5 | I7: =(G7-H7)/2 -> 0 | J7: =(E7-F7)/2 -> 4 | K7: =MAX(1,MIN(10,ROUNDUP(I7+5,0))) -> 5 | L7: =MAX(1,MIN(10,ROUNDUP(5-J7,0))) -> 1 | M7: =MIN(E7,F7) -> 1 | P7: North | Q7: no construction
A8: besides | B8: expansion | C8: additive (we/us) | D8: CA | E8: 9 | F8: 1 | G8: 5 | H8: 5 | I8: =(G8-H8)/2 -> 0 | J8: =(E8-F8)/2 -> 4 | K8: =MAX(1,MIN(10,ROUNDUP(I8+5,0))) -> 5 | L8: =MAX(1,MIN(10,ROUNDUP(5-J8,0))) -> 1 | M8: =MIN(E8,F8) -> 1 | P8: North | Q8: no construction
A9: additionally | B9: expansion | C9: additive (we/us) | D9: CA | E9: 9 | F9: 1 | G9: 5 | H9: 5 | I9: =(G9-H9)/2 -> 0 | J9: =(E9-F9)/2 -> 4 | K9: =MAX(1,MIN(10,ROUNDUP(I9+5,0))) -> 5 | L9: =MAX(1,MIN(10,ROUNDUP(5-J9,0))) -> 1 | M9: =MIN(E9,F9) -> 1 | P9: North | Q9: no construction
A10: likewise | B10: expansion | C10: additive (we/us) | D10: CA | E10: 9 | F10: 1 | G10: 5 | H10: 5 | I10: =(G10-H10)/2 -> 0 | J10: =(E10-F10)/2 -> 4 | K10: =MAX(1,MIN(10,ROUNDUP(I10+5,0))) -> 5 | L10: =MAX(1,MIN(10,ROUNDUP(5-J10,0))) -> 1 | M10: =MIN(E10,F10) -> 1 | P10: North | Q10: no construction
A11: similarly | B11: expansion | C11: additive (we/us) | D11: CA | E11: 9 | F11: 1 | G11: 5 | H11: 5 | I11: =(G11-H11)/2 -> 0 | J11: =(E11-F11)/2 -> 4 | K11: =MAX(1,MIN(10,ROUNDUP(I11+5,0))) -> 5 | L11: =MAX(1,MIN(10,ROUNDUP(5-J11,0))) -> 1 | M11: =MIN(E11,F11) -> 1 | P11: North | Q11: no construction
A12: in addition | B12: expansion | C12: additive (we/us) | D12: TP | E12: 9 | F12: 1 | G12: 5 | H12: 5 | I12: =(G12-H12)/2 -> 0 | J12: =(E12-F12)/2 -> 4 | K12: =MAX(1,MIN(10,ROUNDUP(I12+5,0))) -> 5 | L12: =MAX(1,MIN(10,ROUNDUP(5-J12,0))) -> 1 | M12: =MIN(E12,F12) -> 1 | P12: North | Q12: no construction | R12: yes
A13: as well as | B13: expansion | C13: additive (we/us) | D13: TP | E13: 9 | F13: 1 | G13: 5 | H13: 5 | I13: =(G13-H13)/2 -> 0 | J13: =(E13-F13)/2 -> 4 | K13: =MAX(1,MIN(10,ROUNDUP(I13+5,0))) -> 5 | L13: =MAX(1,MIN(10,ROUNDUP(5-J13,0))) -> 1 | M13: =MIN(E13,F13) -> 1 | P13: North | Q13: no construction | R13: yes
A14: both…and | B14: expansion | C14: additive (we/us) | D14: CORR | E14: 9 | F14: 1 | G14: 5 | H14: 5 | I14: =(G14-H14)/2 -> 0 | J14: =(E14-F14)/2 -> 4 | K14: =MAX(1,MIN(10,ROUNDUP(I14+5,0))) -> 5 | L14: =MAX(1,MIN(10,ROUNDUP(5-J14,0))) -> 1 | M14: =MIN(E14,F14) -> 1 | P14: North | Q14: no construction | R14: yes
A15: if only | B15: contingency | C15: hypothetical | D15: SC | E15: 9 | F15: 1 | G15: 4 | H15: 5 | I15: =(G15-H15)/2 -> -0.5 | J15: =(E15-F15)/2 -> 4 | K15: =MAX(1,MIN(10,ROUNDUP(I15+5,0))) -> 5 | L15: =MAX(1,MIN(10,ROUNDUP(5-J15,0))) -> 1 | M15: =MIN(E15,F15) -> 1 | N15: #14 | O15: North | P15: North | Q15: matches | R15: yes | T15: #14 HYPOTHETICAL
A16: ? | B16: punctuation | C16: punctuation | D16: PUNCT | E16: 9 | F16: 1 | G16: 4 | H16: 5 | I16: =(G16-H16)/2 -> -0.5 | J16: =(E16-F16)/2 -> 4 | K16: =MAX(1,MIN(10,ROUNDUP(I16+5,0))) -> 5 | L16: =MAX(1,MIN(10,ROUNDUP(5-J16,0))) -> 1 | M16: =MIN(E16,F16) -> 1 | N16: #28 | O16: North | P16: North | Q16: matches | T16: question mark: opens possibility: up and centered (#28 DIRECT_Q)
A17: even if | B17: contingency | C17: condition | D17: SC | E17: 8 | F17: 2 | G17: 3 | H17: 7 | I17: =(G17-H17)/2 -> -2 | J17: =(E17-F17)/2 -> 3 | K17: =MAX(1,MIN(10,ROUNDUP(I17+5,0))) -> 3 | L17: =MAX(1,MIN(10,ROUNDUP(5-J17,0))) -> 2 | M17: =MIN(E17,F17) -> 2 | N17: #8 | O17: North | P17: North · West | Q17: matches | R17: yes
A18: provided (that) | B18: contingency | C18: condition | D18: SC | E18: 8 | F18: 2 | G18: 3 | H18: 7 | I18: =(G18-H18)/2 -> -2 | J18: =(E18-F18)/2 -> 3 | K18: =MAX(1,MIN(10,ROUNDUP(I18+5,0))) -> 3 | L18: =MAX(1,MIN(10,ROUNDUP(5-J18,0))) -> 2 | M18: =MIN(E18,F18) -> 2 | N18: #8 | O18: North | P18: North · West | Q18: matches | R18: yes
A19: providing | B19: contingency | C19: condition | D19: SC | E19: 8 | F19: 2 | G19: 3 | H19: 7 | I19: =(G19-H19)/2 -> -2 | J19: =(E19-F19)/2 -> 3 | K19: =MAX(1,MIN(10,ROUNDUP(I19+5,0))) -> 3 | L19: =MAX(1,MIN(10,ROUNDUP(5-J19,0))) -> 2 | M19: =MIN(E19,F19) -> 2 | N19: #8 | O19: North | P19: North · West | Q19: matches
A20: as long as | B20: contingency | C20: condition | D20: SC | E20: 8 | F20: 2 | G20: 3 | H20: 7 | I20: =(G20-H20)/2 -> -2 | J20: =(E20-F20)/2 -> 3 | K20: =MAX(1,MIN(10,ROUNDUP(I20+5,0))) -> 3 | L20: =MAX(1,MIN(10,ROUNDUP(5-J20,0))) -> 2 | M20: =MIN(E20,F20) -> 2 | N20: #8 | O20: North | P20: North · West | Q20: matches | R20: yes
A21: so long as | B21: contingency | C21: condition | D21: SC | E21: 8 | F21: 2 | G21: 3 | H21: 7 | I21: =(G21-H21)/2 -> -2 | J21: =(E21-F21)/2 -> 3 | K21: =MAX(1,MIN(10,ROUNDUP(I21+5,0))) -> 3 | L21: =MAX(1,MIN(10,ROUNDUP(5-J21,0))) -> 2 | M21: =MIN(E21,F21) -> 2 | N21: #8 | O21: North | P21: North · West | Q21: matches | R21: yes
A22: in case | B22: contingency | C22: condition | D22: SC | E22: 8 | F22: 2 | G22: 3 | H22: 7 | I22: =(G22-H22)/2 -> -2 | J22: =(E22-F22)/2 -> 3 | K22: =MAX(1,MIN(10,ROUNDUP(I22+5,0))) -> 3 | L22: =MAX(1,MIN(10,ROUNDUP(5-J22,0))) -> 2 | M22: =MIN(E22,F22) -> 2 | N22: #8 | O22: North | P22: North · West | Q22: matches | R22: yes
A23: on condition that | B23: contingency | C23: condition | D23: SC | E23: 8 | F23: 2 | G23: 3 | H23: 7 | I23: =(G23-H23)/2 -> -2 | J23: =(E23-F23)/2 -> 3 | K23: =MAX(1,MIN(10,ROUNDUP(I23+5,0))) -> 3 | L23: =MAX(1,MIN(10,ROUNDUP(5-J23,0))) -> 2 | M23: =MIN(E23,F23) -> 2 | N23: #8 | O23: North | P23: North · West | Q23: matches | R23: yes
A24: supposing | B24: contingency | C24: condition | D24: SC | E24: 8 | F24: 2 | G24: 3 | H24: 7 | I24: =(G24-H24)/2 -> -2 | J24: =(E24-F24)/2 -> 3 | K24: =MAX(1,MIN(10,ROUNDUP(I24+5,0))) -> 3 | L24: =MAX(1,MIN(10,ROUNDUP(5-J24,0))) -> 2 | M24: =MIN(E24,F24) -> 2 | N24: #8 | O24: North | P24: North · West | Q24: matches
A25: assuming | B25: contingency | C25: condition | D25: SC | E25: 8 | F25: 2 | G25: 3 | H25: 7 | I25: =(G25-H25)/2 -> -2 | J25: =(E25-F25)/2 -> 3 | K25: =MAX(1,MIN(10,ROUNDUP(I25+5,0))) -> 3 | L25: =MAX(1,MIN(10,ROUNDUP(5-J25,0))) -> 2 | M25: =MIN(E25,F25) -> 2 | N25: #8 | O25: North | P25: North · West | Q25: matches
A26: in a way | B26: expansion | C26: hedge / nuance | D26: TP | E26: 8 | F26: 2 | G26: 3 | H26: 5 | I26: =(G26-H26)/2 -> -1 | J26: =(E26-F26)/2 -> 3 | K26: =MAX(1,MIN(10,ROUNDUP(I26+5,0))) -> 4 | L26: =MAX(1,MIN(10,ROUNDUP(5-J26,0))) -> 2 | M26: =MIN(E26,F26) -> 2 | N26: #16 | O26: North | P26: North · West | Q26: matches | R26: yes | T26: #16 NUANCE
A27: sort of | B27: expansion | C27: hedge / nuance | D27: TP | E27: 8 | F27: 2 | G27: 3 | H27: 5 | I27: =(G27-H27)/2 -> -1 | J27: =(E27-F27)/2 -> 3 | K27: =MAX(1,MIN(10,ROUNDUP(I27+5,0))) -> 4 | L27: =MAX(1,MIN(10,ROUNDUP(5-J27,0))) -> 2 | M27: =MIN(E27,F27) -> 2 | N27: #16 | O27: North | P27: North · West | Q27: matches | R27: yes | T27: #16 NUANCE
A28: kind of | B28: expansion | C28: hedge / nuance | D28: TP | E28: 8 | F28: 2 | G28: 3 | H28: 5 | I28: =(G28-H28)/2 -> -1 | J28: =(E28-F28)/2 -> 3 | K28: =MAX(1,MIN(10,ROUNDUP(I28+5,0))) -> 4 | L28: =MAX(1,MIN(10,ROUNDUP(5-J28,0))) -> 2 | M28: =MIN(E28,F28) -> 2 | N28: #16 | O28: North | P28: North · West | Q28: matches | R28: yes | T28: #16 NUANCE
A29: somewhat | B29: expansion | C29: hedge / nuance | D29: TP | E29: 8 | F29: 2 | G29: 3 | H29: 5 | I29: =(G29-H29)/2 -> -1 | J29: =(E29-F29)/2 -> 3 | K29: =MAX(1,MIN(10,ROUNDUP(I29+5,0))) -> 4 | L29: =MAX(1,MIN(10,ROUNDUP(5-J29,0))) -> 2 | M29: =MIN(E29,F29) -> 2 | N29: #16 | O29: North | P29: North · West | Q29: matches | T29: #16 NUANCE
A30: a bit | B30: expansion | C30: hedge / nuance | D30: TP | E30: 8 | F30: 2 | G30: 3 | H30: 5 | I30: =(G30-H30)/2 -> -1 | J30: =(E30-F30)/2 -> 3 | K30: =MAX(1,MIN(10,ROUNDUP(I30+5,0))) -> 4 | L30: =MAX(1,MIN(10,ROUNDUP(5-J30,0))) -> 2 | M30: =MIN(E30,F30) -> 2 | N30: #16 | O30: North | P30: North · West | Q30: matches | R30: yes | T30: #16 NUANCE
A31: more or less | B31: expansion | C31: hedge / nuance | D31: TP | E31: 8 | F31: 2 | G31: 3 | H31: 5 | I31: =(G31-H31)/2 -> -1 | J31: =(E31-F31)/2 -> 3 | K31: =MAX(1,MIN(10,ROUNDUP(I31+5,0))) -> 4 | L31: =MAX(1,MIN(10,ROUNDUP(5-J31,0))) -> 2 | M31: =MIN(E31,F31) -> 2 | N31: #16 | O31: North | P31: North · West | Q31: matches | R31: yes | T31: #16 NUANCE
A32: as if | B32: comparison | C32: manner | D32: SC | E32: 8 | F32: 2 | G32: 3 | H32: 6 | I32: =(G32-H32)/2 -> -1.5 | J32: =(E32-F32)/2 -> 3 | K32: =MAX(1,MIN(10,ROUNDUP(I32+5,0))) -> 4 | L32: =MAX(1,MIN(10,ROUNDUP(5-J32,0))) -> 2 | M32: =MIN(E32,F32) -> 2 | N32: #22 | O32: North | P32: North · West | Q32: matches | R32: yes | T32: #22 MANNER
A33: as though | B33: comparison | C33: manner | D33: SC | E33: 8 | F33: 2 | G33: 3 | H33: 6 | I33: =(G33-H33)/2 -> -1.5 | J33: =(E33-F33)/2 -> 3 | K33: =MAX(1,MIN(10,ROUNDUP(I33+5,0))) -> 4 | L33: =MAX(1,MIN(10,ROUNDUP(5-J33,0))) -> 2 | M33: =MIN(E33,F33) -> 2 | N33: #22 | O33: North | P33: North · West | Q33: matches | R33: yes | T33: #22 MANNER
A34: like (manner) | B34: comparison | C34: manner | D34: SC | E34: 8 | F34: 2 | G34: 3 | H34: 6 | I34: =(G34-H34)/2 -> -1.5 | J34: =(E34-F34)/2 -> 3 | K34: =MAX(1,MIN(10,ROUNDUP(I34+5,0))) -> 4 | L34: =MAX(1,MIN(10,ROUNDUP(5-J34,0))) -> 2 | M34: =MIN(E34,F34) -> 2 | N34: #22 | O34: North | P34: North · West | Q34: matches | R34: yes | T34: #22 MANNER
A35: the way | B35: comparison | C35: manner | D35: SC | E35: 8 | F35: 2 | G35: 3 | H35: 6 | I35: =(G35-H35)/2 -> -1.5 | J35: =(E35-F35)/2 -> 3 | K35: =MAX(1,MIN(10,ROUNDUP(I35+5,0))) -> 4 | L35: =MAX(1,MIN(10,ROUNDUP(5-J35,0))) -> 2 | M35: =MIN(E35,F35) -> 2 | N35: #22 | O35: North | P35: North · West | Q35: matches | R35: yes | T35: #22 MANNER
A36: whether | B36: clauses | C36: complementizer (question) | D36: COMP | E36: 8 | F36: 2 | G36: 3 | H36: 6 | I36: =(G36-H36)/2 -> -1.5 | J36: =(E36-F36)/2 -> 3 | K36: =MAX(1,MIN(10,ROUNDUP(I36+5,0))) -> 4 | L36: =MAX(1,MIN(10,ROUNDUP(5-J36,0))) -> 2 | M36: =MIN(E36,F36) -> 2 | N36: #29 | O36: North | P36: North · West | Q36: matches | T36: #29 INDIRECT_Q
A37: if (complementizer) | B37: clauses | C37: complementizer (question) | D37: COMP | E37: 8 | F37: 2 | G37: 3 | H37: 6 | I37: =(G37-H37)/2 -> -1.5 | J37: =(E37-F37)/2 -> 3 | K37: =MAX(1,MIN(10,ROUNDUP(I37+5,0))) -> 4 | L37: =MAX(1,MIN(10,ROUNDUP(5-J37,0))) -> 2 | M37: =MIN(E37,F37) -> 2 | N37: #29 | O37: North | P37: North · West | Q37: matches | R37: yes | T37: #29 INDIRECT_Q
A38: fortunately | B38: clauses | C38: stance adjunct (+) | D38: STANCE | E38: 8 | F38: 1 | G38: 8 | H38: 2 | I38: =(G38-H38)/2 -> 3 | J38: =(E38-F38)/2 -> 3.5 | K38: =MAX(1,MIN(10,ROUNDUP(I38+5,0))) -> 8 | L38: =MAX(1,MIN(10,ROUNDUP(5-J38,0))) -> 2 | M38: =MIN(E38,F38) -> 1 | P38: North · East | Q38: no construction
A39: first | B39: temporal | C39: sequence (opens) | D39: CA | E39: 6 | F39: 2 | G39: 2 | H39: 8 | I39: =(G39-H39)/2 -> -3 | J39: =(E39-F39)/2 -> 2 | K39: =MAX(1,MIN(10,ROUNDUP(I39+5,0))) -> 2 | L39: =MAX(1,MIN(10,ROUNDUP(5-J39,0))) -> 3 | M39: =MIN(E39,F39) -> 2 | P39: North · West | Q39: no construction
A40: to begin with | B40: temporal | C40: sequence (opens) | D40: CA | E40: 6 | F40: 2 | G40: 2 | H40: 8 | I40: =(G40-H40)/2 -> -3 | J40: =(E40-F40)/2 -> 2 | K40: =MAX(1,MIN(10,ROUNDUP(I40+5,0))) -> 2 | L40: =MAX(1,MIN(10,ROUNDUP(5-J40,0))) -> 3 | M40: =MIN(E40,F40) -> 2 | P40: North · West | Q40: no construction | R40: yes
A41: that (complementizer) | B41: clauses | C41: complementizer (that) | D41: COMP | E41: 7 | F41: 2 | G41: 2 | H41: 8 | I41: =(G41-H41)/2 -> -3 | J41: =(E41-F41)/2 -> 2.5 | K41: =MAX(1,MIN(10,ROUNDUP(I41+5,0))) -> 2 | L41: =MAX(1,MIN(10,ROUNDUP(5-J41,0))) -> 3 | M41: =MIN(E41,F41) -> 2 | N41: #4 | O41: North | P41: North · West | Q41: matches | R41: yes | S41: yes | T41: that: relativo / completivo / demostrativo
A42: & | B42: punctuation | C42: punctuation | D42: PUNCT | E42: 6 | F42: 1 | G42: 2 | H42: 8 | I42: =(G42-H42)/2 -> -3 | J42: =(E42-F42)/2 -> 2.5 | K42: =MAX(1,MIN(10,ROUNDUP(I42+5,0))) -> 2 | L42: =MAX(1,MIN(10,ROUNDUP(5-J42,0))) -> 3 | M42: =MIN(E42,F42) -> 1 | P42: North · West | Q42: no construction | T42: ampersand: equivalent to and
A43: then | B43: temporal | C43: succession (adverb) | D43: CA | E43: 7 | F43: 2 | G43: 3 | H43: 7 | I43: =(G43-H43)/2 -> -2 | J43: =(E43-F43)/2 -> 2.5 | K43: =MAX(1,MIN(10,ROUNDUP(I43+5,0))) -> 3 | L43: =MAX(1,MIN(10,ROUNDUP(5-J43,0))) -> 3 | M43: =MIN(E43,F43) -> 2 | P43: North · West | Q43: no construction
A44: next | B44: temporal | C44: succession (adverb) | D44: CA | E44: 7 | F44: 2 | G44: 3 | H44: 7 | I44: =(G44-H44)/2 -> -2 | J44: =(E44-F44)/2 -> 2.5 | K44: =MAX(1,MIN(10,ROUNDUP(I44+5,0))) -> 3 | L44: =MAX(1,MIN(10,ROUNDUP(5-J44,0))) -> 3 | M44: =MIN(E44,F44) -> 2 | P44: North · West | Q44: no construction
A45: afterwards | B45: temporal | C45: succession (adverb) | D45: CA | E45: 7 | F45: 2 | G45: 3 | H45: 7 | I45: =(G45-H45)/2 -> -2 | J45: =(E45-F45)/2 -> 2.5 | K45: =MAX(1,MIN(10,ROUNDUP(I45+5,0))) -> 3 | L45: =MAX(1,MIN(10,ROUNDUP(5-J45,0))) -> 3 | M45: =MIN(E45,F45) -> 2 | P45: North · West | Q45: no construction
A46: later | B46: temporal | C46: succession (adverb) | D46: CA | E46: 7 | F46: 2 | G46: 3 | H46: 7 | I46: =(G46-H46)/2 -> -2 | J46: =(E46-F46)/2 -> 2.5 | K46: =MAX(1,MIN(10,ROUNDUP(I46+5,0))) -> 3 | L46: =MAX(1,MIN(10,ROUNDUP(5-J46,0))) -> 3 | M46: =MIN(E46,F46) -> 2 | P46: North · West | Q46: no construction
A47: subsequently | B47: temporal | C47: succession (adverb) | D47: CA | E47: 7 | F47: 2 | G47: 3 | H47: 7 | I47: =(G47-H47)/2 -> -2 | J47: =(E47-F47)/2 -> 2.5 | K47: =MAX(1,MIN(10,ROUNDUP(I47+5,0))) -> 3 | L47: =MAX(1,MIN(10,ROUNDUP(5-J47,0))) -> 3 | M47: =MIN(E47,F47) -> 2 | P47: North · West | Q47: no construction
A48: indeed | B48: expansion | C48: emphasis | D48: CA | E48: 6 | F48: 1 | G48: 9 | H48: 1 | I48: =(G48-H48)/2 -> 4 | J48: =(E48-F48)/2 -> 2.5 | K48: =MAX(1,MIN(10,ROUNDUP(I48+5,0))) -> 9 | L48: =MAX(1,MIN(10,ROUNDUP(5-J48,0))) -> 3 | M48: =MIN(E48,F48) -> 1 | P48: North · East | Q48: no construction
A49: in fact | B49: expansion | C49: emphasis | D49: CA | E49: 6 | F49: 1 | G49: 9 | H49: 1 | I49: =(G49-H49)/2 -> 4 | J49: =(E49-F49)/2 -> 2.5 | K49: =MAX(1,MIN(10,ROUNDUP(I49+5,0))) -> 9 | L49: =MAX(1,MIN(10,ROUNDUP(5-J49,0))) -> 3 | M49: =MIN(E49,F49) -> 1 | P49: North · East | Q49: no construction | R49: yes
A50: actually | B50: expansion | C50: emphasis | D50: CA | E50: 6 | F50: 1 | G50: 9 | H50: 1 | I50: =(G50-H50)/2 -> 4 | J50: =(E50-F50)/2 -> 2.5 | K50: =MAX(1,MIN(10,ROUNDUP(I50+5,0))) -> 9 | L50: =MAX(1,MIN(10,ROUNDUP(5-J50,0))) -> 3 | M50: =MIN(E50,F50) -> 1 | P50: North · East | Q50: no construction
A51: especially | B51: expansion | C51: emphasis | D51: CA | E51: 6 | F51: 1 | G51: 9 | H51: 1 | I51: =(G51-H51)/2 -> 4 | J51: =(E51-F51)/2 -> 2.5 | K51: =MAX(1,MIN(10,ROUNDUP(I51+5,0))) -> 9 | L51: =MAX(1,MIN(10,ROUNDUP(5-J51,0))) -> 3 | M51: =MIN(E51,F51) -> 1 | P51: North · East | Q51: no construction
A52: certainly | B52: expansion | C52: emphasis | D52: CA | E52: 6 | F52: 1 | G52: 9 | H52: 1 | I52: =(G52-H52)/2 -> 4 | J52: =(E52-F52)/2 -> 2.5 | K52: =MAX(1,MIN(10,ROUNDUP(I52+5,0))) -> 9 | L52: =MAX(1,MIN(10,ROUNDUP(5-J52,0))) -> 3 | M52: =MIN(E52,F52) -> 1 | P52: North · East | Q52: no construction
A53: as a matter of fact | B53: expansion | C53: emphasis | D53: TP | E53: 6 | F53: 1 | G53: 9 | H53: 1 | I53: =(G53-H53)/2 -> 4 | J53: =(E53-F53)/2 -> 2.5 | K53: =MAX(1,MIN(10,ROUNDUP(I53+5,0))) -> 9 | L53: =MAX(1,MIN(10,ROUNDUP(5-J53,0))) -> 3 | M53: =MIN(E53,F53) -> 1 | P53: North · East | Q53: no construction | R53: yes | T53: of course is also in AXIS_NORTH.affirmatives
A54: above all | B54: expansion | C54: emphasis | D54: TP | E54: 6 | F54: 1 | G54: 9 | H54: 1 | I54: =(G54-H54)/2 -> 4 | J54: =(E54-F54)/2 -> 2.5 | K54: =MAX(1,MIN(10,ROUNDUP(I54+5,0))) -> 9 | L54: =MAX(1,MIN(10,ROUNDUP(5-J54,0))) -> 3 | M54: =MIN(E54,F54) -> 1 | P54: North · East | Q54: no construction | R54: yes | T54: of course is also in AXIS_NORTH.affirmatives
A55: of course | B55: expansion | C55: emphasis | D55: TP | E55: 6 | F55: 1 | G55: 9 | H55: 1 | I55: =(G55-H55)/2 -> 4 | J55: =(E55-F55)/2 -> 2.5 | K55: =MAX(1,MIN(10,ROUNDUP(I55+5,0))) -> 9 | L55: =MAX(1,MIN(10,ROUNDUP(5-J55,0))) -> 3 | M55: =MIN(E55,F55) -> 1 | P55: North · East | Q55: no construction | R55: yes | T55: of course is also in AXIS_NORTH.affirmatives
A56: and | B56: expansion | C56: additive | D56: CC | E56: 3 | F56: 1 | G56: 2 | H56: 8 | I56: =(G56-H56)/2 -> -3 | J56: =(E56-F56)/2 -> 1 | K56: =MAX(1,MIN(10,ROUNDUP(I56+5,0))) -> 2 | L56: =MAX(1,MIN(10,ROUNDUP(5-J56,0))) -> 4 | M56: =MIN(E56,F56) -> 1 | N56: #5 | O56: West | P56: Present · West | Q56: matches | T56: #5 SIMPLE_CONNECTOR
A57: also | B57: expansion | C57: additive | D57: CC | E57: 3 | F57: 1 | G57: 2 | H57: 8 | I57: =(G57-H57)/2 -> -3 | J57: =(E57-F57)/2 -> 1 | K57: =MAX(1,MIN(10,ROUNDUP(I57+5,0))) -> 2 | L57: =MAX(1,MIN(10,ROUNDUP(5-J57,0))) -> 4 | M57: =MIN(E57,F57) -> 1 | N57: #5 | O57: West | P57: Present · West | Q57: matches | T57: #5 SIMPLE_CONNECTOR
A58: too | B58: expansion | C58: additive | D58: CC | E58: 3 | F58: 1 | G58: 2 | H58: 8 | I58: =(G58-H58)/2 -> -3 | J58: =(E58-F58)/2 -> 1 | K58: =MAX(1,MIN(10,ROUNDUP(I58+5,0))) -> 2 | L58: =MAX(1,MIN(10,ROUNDUP(5-J58,0))) -> 4 | M58: =MIN(E58,F58) -> 1 | N58: #5 | O58: West | P58: Present · West | Q58: matches | T58: #5 SIMPLE_CONNECTOR
A59: plus | B59: expansion | C59: additive | D59: CC | E59: 3 | F59: 1 | G59: 2 | H59: 8 | I59: =(G59-H59)/2 -> -3 | J59: =(E59-F59)/2 -> 1 | K59: =MAX(1,MIN(10,ROUNDUP(I59+5,0))) -> 2 | L59: =MAX(1,MIN(10,ROUNDUP(5-J59,0))) -> 4 | M59: =MIN(E59,F59) -> 1 | N59: #5 | O59: West | P59: Present · West | Q59: matches | T59: #5 SIMPLE_CONNECTOR
A60: by the way | B60: expansion | C60: topic shift | D60: TP | E60: 5 | F60: 3 | G60: 2 | H60: 8 | I60: =(G60-H60)/2 -> -3 | J60: =(E60-F60)/2 -> 1 | K60: =MAX(1,MIN(10,ROUNDUP(I60+5,0))) -> 2 | L60: =MAX(1,MIN(10,ROUNDUP(5-J60,0))) -> 4 | M60: =MIN(E60,F60) -> 3 | P60: Present · West | Q60: no construction | R60: yes
A61: incidentally | B61: expansion | C61: topic shift | D61: TP | E61: 5 | F61: 3 | G61: 2 | H61: 8 | I61: =(G61-H61)/2 -> -3 | J61: =(E61-F61)/2 -> 1 | K61: =MAX(1,MIN(10,ROUNDUP(I61+5,0))) -> 2 | L61: =MAX(1,MIN(10,ROUNDUP(5-J61,0))) -> 4 | M61: =MIN(E61,F61) -> 3 | P61: Present · West | Q61: no construction
A62: anyway | B62: expansion | C62: topic shift | D62: TP | E62: 5 | F62: 3 | G62: 2 | H62: 8 | I62: =(G62-H62)/2 -> -3 | J62: =(E62-F62)/2 -> 1 | K62: =MAX(1,MIN(10,ROUNDUP(I62+5,0))) -> 2 | L62: =MAX(1,MIN(10,ROUNDUP(5-J62,0))) -> 4 | M62: =MIN(E62,F62) -> 3 | P62: Present · West | Q62: no construction
A63: anyhow | B63: expansion | C63: topic shift | D63: TP | E63: 5 | F63: 3 | G63: 2 | H63: 8 | I63: =(G63-H63)/2 -> -3 | J63: =(E63-F63)/2 -> 1 | K63: =MAX(1,MIN(10,ROUNDUP(I63+5,0))) -> 2 | L63: =MAX(1,MIN(10,ROUNDUP(5-J63,0))) -> 4 | M63: =MIN(E63,F63) -> 3 | P63: Present · West | Q63: no construction
A64: as for | B64: expansion | C64: topic shift | D64: TP | E64: 5 | F64: 3 | G64: 2 | H64: 8 | I64: =(G64-H64)/2 -> -3 | J64: =(E64-F64)/2 -> 1 | K64: =MAX(1,MIN(10,ROUNDUP(I64+5,0))) -> 2 | L64: =MAX(1,MIN(10,ROUNDUP(5-J64,0))) -> 4 | M64: =MIN(E64,F64) -> 3 | P64: Present · West | Q64: no construction | R64: yes
A65: speaking of | B65: expansion | C65: topic shift | D65: TP | E65: 5 | F65: 3 | G65: 2 | H65: 8 | I65: =(G65-H65)/2 -> -3 | J65: =(E65-F65)/2 -> 1 | K65: =MAX(1,MIN(10,ROUNDUP(I65+5,0))) -> 2 | L65: =MAX(1,MIN(10,ROUNDUP(5-J65,0))) -> 4 | M65: =MIN(E65,F65) -> 3 | P65: Present · West | Q65: no construction | R65: yes
A66: regarding | B66: expansion | C66: topic shift | D66: TP | E66: 5 | F66: 3 | G66: 2 | H66: 8 | I66: =(G66-H66)/2 -> -3 | J66: =(E66-F66)/2 -> 1 | K66: =MAX(1,MIN(10,ROUNDUP(I66+5,0))) -> 2 | L66: =MAX(1,MIN(10,ROUNDUP(5-J66,0))) -> 4 | M66: =MIN(E66,F66) -> 3 | P66: Present · West | Q66: no construction
A67: with regard to | B67: expansion | C67: topic shift | D67: TP | E67: 5 | F67: 3 | G67: 2 | H67: 8 | I67: =(G67-H67)/2 -> -3 | J67: =(E67-F67)/2 -> 1 | K67: =MAX(1,MIN(10,ROUNDUP(I67+5,0))) -> 2 | L67: =MAX(1,MIN(10,ROUNDUP(5-J67,0))) -> 4 | M67: =MIN(E67,F67) -> 3 | P67: Present · West | Q67: no construction | R67: yes
A68: after | B68: temporal | C68: succession | D68: SC | E68: 5 | F68: 3 | G68: 2 | H68: 8 | I68: =(G68-H68)/2 -> -3 | J68: =(E68-F68)/2 -> 1 | K68: =MAX(1,MIN(10,ROUNDUP(I68+5,0))) -> 2 | L68: =MAX(1,MIN(10,ROUNDUP(5-J68,0))) -> 4 | M68: =MIN(E68,F68) -> 3 | N68: #10 | O68: West | P68: Present · West | Q68: matches
A69: once | B69: temporal | C69: succession | D69: SC | E69: 5 | F69: 3 | G69: 2 | H69: 8 | I69: =(G69-H69)/2 -> -3 | J69: =(E69-F69)/2 -> 1 | K69: =MAX(1,MIN(10,ROUNDUP(I69+5,0))) -> 2 | L69: =MAX(1,MIN(10,ROUNDUP(5-J69,0))) -> 4 | M69: =MIN(E69,F69) -> 3 | N69: #10 | O69: West | P69: Present · West | Q69: matches
A70: as soon as | B70: temporal | C70: succession | D70: SC | E70: 5 | F70: 3 | G70: 2 | H70: 8 | I70: =(G70-H70)/2 -> -3 | J70: =(E70-F70)/2 -> 1 | K70: =MAX(1,MIN(10,ROUNDUP(I70+5,0))) -> 2 | L70: =MAX(1,MIN(10,ROUNDUP(5-J70,0))) -> 4 | M70: =MIN(E70,F70) -> 3 | N70: #10 | O70: West | P70: Present · West | Q70: matches | R70: yes
A71: since (temporal) | B71: temporal | C71: succession | D71: SC | E71: 5 | F71: 3 | G71: 2 | H71: 8 | I71: =(G71-H71)/2 -> -3 | J71: =(E71-F71)/2 -> 1 | K71: =MAX(1,MIN(10,ROUNDUP(I71+5,0))) -> 2 | L71: =MAX(1,MIN(10,ROUNDUP(5-J71,0))) -> 4 | M71: =MIN(E71,F71) -> 3 | N71: #10 | O71: West | P71: Present · West | Q71: matches | R71: yes | S71: yes
A72: / | B72: punctuation | C72: punctuation | D72: PUNCT | E72: 5 | F72: 2 | G72: 2 | H72: 8 | I72: =(G72-H72)/2 -> -3 | J72: =(E72-F72)/2 -> 1.5 | K72: =MAX(1,MIN(10,ROUNDUP(I72+5,0))) -> 2 | L72: =MAX(1,MIN(10,ROUNDUP(5-J72,0))) -> 4 | M72: =MIN(E72,F72) -> 2 | P72: North · West | Q72: no construction | T72: slash: alternative (and/or)
A73: or | B73: expansion | C73: alternative | D73: CC | E73: 5 | F73: 3 | G73: 3 | H73: 7 | I73: =(G73-H73)/2 -> -2 | J73: =(E73-F73)/2 -> 1 | K73: =MAX(1,MIN(10,ROUNDUP(I73+5,0))) -> 3 | L73: =MAX(1,MIN(10,ROUNDUP(5-J73,0))) -> 4 | M73: =MIN(E73,F73) -> 3 | N73: #5 | O73: West | P73: Present · West | Q73: matches
A74: either…or | B74: expansion | C74: alternative | D74: CORR | E74: 5 | F74: 3 | G74: 3 | H74: 7 | I74: =(G74-H74)/2 -> -2 | J74: =(E74-F74)/2 -> 1 | K74: =MAX(1,MIN(10,ROUNDUP(I74+5,0))) -> 3 | L74: =MAX(1,MIN(10,ROUNDUP(5-J74,0))) -> 4 | M74: =MIN(E74,F74) -> 3 | P74: Present · West | Q74: no construction | R74: yes
A75: alternatively | B75: expansion | C75: alternative | D75: CA | E75: 5 | F75: 3 | G75: 3 | H75: 7 | I75: =(G75-H75)/2 -> -2 | J75: =(E75-F75)/2 -> 1 | K75: =MAX(1,MIN(10,ROUNDUP(I75+5,0))) -> 3 | L75: =MAX(1,MIN(10,ROUNDUP(5-J75,0))) -> 4 | M75: =MIN(E75,F75) -> 3 | P75: Present · West | Q75: no construction
A76: … | B76: punctuation | C76: punctuation | D76: PUNCT | E76: 5 | F76: 3 | G76: 3 | H76: 6 | I76: =(G76-H76)/2 -> -1.5 | J76: =(E76-F76)/2 -> 1 | K76: =MAX(1,MIN(10,ROUNDUP(I76+5,0))) -> 4 | L76: =MAX(1,MIN(10,ROUNDUP(5-J76,0))) -> 4 | M76: =MIN(E76,F76) -> 3 | P76: Present · West | Q76: no construction | R76: yes | T76: ellipsis: trailing-off phrase, doubt (like POSSIBILITY_DAMPENERS)
A77: for example | B77: expansion | C77: exemplification | D77: TP | E77: 4 | F77: 2 | G77: 7 | H77: 4 | I77: =(G77-H77)/2 -> 1.5 | J77: =(E77-F77)/2 -> 1 | K77: =MAX(1,MIN(10,ROUNDUP(I77+5,0))) -> 7 | L77: =MAX(1,MIN(10,ROUNDUP(5-J77,0))) -> 4 | M77: =MIN(E77,F77) -> 2 | P77: Present · East | Q77: no construction | R77: yes
A78: for instance | B78: expansion | C78: exemplification | D78: TP | E78: 4 | F78: 2 | G78: 7 | H78: 4 | I78: =(G78-H78)/2 -> 1.5 | J78: =(E78-F78)/2 -> 1 | K78: =MAX(1,MIN(10,ROUNDUP(I78+5,0))) -> 7 | L78: =MAX(1,MIN(10,ROUNDUP(5-J78,0))) -> 4 | M78: =MIN(E78,F78) -> 2 | P78: Present · East | Q78: no construction | R78: yes
A79: such as | B79: expansion | C79: exemplification | D79: TP | E79: 4 | F79: 2 | G79: 7 | H79: 4 | I79: =(G79-H79)/2 -> 1.5 | J79: =(E79-F79)/2 -> 1 | K79: =MAX(1,MIN(10,ROUNDUP(I79+5,0))) -> 7 | L79: =MAX(1,MIN(10,ROUNDUP(5-J79,0))) -> 4 | M79: =MIN(E79,F79) -> 2 | P79: Present · East | Q79: no construction | R79: yes
A80: including | B80: expansion | C80: exemplification | D80: TP | E80: 4 | F80: 2 | G80: 7 | H80: 4 | I80: =(G80-H80)/2 -> 1.5 | J80: =(E80-F80)/2 -> 1 | K80: =MAX(1,MIN(10,ROUNDUP(I80+5,0))) -> 7 | L80: =MAX(1,MIN(10,ROUNDUP(5-J80,0))) -> 4 | M80: =MIN(E80,F80) -> 2 | P80: Present · East | Q80: no construction
A81: e.g. | B81: expansion | C81: exemplification | D81: TP | E81: 4 | F81: 2 | G81: 7 | H81: 4 | I81: =(G81-H81)/2 -> 1.5 | J81: =(E81-F81)/2 -> 1 | K81: =MAX(1,MIN(10,ROUNDUP(I81+5,0))) -> 7 | L81: =MAX(1,MIN(10,ROUNDUP(5-J81,0))) -> 4 | M81: =MIN(E81,F81) -> 2 | P81: Present · East | Q81: no construction
A82: in particular | B82: expansion | C82: exemplification | D82: TP | E82: 4 | F82: 2 | G82: 7 | H82: 4 | I82: =(G82-H82)/2 -> 1.5 | J82: =(E82-F82)/2 -> 1 | K82: =MAX(1,MIN(10,ROUNDUP(I82+5,0))) -> 7 | L82: =MAX(1,MIN(10,ROUNDUP(5-J82,0))) -> 4 | M82: =MIN(E82,F82) -> 2 | P82: Present · East | Q82: no construction | R82: yes
A83: specifically | B83: expansion | C83: exemplification | D83: TP | E83: 4 | F83: 2 | G83: 7 | H83: 4 | I83: =(G83-H83)/2 -> 1.5 | J83: =(E83-F83)/2 -> 1 | K83: =MAX(1,MIN(10,ROUNDUP(I83+5,0))) -> 7 | L83: =MAX(1,MIN(10,ROUNDUP(5-J83,0))) -> 4 | M83: =MIN(E83,F83) -> 2 | P83: Present · East | Q83: no construction
A84: namely | B84: expansion | C84: exemplification | D84: TP | E84: 4 | F84: 2 | G84: 7 | H84: 4 | I84: =(G84-H84)/2 -> 1.5 | J84: =(E84-F84)/2 -> 1 | K84: =MAX(1,MIN(10,ROUNDUP(I84+5,0))) -> 7 | L84: =MAX(1,MIN(10,ROUNDUP(5-J84,0))) -> 4 | M84: =MIN(E84,F84) -> 2 | P84: Present · East | Q84: no construction
A85: frankly | B85: clauses | C85: stance adjunct | D85: STANCE | E85: 5 | F85: 2 | G85: 8 | H85: 2 | I85: =(G85-H85)/2 -> 3 | J85: =(E85-F85)/2 -> 1.5 | K85: =MAX(1,MIN(10,ROUNDUP(I85+5,0))) -> 8 | L85: =MAX(1,MIN(10,ROUNDUP(5-J85,0))) -> 4 | M85: =MIN(E85,F85) -> 2 | P85: North · East | Q85: no construction
A86: honestly | B86: clauses | C86: stance adjunct | D86: STANCE | E86: 5 | F86: 2 | G86: 8 | H86: 2 | I86: =(G86-H86)/2 -> 3 | J86: =(E86-F86)/2 -> 1.5 | K86: =MAX(1,MIN(10,ROUNDUP(I86+5,0))) -> 8 | L86: =MAX(1,MIN(10,ROUNDUP(5-J86,0))) -> 4 | M86: =MIN(E86,F86) -> 2 | P86: North · East | Q86: no construction
A87: clearly | B87: clauses | C87: stance adjunct | D87: STANCE | E87: 5 | F87: 2 | G87: 8 | H87: 2 | I87: =(G87-H87)/2 -> 3 | J87: =(E87-F87)/2 -> 1.5 | K87: =MAX(1,MIN(10,ROUNDUP(I87+5,0))) -> 8 | L87: =MAX(1,MIN(10,ROUNDUP(5-J87,0))) -> 4 | M87: =MIN(E87,F87) -> 2 | P87: North · East | Q87: no construction
A88: obviously | B88: clauses | C88: stance adjunct | D88: STANCE | E88: 5 | F88: 2 | G88: 8 | H88: 2 | I88: =(G88-H88)/2 -> 3 | J88: =(E88-F88)/2 -> 1.5 | K88: =MAX(1,MIN(10,ROUNDUP(I88+5,0))) -> 8 | L88: =MAX(1,MIN(10,ROUNDUP(5-J88,0))) -> 4 | M88: =MIN(E88,F88) -> 2 | P88: North · East | Q88: no construction
A89: apparently | B89: clauses | C89: stance adjunct | D89: STANCE | E89: 5 | F89: 2 | G89: 8 | H89: 2 | I89: =(G89-H89)/2 -> 3 | J89: =(E89-F89)/2 -> 1.5 | K89: =MAX(1,MIN(10,ROUNDUP(I89+5,0))) -> 8 | L89: =MAX(1,MIN(10,ROUNDUP(5-J89,0))) -> 4 | M89: =MIN(E89,F89) -> 2 | P89: North · East | Q89: no construction
A90: surprisingly | B90: clauses | C90: stance adjunct | D90: STANCE | E90: 5 | F90: 2 | G90: 8 | H90: 2 | I90: =(G90-H90)/2 -> 3 | J90: =(E90-F90)/2 -> 1.5 | K90: =MAX(1,MIN(10,ROUNDUP(I90+5,0))) -> 8 | L90: =MAX(1,MIN(10,ROUNDUP(5-J90,0))) -> 4 | M90: =MIN(E90,F90) -> 2 | P90: North · East | Q90: no construction
A91: " " | B91: punctuation | C91: punctuation | D91: PUNCT | E91: 4 | F91: 3 | G91: 1 | H91: 9 | I91: =(G91-H91)/2 -> -4 | J91: =(E91-F91)/2 -> 0.5 | K91: =MAX(1,MIN(10,ROUNDUP(I91+5,0))) -> 1 | L91: =MAX(1,MIN(10,ROUNDUP(5-J91,0))) -> 5 | M91: =MIN(E91,F91) -> 3 | P91: Present · West | Q91: no construction | T91: quotation marks: another person's direct speech (You); clashes with marker_parser (emotion)
A92: in other words | B92: expansion | C92: clarification | D92: TP | E92: 4 | F92: 3 | G92: 2 | H92: 8 | I92: =(G92-H92)/2 -> -3 | J92: =(E92-F92)/2 -> 0.5 | K92: =MAX(1,MIN(10,ROUNDUP(I92+5,0))) -> 2 | L92: =MAX(1,MIN(10,ROUNDUP(5-J92,0))) -> 5 | M92: =MIN(E92,F92) -> 3 | N92: #15, #11 | O92: South/West | P92: Present · West | Q92: matches | R92: yes
A93: that is | B93: expansion | C93: clarification | D93: TP | E93: 4 | F93: 3 | G93: 2 | H93: 8 | I93: =(G93-H93)/2 -> -3 | J93: =(E93-F93)/2 -> 0.5 | K93: =MAX(1,MIN(10,ROUNDUP(I93+5,0))) -> 2 | L93: =MAX(1,MIN(10,ROUNDUP(5-J93,0))) -> 5 | M93: =MIN(E93,F93) -> 3 | N93: #15, #11 | O93: South/West | P93: Present · West | Q93: matches | R93: yes
A94: i.e. | B94: expansion | C94: clarification | D94: TP | E94: 4 | F94: 3 | G94: 2 | H94: 8 | I94: =(G94-H94)/2 -> -3 | J94: =(E94-F94)/2 -> 0.5 | K94: =MAX(1,MIN(10,ROUNDUP(I94+5,0))) -> 2 | L94: =MAX(1,MIN(10,ROUNDUP(5-J94,0))) -> 5 | M94: =MIN(E94,F94) -> 3 | N94: #15, #11 | O94: South/West | P94: Present · West | Q94: matches
A95: to put it another way | B95: expansion | C95: clarification | D95: TP | E95: 4 | F95: 3 | G95: 2 | H95: 8 | I95: =(G95-H95)/2 -> -3 | J95: =(E95-F95)/2 -> 0.5 | K95: =MAX(1,MIN(10,ROUNDUP(I95+5,0))) -> 2 | L95: =MAX(1,MIN(10,ROUNDUP(5-J95,0))) -> 5 | M95: =MIN(E95,F95) -> 3 | N95: #15, #11 | O95: South/West | P95: Present · West | Q95: matches | R95: yes
A96: although | B96: comparison | C96: concession | D96: SC | E96: 4 | F96: 4 | G96: 2 | H96: 8 | I96: =(G96-H96)/2 -> -3 | J96: =(E96-F96)/2 -> 0 | K96: =MAX(1,MIN(10,ROUNDUP(I96+5,0))) -> 2 | L96: =MAX(1,MIN(10,ROUNDUP(5-J96,0))) -> 5 | M96: =MIN(E96,F96) -> 4 | N96: #9 | O96: West | P96: Present · West | Q96: matches | T96: #9 CONCESSIVE
A97: even though | B97: comparison | C97: concession | D97: SC | E97: 4 | F97: 4 | G97: 2 | H97: 8 | I97: =(G97-H97)/2 -> -3 | J97: =(E97-F97)/2 -> 0 | K97: =MAX(1,MIN(10,ROUNDUP(I97+5,0))) -> 2 | L97: =MAX(1,MIN(10,ROUNDUP(5-J97,0))) -> 5 | M97: =MIN(E97,F97) -> 4 | N97: #9 | O97: West | P97: Present · West | Q97: matches | R97: yes | T97: #9 CONCESSIVE
A98: albeit | B98: comparison | C98: concession | D98: SC | E98: 4 | F98: 4 | G98: 2 | H98: 8 | I98: =(G98-H98)/2 -> -3 | J98: =(E98-F98)/2 -> 0 | K98: =MAX(1,MIN(10,ROUNDUP(I98+5,0))) -> 2 | L98: =MAX(1,MIN(10,ROUNDUP(5-J98,0))) -> 5 | M98: =MIN(E98,F98) -> 4 | N98: #9 | O98: West | P98: Present · West | Q98: matches | T98: #9 CONCESSIVE
A99: despite | B99: comparison | C99: concession | D99: SC | E99: 4 | F99: 4 | G99: 2 | H99: 8 | I99: =(G99-H99)/2 -> -3 | J99: =(E99-F99)/2 -> 0 | K99: =MAX(1,MIN(10,ROUNDUP(I99+5,0))) -> 2 | L99: =MAX(1,MIN(10,ROUNDUP(5-J99,0))) -> 5 | M99: =MIN(E99,F99) -> 4 | N99: #9 | O99: West | P99: Present · West | Q99: matches | T99: #9 CONCESSIVE
A100: in spite of | B100: comparison | C100: concession | D100: SC | E100: 4 | F100: 4 | G100: 2 | H100: 8 | I100: =(G100-H100)/2 -> -3 | J100: =(E100-F100)/2 -> 0 | K100: =MAX(1,MIN(10,ROUNDUP(I100+5,0))) -> 2 | L100: =MAX(1,MIN(10,ROUNDUP(5-J100,0))) -> 5 | M100: =MIN(E100,F100) -> 4 | N100: #9 | O100: West | P100: Present · West | Q100: matches | R100: yes | T100: #9 CONCESSIVE
...

Sheet Weight_rules
A1: Default weights (blue = design assumption, editable in build_tables.py). They are ADDED in this order: type → category → subtype → per-axis lists → valence → concept.
A3: Level 1 — node type
A4: Type | B4: V | C4: I | D4: Lv | E4: Gv | F4: Reason
A5: biological | B5: 6 | C5: 1 | D5: 4 | E5: 7 | F5: alive: up and toward Adaptation (NW quadrant)
A6: non_biological | B6: 2 | C6: 4 | D6: 6 | E6: 3 | F6: inert: down and toward Imposition (SE quadrant)
A7: action | B7: 4 | C7: 2 | D7: 7 | E7: 3 | F7: sensory: toward Imposition
A8: quality | B8: 3 | C8: 1 | D8: 3 | E8: 7 | F8: structural: toward Adaptation
A10: Level 2 — category (adjustment)
A11: Category | B11: ΔV | C11: ΔI | D11: ΔLv | E11: ΔGv
A12: person | B12: 1 | C12: 0 | D12: -1 | E12: 1
A13: animal | B13: 0 | C13: 1 | D13: -1 | E13: 1
A14: plant | B14: 0 | C14: 0 | D14: 1 | E14: -2
A15: body_part | B15: -1 | C15: 1 | D15: 4 | E15: -4
A16: group | B16: 0 | C16: 1 | D16: -1 | E16: 1
A17: object | B17: 0 | C17: 0 | D17: 2 | E17: -1
A18: substance | B18: 0 | C18: 1 | D18: 2 | E18: -1
A19: food | B19: 3 | C19: -3 | D19: 2 | E19: -1
A20: place | B20: 1 | C20: 0 | D20: 0 | E20: 1
A21: weather | B21: 0 | C21: 2 | D21: 1 | E21: 0
A22: time | B22: 0 | C22: 2 | D22: -4 | E22: 3
A23: communication | B23: 3 | C23: -1 | D23: -2 | E23: 5
... A36: emotion | B36: 1 | C36: -3 | D36: 2 | E36: -1
A38: Level 3 — subtype (adjustment)
A39: Category | B39: Subtype | C39: ΔV | D39: ΔI | E39: ΔLv | F39: ΔGv
A40: action | B40: communication | C40: 1 | D40: 0 | E40: -3 | F40: 5
A41: action | B41: social | C41: 1 | D41: 0 | E41: -2 | F41: 5
A42: action | B42: cognition | C42: 1 | D42: 0 | E42: -4 | F42: 5
A43: action | B43: possession | C43: 0 | D43: 1 | E43: -3 | F43: 3
A44: action | B44: stative | C44: 0 | D44: 1 | E44: -4 | F44: 3
A45: action | B45: motion | C45: 1 | D45: 0 | E45: 1 | F45: -1
A46: action | B46: contact | C46: 0 | D46: 1 | E46: 2 | F46: -1
A47: action | B47: perception | C47: 0 | D47: 0 | E47: 3 | F47: -2
A48: action | B48: creation | C48: 2 | D48: -1 | E48: -1 | F48: 2
A49: action | B49: emotion | C49: 0 | D49: 0 | E49: 1 | F49: 1
A50: action | B50: competition | C50: 0 | D50: 2 | E50: 0 | F50: 0
A51: action | B51: consumption | C51: 1 | D51: 0 | E51: 2 | F51: -1
... A83: place | B83: landform | C83: 0 | D83: 1 | E83: 1 | F83: -1
A85: Hand-made concept — intrinsic emotion (adjustment)
A86: Emotion | B86: ΔV | C86: ΔI | D86: ΔLv | E86: ΔGv
A87: joy | B87: 3 | C87: 0 | D87: 0 | E87: 0
A88: warmth | B88: 3 | C88: 0 | D88: 0 | E88: 1
A89: pride | B89: 2 | C89: 0 | D89: 2 | E89: 0
A90: awe | B90: 1 | C90: 1 | D90: 1 | E90: 0
A91: anger | B91: -1 | C91: 3 | D91: 2 | E91: 0
A92: fear | B92: -1 | C92: 4 | D92: 0 | E92: 0
A93: sadness | B93: -1 | C93: 3 | D93: 0 | E93: 0
A94: shame | B94: -1 | C94: 2 | D94: 0 | E94: 1
A95: meta | B95: 0 | C95: 0 | D95: 0 | E95: 0
A97: Hand-made concept — state subtype (adjustment)
A98: Subtype | B98: ΔV | C98: ΔI | D98: ΔLv | E98: ΔGv
A99: threat | B99: -1 | C99: 4 | D99: 0 | E99: 0
A100: safety | B100: 4 | C100: -1 | D100: 0 | E100: 0
A101: social | B101: 0 | C101: 0 | D101: -1 | E101: 3
A102: judgment | B102: 0 | C102: 0 | D102: -2 | E102: 4
A103: physical | B103: 0 | C103: 0 | D103: 3 | E103: -1
A104: condition | B104: 0 | C104: 1 | D104: 0 | E104: 1
A105: emotional | B105: 0 | C105: 0 | D105: 2 | E105: 0
A107: Other adjustments
A108: Rule | B108: ΔV | C108: ΔI | D108: ΔLv | E108: ΔGv
A109: intrinsic danger (violence, hazard, weapon…) | B109: -2 | C109: 4 | D109: 0 | E109: 0
A110: has a sensory channel (sight, hearing) | B110: 0 | C110: 0 | D110: 2 | E110: -1
A111: illogical (occurrences) | B111: -2 | C111: 4 | D111: 1 | E111: 0
A112: tone (voice, volume) | B112: 0 | C112: 0 | D112: 4 | E112: -2
A113: music | B113: 2 | C113: 0 | D113: 3 | E113: 0
A114: North 'concepts' list (hope, plan, dream…) | B114: 3 | C114: -1 | D114: 0 | E114: 0
A115: South 'concepts' list (failure, past, history…) | B115: -1 | C115: 3 | D115: 0 | E115: 0
A117: WordNet lineage — people (the first group wins; adjustment)
A118: Group (lemma examples) | B118: ΔV | C118: ΔI | D118: ΔLv | E118: ΔGv
A119: adversary, bad_person, criminal, enemy, killer … | B119: -2 | C119: 3 | D119: 2 | E119: -2
A120: administrator, athlete, boss, capitalist, contestant … | B120: 0 | C120: 0 | D120: 3 | E120: -3
A121: ancestor, associate, child, domestic_partner, friend … | B121: 2 | C121: 0 | D121: -2 | E121: 2
A122: communicator, creator, educator, entertainer, expert … | B122: 1 | C122: 0 | D122: -1 | E122: 2
A123: unfortunate … | B123: -1 | C123: 2 | D123: 0 | E123: 1
A124: imaginary_being, spiritual_being … | B124: 0 | C124: 2 | D124: 2 | E124: 0
A126: WordNet lineage — animals (adjustment)
A127: Group | B127: ΔV | C127: ΔI | D127: ΔLv | E127: ΔGv
A128: domestic_animal | B128: 1 | C128: 0 | D128: 0 | E128: 1
A129: big_cat, bird_of_prey, carnivore, predator | B129: -1 | C129: 2 | D129: 2 | E129: -1
A131: Connectors — base weight per relation (V, I, Lv, Gv)
A132: Relation | B132: Group | C132: V | D132: I | E132: Lv | F132: Gv
A133: additive (we/us) | B133: expansion | C133: 9 | D133: 1 | E133: 5 | F133: 5
A134: additive | B134: expansion | C134: 3 | D134: 1 | E134: 2 | F134: 8
A135: alternative | B135: expansion | C135: 5 | D135: 3 | E135: 3 | F135: 7
A136: alternative (substitution) | B136: expansion | C136: 3 | D136: 6 | E136: 3 | F136: 7
A137: negative alternative | B137: expansion | C137: 0 | D137: 9 | E137: 4 | F137: 6
A138: exception | B138: expansion | C138: 1 | D138: 8 | E138: 3 | F138: 6
A139: exemplification | B139: expansion | C139: 4 | D139: 2 | E139: 7 | F139: 4
A140: clarification | B140: expansion | C140: 4 | D140: 3 | E140: 2 | F140: 8
A141: clarification (speaker) | B141: expansion | C141: 2 | D141: 6 | E141: 6 | F141: 3
A142: emphasis | B142: expansion | C142: 6 | D142: 1 | E142: 9 | F142: 1
A143: hedge / nuance | B143: expansion | C143: 8 | D143: 2 | E143: 3 | F143: 5
A144: topic shift | B144: expansion | C144: 5 | D144: 3 | E144: 2 | F144: 8
... A173: stance adjunct (−) | B173: clauses | C173: 1 | D173: 8 | E173: 8 | F173: 2
A175: Pronouns (fixed weights)
A176: Axis | B176: Words | C176: V | D176: I | E176: Lv | F176: Gv
A177: Context (We) | B177: we, us, our, ours, ourselves | C177: 10 | D177: 0 | E177: 5 | F177: 5
A178: Imposition (I) | B178: i, me, my, mine, myself | C178: 6 | D178: 2 | E178: 10 | F178: 0
A179: Adaptation (You) | B179: you, your, yours, yourself | C179: 6 | D179: 2 | E179: 0 | F179: 10
A180: World (That) | B180: that, it, those, itself | C180: 0 | D180: 10 | E180: 5 | F180: 5
A181: They (3rd person) | B181: he, she, they, him, her, his, hers, their, theirs, them, himself, herself, themselves | C181: 7 | D181: 2 | E181: 3 | F181: 7
...
